Workbook

Sheet Cover
A1: 智擎集团 · 集团财务分析模型
A2: 虚构大模型集团（参考智谱商业模式）| Python+openpyxl 全公式生成 | 单位：万元
A4: 导航 | B4: 说明
A5: Meta | B5: 数据层宽表——全模型唯一取数源，日常只改 G 列
A6: Assumptions | B6: 指标视图层——全部实时取自 Meta（SUMIFS）
A7: Capex_Dep | B7: GPU 资本开支与折旧引擎（批次法）
A8: Cloud_IS | B8: 智擎云 · MaaS（单体全量）
A9: Ind_IS | B9: 智擎行业 · 私有化+解决方案
A10: Toc_IS | B10: 智擎互联 · C端（母持 80%）
A11: HoldCo_IS | B11: 智擎研究院 · 全量三表（关联收入方）
A12: IC_Register | B12: 内部交易登记簿（T1/T2/T3）
A13: IC_Recon | B13: 关联方对账矩阵 + cut-off 在途调节
A14: Eliminations | B14: 合并抵消分录底稿（E0-E3）
A15: Consol_IS | B15: 合并三表（Σ单体−抵消）
... A19: Checks | B19: 勾稽自检面板：8 组断言全绿才可信
A21: 集团速览（合并口径） | B21: 2023 | C21: 2024 | D21: 2025 | E21: 2026 | F21: 2027
A22: 营业收入 | B22: =Consol_IS!C6 | C22: =Consol_IS!D6 | D22: =Consol_IS!E6 | E22: =Consol_IS!F6 | F22: =Consol_IS!G6
A23: 净利润 | B23: =Consol_IS!C16 | C23: =Consol_IS!D16 | D23: =Consol_IS!E16 | E23: =Consol_IS!F16 | F23: =Consol_IS!G16
A24: 归母净利润 | B24: =Consol_IS!C18 | C24: =Consol_IS!D18 | D24: =Consol_IS!E18 | E24: =Consol_IS!F18 | F24: =Consol_IS!G18
A25: 期末现金 | B25: =Consol_BS!C4 | C25: =Consol_BS!D4 | D25: =Consol_BS!E4 | E25: =Consol_BS!F4 | F25: =Consol_BS!G4
A26: GPU 净值 | B26: =Consol_BS!C6 | C26: =Consol_BS!D6 | D26: =Consol_BS!E6 | E26: =Consol_BS!F6 | F26: =Consol_BS!G6
A28: 勾稽总检灯 → | B28: =IF(Checks!C34="","",Checks!C34)

Sheet Meta
A1: Meta · 数据层宽表（全模型唯一取数源）
A2: 字段：主体/业务线/地区/期间/场景(A实际·B预算)/指标/值/来源/备注 | 日常=按期灌数与维护来源；引擎与公式零改动
A3: entity | B3: segment | C3: region | D3: period | E3: scenario | F3: metric | G3: value | H3: source | I3: note
A4: GROUP | D4: 2023 | E4: ACTUAL | F4: tax_rate | G4: 0.15 | H4: 假设初始化 | I4: 所得税率
A5: GROUP | D5: 2023 | E5: ACTUAL | F5: dso_days | G5: 60 | H5: 假设初始化 | I5: 应收账期（天）
A6: GROUP | D6: 2023 | E6: ACTUAL | F6: dpo_days | G6: 45 | H6: 假设初始化 | I6: 应付账期（天）
A7: GROUP | D7: 2023 | E7: ACTUAL | F7: ic_days | G7: 60 | H7: 假设初始化 | I7: 内部往来账期（天）
A8: GROUP | D8: 2023 | E8: ACTUAL | F8: wacc | G8: 0.1 | H8: 假设初始化 | I8: WACC
A9: GROUP | C9: 华东 | D9: 2023 | E9: ACTUAL | F9: region_mix | G9: 0.35 | H9: 行业研究 | I9: 收入地区占比
A10: GROUP | C10: 华北 | D10: 2023 | E10: ACTUAL | F10: region_mix | G10: 0.3 | H10: 行业研究 | I10: 收入地区占比
A11: GROUP | C11: 华南 | D11: 2023 | E11: ACTUAL | F11: region_mix | G11: 0.2 | H11: 行业研究 | I11: 收入地区占比
A12: GROUP | C12: 海外 | D12: 2023 | E12: ACTUAL | F12: region_mix | G12: 0.15 | H12: 行业研究 | I12: 收入地区占比
A13: CLOUD | D13: 2023 | E13: ACTUAL | F13: token_volume_day | G13: 30 | H13: 假设初始化 | I13: 日均 token 消耗（B/day）
A14: CLOUD | D14: 2023 | E14: ACTUAL | F14: api_price | G14: 5.5 | H14: 假设初始化 | I14: 综合单价（元/M tokens）
A15: CLOUD | D15: 2023 | E15: ACTUAL | F15: inference_ucost | G15: 2.5 | H15: 假设初始化 | I15: 推理单位成本（元/M tok）
A16: CLOUD | D16: 2023 | E16: ACTUAL | F16: bandwidth_fee | G16: 300 | H16: 假设初始化 | I16: 带宽机房费用（万）
A17: CLOUD | D17: 2023 | E17: ACTUAL | F17: customers | G17: 800 | H17: 假设初始化 | I17: 付费客户数（家）
A18: CLOUD | D18: 2023 | E18: ACTUAL | F18: churn_m | G18: 0.012 | H18: 假设初始化 | I18: 月流失率
A19: IND | D19: 2023 | E19: ACTUAL | F19: projects_pvt | G19: 8 | H19: 假设初始化 | I19: 私有化项目数（个）
A20: IND | D20: 2023 | E20: ACTUAL | F20: avg_contract | G20: 1000 | H20: 假设初始化 | I20: 平均合同额（万）
A21: IND | D21: 2023 | E21: ACTUAL | F21: subscribers_sol | G21: 12 | H21: 假设初始化 | I21: 解决方案签约客户（累计）
A22: IND | D22: 2023 | E22: ACTUAL | F22: sub_fee | G22: 100 | H22: 假设初始化 | I22: 解决方案年费（万）
A23: IND | D23: 2023 | E23: ACTUAL | F23: cogs_rate_pvt | G23: 0.61 | H23: 假设初始化 | I23: 私有化成本率
A24: IND | D24: 2023 | E24: ACTUAL | F24: cogs_rate_sol | G24: 0.42 | H24: 假设初始化 | I24: 解决方案成本率
... A86: GROUP | D86: 2024 | E86: ACTUAL | F86: wacc | G86: 0.1 | H86: 假设初始化 | I86: WACC
A87: GROUP | C87: 华东 | D87: 2024 | E87: ACTUAL | F87: region_mix | G87: 0.32 | H87: 行业研究 | I87: 收入地区占比
A88: GROUP | C88: 华北 | D88: 2024 | E88: ACTUAL | F88: region_mix | G88: 0.3 | H88: 行业研究 | I88: 收入地区占比
A89: GROUP | C89: 华南 | D89: 2024 | E89: ACTUAL | F89: region_mix | G89: 0.2 | H89: 行业研究 | I89: 收入地区占比
A90: GROUP | C90: 海外 | D90: 2024 | E90: ACTUAL | F90: region_mix | G90: 0.18 | H90: 行业研究 | I90: 收入地区占比
A91: CLOUD | D91: 2024 | E91: ACTUAL | F91: token_volume_day | G91: 200 | H91: 假设初始化 | I91: 日均 token 消耗（B/day）
A92: CLOUD | D92: 2024 | E92: ACTUAL | F92: api_price | G92: 5 | H92: 假设初始化 | I92: 综合单价（元/M tokens）
A93: CLOUD | D93: 2024 | E93: ACTUAL | F93: inference_ucost | G93: 2.35 | H93: 假设初始化 | I93: 推理单位成本（元/M tok）
A94: CLOUD | D94: 2024 | E94: ACTUAL | F94: bandwidth_fee | G94: 700 | H94: 假设初始化 | I94: 带宽机房费用（万）
A95: CLOUD | D95: 2024 | E95: ACTUAL | F95: customers | G95: 2200 | H95: 假设初始化 | I95: 付费客户数（家）
A96: CLOUD | D96: 2024 | E96: ACTUAL | F96: churn_m | G96: 0.012 | H96: 假设初始化 | I96: 月流失率
A97: IND | D97: 2024 | E97: ACTUAL | F97: projects_pvt | G97: 14 | H97: 假设初始化 | I97: 私有化项目数（个）
A98: IND | D98: 2024 | E98: ACTUAL | F98: avg_contract | G98: 1100 | H98: 假设初始化 | I98: 平均合同额（万）
A99: IND | D99: 2024 | E99: ACTUAL | F99: subscribers_sol | G99: 30 | H99: 假设初始化 | I99: 解决方案签约客户（累计）
A100: IND | D100: 2024 | E100: ACTUAL | F100: sub_fee | G100: 100 | H100: 假设初始化 | I100: 解决方案年费（万）
A101: IND | D101: 2024 | E101: ACTUAL | F101: cogs_rate_pvt | G101: 0.61 | H101: 假设初始化 | I101: 私有化成本率
A102: IND | D102: 2024 | E102: ACTUAL | F102: cogs_rate_sol | G102: 0.42 | H102: 假设初始化 | I102: 解决方案成本率
... A164: GROUP | D164: 2025 | E164: ACTUAL | F164: wacc | G164: 0.1 | H164: 假设初始化 | I164: WACC
A165: GROUP | C165: 华东 | D165: 2025 | E165: ACTUAL | F165: region_mix | G165: 0.3 | H165: 行业研究 | I165: 收入地区占比
A166: GROUP | C166: 华北 | D166: 2025 | E166: ACTUAL | F166: region_mix | G166: 0.29 | H166: 行业研究 | I166: 收入地区占比
A167: GROUP | C167: 华南 | D167: 2025 | E167: ACTUAL | F167: region_mix | G167: 0.2 | H167: 行业研究 | I167: 收入地区占比
A168: GROUP | C168: 海外 | D168: 2025 | E168: ACTUAL | F168: region_mix | G168: 0.21 | H168: 行业研究 | I168: 收入地区占比
A169: CLOUD | D169: 2025 | E169: ACTUAL | F169: token_volume_day | G169: 450 | H169: 假设初始化 | I169: 日均 token 消耗（B/day）
A170: CLOUD | D170: 2025 | E170: ACTUAL | F170: api_price | G170: 4.8 | H170: 假设初始化 | I170: 综合单价（元/M tokens）
A171: CLOUD | D171: 2025 | E171: ACTUAL | F171: inference_ucost | G171: 2.15 | H171: 假设初始化 | I171: 推理单位成本（元/M tok）
A172: CLOUD | D172: 2025 | E172: ACTUAL | F172: bandwidth_fee | G172: 1300 | H172: 假设初始化 | I172: 带宽机房费用（万）
A173: CLOUD | D173: 2025 | E173: ACTUAL | F173: customers | G173: 4500 | H173: 假设初始化 | I173: 付费客户数（家）
A174: CLOUD | D174: 2025 | E174: ACTUAL | F174: churn_m | G174: 0.012 | H174: 假设初始化 | I174: 月流失率
A175: IND | D175: 2025 | E175: ACTUAL | F175: projects_pvt | G175: 22 | H175: 假设初始化 | I175: 私有化项目数（个）
A176: IND | D176: 2025 | E176: ACTUAL | F176: avg_contract | G176: 1250 | H176: 假设初始化 | I176: 平均合同额（万）
A177: IND | D177: 2025 | E177: ACTUAL | F177: subscribers_sol | G177: 62 | H177: 假设初始化 | I177: 解决方案签约客户（累计）
A178: IND | D178: 2025 | E178: ACTUAL | F178: sub_fee | G178: 105 | H178: 假设初始化 | I178: 解决方案年费（万）
A179: IND | D179: 2025 | E179: ACTUAL | F179: cogs_rate_pvt | G179: 0.61 | H179: 假设初始化 | I179: 私有化成本率
A180: IND | D180: 2025 | E180: ACTUAL | F180: cogs_rate_sol | G180: 0.42 | H180: 假设初始化 | I180: 解决方案成本率
... A242: GROUP | D242: 2026 | E242: BUDGET | F242: wacc | G242: 0.1 | H242: 假设初始化 | I242: WACC
A243: GROUP | C243: 华东 | D243: 2026 | E243: BUDGET | F243: region_mix | G243: 0.29 | H243: 行业研究 | I243: 收入地区占比
A244: GROUP | C244: 华北 | D244: 2026 | E244: BUDGET | F244: region_mix | G244: 0.28 | H244: 行业研究 | I244: 收入地区占比
A245: GROUP | C245: 华南 | D245: 2026 | E245: BUDGET | F245: region_mix | G245: 0.2 | H245: 行业研究 | I245: 收入地区占比
A246: GROUP | C246: 海外 | D246: 2026 | E246: BUDGET | F246: region_mix | G246: 0.23 | H246: 行业研究 | I246: 收入地区占比
A247: CLOUD | D247: 2026 | E247: BUDGET | F247: token_volume_day | G247: 650 | H247: 假设初始化 | I247: 日均 token 消耗（B/day）
A248: CLOUD | D248: 2026 | E248: BUDGET | F248: api_price | G248: 4.6 | H248: 假设初始化 | I248: 综合单价（元/M tokens）
A249: CLOUD | D249: 2026 | E249: BUDGET | F249: inference_ucost | G249: 1.72 | H249: 假设初始化 | I249: 推理单位成本（元/M tok）
A250: CLOUD | D250: 2026 | E250: BUDGET | F250: bandwidth_fee | G250: 2200 | H250: 假设初始化 | I250: 带宽机房费用（万）
A251: CLOUD | D251: 2026 | E251: BUDGET | F251: customers | G251: 7000 | H251: 假设初始化 | I251: 付费客户数（家）
A252: CLOUD | D252: 2026 | E252: BUDGET | F252: churn_m | G252: 0.012 | H252: 假设初始化 | I252: 月流失率
A253: IND | D253: 2026 | E253: BUDGET | F253: projects_pvt | G253: 32 | H253: 假设初始化 | I253: 私有化项目数（个）
A254: IND | D254: 2026 | E254: BUDGET | F254: avg_contract | G254: 1400 | H254: 假设初始化 | I254: 平均合同额（万）
A255: IND | D255: 2026 | E255: BUDGET | F255: subscribers_sol | G255: 105 | H255: 假设初始化 | I255: 解决方案签约客户（累计）
A256: IND | D256: 2026 | E256: BUDGET | F256: sub_fee | G256: 110 | H256: 假设初始化 | I256: 解决方案年费（万）
A257: IND | D257: 2026 | E257: BUDGET | F257: cogs_rate_pvt | G257: 0.61 | H257: 假设初始化 | I257: 私有化成本率
A258: IND | D258: 2026 | E258: BUDGET | F258: cogs_rate_sol | G258: 0.42 | H258: 假设初始化 | I258: 解决方案成本率
... A320: GROUP | D320: 2027 | E320: BUDGET | F320: wacc | G320: 0.1 | H320: 假设初始化 | I320: WACC
A321: GROUP | C321: 华东 | D321: 2027 | E321: BUDGET | F321: region_mix | G321: 0.28 | H321: 行业研究 | I321: 收入地区占比
A322: GROUP | C322: 华北 | D322: 2027 | E322: BUDGET | F322: region_mix | G322: 0.27 | H322: 行业研究 | I322: 收入地区占比
A323: GROUP | C323: 华南 | D323: 2027 | E323: BUDGET | F323: region_mix | G323: 0.2 | H323: 行业研究 | I323: 收入地区占比
A324: GROUP | C324: 海外 | D324: 2027 | E324: BUDGET | F324: region_mix | G324: 0.25 | H324: 行业研究 | I324: 收入地区占比
A325: CLOUD | D325: 2027 | E325: BUDGET | F325: token_volume_day | G325: 850 | H325: 假设初始化 | I325: 日均 token 消耗（B/day）
A326: CLOUD | D326: 2027 | E326: BUDGET | F326: api_price | G326: 4.5 | H326: 假设初始化 | I326: 综合单价（元/M tokens）
A327: CLOUD | D327: 2027 | E327: BUDGET | F327: inference_ucost | G327: 1.68 | H327: 假设初始化 | I327: 推理单位成本（元/M tok）
A328: CLOUD | D328: 2027 | E328: BUDGET | F328: bandwidth_fee | G328: 4000 | H328: 假设初始化 | I328: 带宽机房费用（万）
A329: CLOUD | D329: 2027 | E329: BUDGET | F329: customers | G329: 10000 | H329: 假设初始化 | I329: 付费客户数（家）
A330: CLOUD | D330: 2027 | E330: BUDGET | F330: churn_m | G330: 0.012 | H330: 假设初始化 | I330: 月流失率
A331: IND | D331: 2027 | E331: BUDGET | F331: projects_pvt | G331: 40 | H331: 假设初始化 | I331: 私有化项目数（个）
A332: IND | D332: 2027 | E332: BUDGET | F332: avg_contract | G332: 1500 | H332: 假设初始化 | I332: 平均合同额（万）
A333: IND | D333: 2027 | E333: BUDGET | F333: subscribers_sol | G333: 168 | H333: 假设初始化 | I333: 解决方案签约客户（累计）
A334: IND | D334: 2027 | E334: BUDGET | F334: sub_fee | G334: 115 | H334: 假设初始化 | I334: 解决方案年费（万）
A335: IND | D335: 2027 | E335: BUDGET | F335: cogs_rate_pvt | G335: 0.61 | H335: 假设初始化 | I335: 私有化成本率
A336: IND | D336: 2027 | E336: BUDGET | F336: cogs_rate_sol | G336: 0.42 | H336: 假设初始化 | I336: 解决方案成本率
... A393: CLOUD | D393: 2027 | E393: BUDGET | F393: capex_gpu | G393: 10000 | H393: 假设初始化 | I393: 推理卡

Sheet Assumptions
A1: 智擎集团 · 指标视图层 Assumptions
A2: 全部数值实时取自 Meta 数据表（SUMIFS）| 本页只读，改数请改 Meta!G 列 | 单位：万元
A3: 科目（万元） | B3: 备注 | C3: 2023 | D3: 2024 | E3: 2025 | F3: 2026 | G3: 2027
A4: ── 集团共用 ──
A5: 所得税率（高新15%） | C5: =SUMIFS(Meta!$G$2:$G$400,Meta!$F$2:$F$400,"tax_rate",Meta!$D$2:$D$400,C$3,Meta!$A$2:$A$400,"GROUP") | D5: =SUMIFS(Meta!$G$2:$G$400,Meta!$F$2:$F$400,"tax_rate",Meta!$D$2:$D$400,D$3,Meta!$A$2:$A$400,"GROUP") | E5: =SUMIFS(Meta!$G$2:$G$400,Meta!$F$2:$F$400,"tax_rate",Meta!$D$2:$D$400,E$3,Meta!$A$2:$A$400,"GROUP") | F5: =SUMIFS(Meta!$G$2:$G$400,Meta!$F$2:$F$400,"tax_rate",Meta!$D$2:$D$400,F$3,Meta!$A$2:$A$400,"GROUP") | G5: =SUMIFS(Meta!$G$2:$G$400,Meta!$F$2:$F$400,"tax_rate",Meta!$D$2:$D$400,G$3,Meta!$A$2:$A$400,"GROUP")
A6: 应收账期（天） | C6: =SUMIFS(Meta!$G$2:$G$400,Meta!$F$2:$F$400,"dso_days",Meta!$D$2:$D$400,C$3,Meta!$A$2:$A$400,"GROUP") | D6: =SUMIFS(Meta!$G$2:$G$400,Meta!$F$2:$F$400,"dso_days",Meta!$D$2:$D$400,D$3,Meta!$A$2:$A$400,"GROUP") | E6: =SUMIFS(Meta!$G$2:$G$400,Meta!$F$2:$F$400,"dso_days",Meta!$D$2:$D$400,E$3,Meta!$A$2:$A$400,"GROUP") | F6: =SUMIFS(Meta!$G$2:$G$400,Meta!$F$2:$F$400,"dso_days",Meta!$D$2:$D$400,F$3,Meta!$A$2:$A$400,"GROUP") | G6: =SUMIFS(Meta!$G$2:$G$400,Meta!$F$2:$F$400,"dso_days",Meta!$D$2:$D$400,G$3,Meta!$A$2:$A$400,"GROUP")
A7: 应付账期（天） | C7: =SUMIFS(Meta!$G$2:$G$400,Meta!$F$2:$F$400,"dpo_days",Meta!$D$2:$D$400,C$3,Meta!$A$2:$A$400,"GROUP") | D7: =SUMIFS(Meta!$G$2:$G$400,Meta!$F$2:$F$400,"dpo_days",Meta!$D$2:$D$400,D$3,Meta!$A$2:$A$400,"GROUP") | E7: =SUMIFS(Meta!$G$2:$G$400,Meta!$F$2:$F$400,"dpo_days",Meta!$D$2:$D$400,E$3,Meta!$A$2:$A$400,"GROUP") | F7: =SUMIFS(Meta!$G$2:$G$400,Meta!$F$2:$F$400,"dpo_days",Meta!$D$2:$D$400,F$3,Meta!$A$2:$A$400,"GROUP") | G7: =SUMIFS(Meta!$G$2:$G$400,Meta!$F$2:$F$400,"dpo_days",Meta!$D$2:$D$400,G$3,Meta!$A$2:$A$400,"GROUP")
A8: 内部往来账期（天） | C8: =SUMIFS(Meta!$G$2:$G$400,Meta!$F$2:$F$400,"ic_days",Meta!$D$2:$D$400,C$3,Meta!$A$2:$A$400,"GROUP") | D8: =SUMIFS(Meta!$G$2:$G$400,Meta!$F$2:$F$400,"ic_days",Meta!$D$2:$D$400,D$3,Meta!$A$2:$A$400,"GROUP") | E8: =SUMIFS(Meta!$G$2:$G$400,Meta!$F$2:$F$400,"ic_days",Meta!$D$2:$D$400,E$3,Meta!$A$2:$A$400,"GROUP") | F8: =SUMIFS(Meta!$G$2:$G$400,Meta!$F$2:$F$400,"ic_days",Meta!$D$2:$D$400,F$3,Meta!$A$2:$A$400,"GROUP") | G8: =SUMIFS(Meta!$G$2:$G$400,Meta!$F$2:$F$400,"ic_days",Meta!$D$2:$D$400,G$3,Meta!$A$2:$A$400,"GROUP")
A9: WACC（项目评估） | C9: =SUMIFS(Meta!$G$2:$G$400,Meta!$F$2:$F$400,"wacc",Meta!$D$2:$D$400,C$3,Meta!$A$2:$A$400,"GROUP") | D9: =SUMIFS(Meta!$G$2:$G$400,Meta!$F$2:$F$400,"wacc",Meta!$D$2:$D$400,D$3,Meta!$A$2:$A$400,"GROUP") | E9: =SUMIFS(Meta!$G$2:$G$400,Meta!$F$2:$F$400,"wacc",Meta!$D$2:$D$400,E$3,Meta!$A$2:$A$400,"GROUP") | F9: =SUMIFS(Meta!$G$2:$G$400,Meta!$F$2:$F$400,"wacc",Meta!$D$2:$D$400,F$3,Meta!$A$2:$A$400,"GROUP") | G9: =SUMIFS(Meta!$G$2:$G$400,Meta!$F$2:$F$400,"wacc",Meta!$D$2:$D$400,G$3,Meta!$A$2:$A$400,"GROUP")
A10: ── 智擎云 · MaaS ──
A11: 日均 token 消耗（B/day） | B11: 智谱 bigmodel 模式 | C11: =SUMIFS(Meta!$G$2:$G$400,Meta!$F$2:$F$400,"token_volume_day",Meta!$D$2:$D$400,C$3,Meta!$A$2:$A$400,"CLOUD") | D11: =SUMIFS(Meta!$G$2:$G$400,Meta!$F$2:$F$400,"token_volume_day",Meta!$D$2:$D$400,D$3,Meta!$A$2:$A$400,"CLOUD") | E11: =SUMIFS(Meta!$G$2:$G$400,Meta!$F$2:$F$400,"token_volume_day",Meta!$D$2:$D$400,E$3,Meta!$A$2:$A$400,"CLOUD") | F11: =SUMIFS(Meta!$G$2:$G$400,Meta!$F$2:$F$400,"token_volume_day",Meta!$D$2:$D$400,F$3,Meta!$A$2:$A$400,"CLOUD") | G11: =SUMIFS(Meta!$G$2:$G$400,Meta!$F$2:$F$400,"token_volume_day",Meta!$D$2:$D$400,G$3,Meta!$A$2:$A$400,"CLOUD")
A12: 综合单价（元/M tokens） | B12: 混合计价 | C12: =SUMIFS(Meta!$G$2:$G$400,Meta!$F$2:$F$400,"api_price",Meta!$D$2:$D$400,C$3,Meta!$A$2:$A$400,"CLOUD") | D12: =SUMIFS(Meta!$G$2:$G$400,Meta!$F$2:$F$400,"api_price",Meta!$D$2:$D$400,D$3,Meta!$A$2:$A$400,"CLOUD") | E12: =SUMIFS(Meta!$G$2:$G$400,Meta!$F$2:$F$400,"api_price",Meta!$D$2:$D$400,E$3,Meta!$A$2:$A$400,"CLOUD") | F12: =SUMIFS(Meta!$G$2:$G$400,Meta!$F$2:$F$400,"api_price",Meta!$D$2:$D$400,F$3,Meta!$A$2:$A$400,"CLOUD") | G12: =SUMIFS(Meta!$G$2:$G$400,Meta!$F$2:$F$400,"api_price",Meta!$D$2:$D$400,G$3,Meta!$A$2:$A$400,"CLOUD")
A13: 推理单位成本（元/M tokens） | B13: 自持+外租混合 | C13: =SUMIFS(Meta!$G$2:$G$400,Meta!$F$2:$F$400,"inference_ucost",Meta!$D$2:$D$400,C$3,Meta!$A$2:$A$400,"CLOUD") | D13: =SUMIFS(Meta!$G$2:$G$400,Meta!$F$2:$F$400,"inference_ucost",Meta!$D$2:$D$400,D$3,Meta!$A$2:$A$400,"CLOUD") | E13: =SUMIFS(Meta!$G$2:$G$400,Meta!$F$2:$F$400,"inference_ucost",Meta!$D$2:$D$400,E$3,Meta!$A$2:$A$400,"CLOUD") | F13: =SUMIFS(Meta!$G$2:$G$400,Meta!$F$2:$F$400,"inference_ucost",Meta!$D$2:$D$400,F$3,Meta!$A$2:$A$400,"CLOUD") | G13: =SUMIFS(Meta!$G$2:$G$400,Meta!$F$2:$F$400,"inference_ucost",Meta!$D$2:$D$400,G$3,Meta!$A$2:$A$400,"CLOUD")
A14: 带宽机房费用 | C14: =SUMIFS(Meta!$G$2:$G$400,Meta!$F$2:$F$400,"bandwidth_fee",Meta!$D$2:$D$400,C$3,Meta!$A$2:$A$400,"CLOUD") | D14: =SUMIFS(Meta!$G$2:$G$400,Meta!$F$2:$F$400,"bandwidth_fee",Meta!$D$2:$D$400,D$3,Meta!$A$2:$A$400,"CLOUD") | E14: =SUMIFS(Meta!$G$2:$G$400,Meta!$F$2:$F$400,"bandwidth_fee",Meta!$D$2:$D$400,E$3,Meta!$A$2:$A$400,"CLOUD") | F14: =SUMIFS(Meta!$G$2:$G$400,Meta!$F$2:$F$400,"bandwidth_fee",Meta!$D$2:$D$400,F$3,Meta!$A$2:$A$400,"CLOUD") | G14: =SUMIFS(Meta!$G$2:$G$400,Meta!$F$2:$F$400,"bandwidth_fee",Meta!$D$2:$D$400,G$3,Meta!$A$2:$A$400,"CLOUD")
A15: 研发编制（人） | C15: =SUMIFS(Meta!$G$2:$G$400,Meta!$F$2:$F$400,"headcount_rd",Meta!$D$2:$D$400,C$3,Meta!$A$2:$A$400,"CLOUD") | D15: =SUMIFS(Meta!$G$2:$G$400,Meta!$F$2:$F$400,"headcount_rd",Meta!$D$2:$D$400,D$3,Meta!$A$2:$A$400,"CLOUD") | E15: =SUMIFS(Meta!$G$2:$G$400,Meta!$F$2:$F$400,"headcount_rd",Meta!$D$2:$D$400,E$3,Meta!$A$2:$A$400,"CLOUD") | F15: =SUMIFS(Meta!$G$2:$G$400,Meta!$F$2:$F$400,"headcount_rd",Meta!$D$2:$D$400,F$3,Meta!$A$2:$A$400,"CLOUD") | G15: =SUMIFS(Meta!$G$2:$G$400,Meta!$F$2:$F$400,"headcount_rd",Meta!$D$2:$D$400,G$3,Meta!$A$2:$A$400,"CLOUD")
A16: 销售编制（人） | C16: =SUMIFS(Meta!$G$2:$G$400,Meta!$F$2:$F$400,"headcount_sales",Meta!$D$2:$D$400,C$3,Meta!$A$2:$A$400,"CLOUD") | D16: =SUMIFS(Meta!$G$2:$G$400,Meta!$F$2:$F$400,"headcount_sales",Meta!$D$2:$D$400,D$3,Meta!$A$2:$A$400,"CLOUD") | E16: =SUMIFS(Meta!$G$2:$G$400,Meta!$F$2:$F$400,"headcount_sales",Meta!$D$2:$D$400,E$3,Meta!$A$2:$A$400,"CLOUD") | F16: =SUMIFS(Meta!$G$2:$G$400,Meta!$F$2:$F$400,"headcount_sales",Meta!$D$2:$D$400,F$3,Meta!$A$2:$A$400,"CLOUD") | G16: =SUMIFS(Meta!$G$2:$G$400,Meta!$F$2:$F$400,"headcount_sales",Meta!$D$2:$D$400,G$3,Meta!$A$2:$A$400,"CLOUD")
A17: 管理编制（人） | C17: =SUMIFS(Meta!$G$2:$G$400,Meta!$F$2:$F$400,"headcount_gna",Meta!$D$2:$D$400,C$3,Meta!$A$2:$A$400,"CLOUD") | D17: =SUMIFS(Meta!$G$2:$G$400,Meta!$F$2:$F$400,"headcount_gna",Meta!$D$2:$D$400,D$3,Meta!$A$2:$A$400,"CLOUD") | E17: =SUMIFS(Meta!$G$2:$G$400,Meta!$F$2:$F$400,"headcount_gna",Meta!$D$2:$D$400,E$3,Meta!$A$2:$A$400,"CLOUD") | F17: =SUMIFS(Meta!$G$2:$G$400,Meta!$F$2:$F$400,"headcount_gna",Meta!$D$2:$D$400,F$3,Meta!$A$2:$A$400,"CLOUD") | G17: =SUMIFS(Meta!$G$2:$G$400,Meta!$F$2:$F$400,"headcount_gna",Meta!$D$2:$D$400,G$3,Meta!$A$2:$A$400,"CLOUD")
A18: 付费客户数（家） | B18: UE 用 | C18: =SUMIFS(Meta!$G$2:$G$400,Meta!$F$2:$F$400,"customers",Meta!$D$2:$D$400,C$3,Meta!$A$2:$A$400,"CLOUD") | D18: =SUMIFS(Meta!$G$2:$G$400,Meta!$F$2:$F$400,"customers",Meta!$D$2:$D$400,D$3,Meta!$A$2:$A$400,"CLOUD") | E18: =SUMIFS(Meta!$G$2:$G$400,Meta!$F$2:$F$400,"customers",Meta!$D$2:$D$400,E$3,Meta!$A$2:$A$400,"CLOUD") | F18: =SUMIFS(Meta!$G$2:$G$400,Meta!$F$2:$F$400,"customers",Meta!$D$2:$D$400,F$3,Meta!$A$2:$A$400,"CLOUD") | G18: =SUMIFS(Meta!$G$2:$G$400,Meta!$F$2:$F$400,"customers",Meta!$D$2:$D$400,G$3,Meta!$A$2:$A$400,"CLOUD")
A19: 月流失率 | B19: UE 用 | C19: =SUMIFS(Meta!$G$2:$G$400,Meta!$F$2:$F$400,"churn_m",Meta!$D$2:$D$400,C$3,Meta!$A$2:$A$400,"CLOUD") | D19: =SUMIFS(Meta!$G$2:$G$400,Meta!$F$2:$F$400,"churn_m",Meta!$D$2:$D$400,D$3,Meta!$A$2:$A$400,"CLOUD") | E19: =SUMIFS(Meta!$G$2:$G$400,Meta!$F$2:$F$400,"churn_m",Meta!$D$2:$D$400,E$3,Meta!$A$2:$A$400,"CLOUD") | F19: =SUMIFS(Meta!$G$2:$G$400,Meta!$F$2:$F$400,"churn_m",Meta!$D$2:$D$400,F$3,Meta!$A$2:$A$400,"CLOUD") | G19: =SUMIFS(Meta!$G$2:$G$400,Meta!$F$2:$F$400,"churn_m",Meta!$D$2:$D$400,G$3,Meta!$A$2:$A$400,"CLOUD")
A20: ── 智擎行业 · 私有化+解决方案 ──
A21: 私有化项目数（个） | C21: =SUMIFS(Meta!$G$2:$G$400,Meta!$F$2:$F$400,"projects_pvt",Meta!$D$2:$D$400,C$3,Meta!$A$2:$A$400,"IND") | D21: =SUMIFS(Meta!$G$2:$G$400,Meta!$F$2:$F$400,"projects_pvt",Meta!$D$2:$D$400,D$3,Meta!$A$2:$A$400,"IND") | E21: =SUMIFS(Meta!$G$2:$G$400,Meta!$F$2:$F$400,"projects_pvt",Meta!$D$2:$D$400,E$3,Meta!$A$2:$A$400,"IND") | F21: =SUMIFS(Meta!$G$2:$G$400,Meta!$F$2:$F$400,"projects_pvt",Meta!$D$2:$D$400,F$3,Meta!$A$2:$A$400,"IND") | G21: =SUMIFS(Meta!$G$2:$G$400,Meta!$F$2:$F$400,"projects_pvt",Meta!$D$2:$D$400,G$3,Meta!$A$2:$A$400,"IND")
A22: 平均合同额 | C22: =SUMIFS(Meta!$G$2:$G$400,Meta!$F$2:$F$400,"avg_contract",Meta!$D$2:$D$400,C$3,Meta!$A$2:$A$400,"IND") | D22: =SUMIFS(Meta!$G$2:$G$400,Meta!$F$2:$F$400,"avg_contract",Meta!$D$2:$D$400,D$3,Meta!$A$2:$A$400,"IND") | E22: =SUMIFS(Meta!$G$2:$G$400,Meta!$F$2:$F$400,"avg_contract",Meta!$D$2:$D$400,E$3,Meta!$A$2:$A$400,"IND") | F22: =SUMIFS(Meta!$G$2:$G$400,Meta!$F$2:$F$400,"avg_contract",Meta!$D$2:$D$400,F$3,Meta!$A$2:$A$400,"IND") | G22: =SUMIFS(Meta!$G$2:$G$400,Meta!$F$2:$F$400,"avg_contract",Meta!$D$2:$D$400,G$3,Meta!$A$2:$A$400,"IND")
A23: 解决方案签约客户（累计） | B23: 订阅/运维 | C23: =SUMIFS(Meta!$G$2:$G$400,Meta!$F$2:$F$400,"subscribers_sol",Meta!$D$2:$D$400,C$3,Meta!$A$2:$A$400,"IND") | D23: =SUMIFS(Meta!$G$2:$G$400,Meta!$F$2:$F$400,"subscribers_sol",Meta!$D$2:$D$400,D$3,Meta!$A$2:$A$400,"IND") | E23: =SUMIFS(Meta!$G$2:$G$400,Meta!$F$2:$F$400,"subscribers_sol",Meta!$D$2:$D$400,E$3,Meta!$A$2:$A$400,"IND") | F23: =SUMIFS(Meta!$G$2:$G$400,Meta!$F$2:$F$400,"subscribers_sol",Meta!$D$2:$D$400,F$3,Meta!$A$2:$A$400,"IND") | G23: =SUMIFS(Meta!$G$2:$G$400,Meta!$F$2:$F$400,"subscribers_sol",Meta!$D$2:$D$400,G$3,Meta!$A$2:$A$400,"IND")
A24: 解决方案年费 | C24: =SUMIFS(Meta!$G$2:$G$400,Meta!$F$2:$F$400,"sub_fee",Meta!$D$2:$D$400,C$3,Meta!$A$2:$A$400,"IND") | D24: =SUMIFS(Meta!$G$2:$G$400,Meta!$F$2:$F$400,"sub_fee",Meta!$D$2:$D$400,D$3,Meta!$A$2:$A$400,"IND") | E24: =SUMIFS(Meta!$G$2:$G$400,Meta!$F$2:$F$400,"sub_fee",Meta!$D$2:$D$400,E$3,Meta!$A$2:$A$400,"IND") | F24: =SUMIFS(Meta!$G$2:$G$400,Meta!$F$2:$F$400,"sub_fee",Meta!$D$2:$D$400,F$3,Meta!$A$2:$A$400,"IND") | G24: =SUMIFS(Meta!$G$2:$G$400,Meta!$F$2:$F$400,"sub_fee",Meta!$D$2:$D$400,G$3,Meta!$A$2:$A$400,"IND")
A25: 私有化成本率（硬件+人力） | C25: =SUMIFS(Meta!$G$2:$G$400,Meta!$F$2:$F$400,"cogs_rate_pvt",Meta!$D$2:$D$400,C$3,Meta!$A$2:$A$400,"IND") | D25: =SUMIFS(Meta!$G$2:$G$400,Meta!$F$2:$F$400,"cogs_rate_pvt",Meta!$D$2:$D$400,D$3,Meta!$A$2:$A$400,"IND") | E25: =SUMIFS(Meta!$G$2:$G$400,Meta!$F$2:$F$400,"cogs_rate_pvt",Meta!$D$2:$D$400,E$3,Meta!$A$2:$A$400,"IND") | F25: =SUMIFS(Meta!$G$2:$G$400,Meta!$F$2:$F$400,"cogs_rate_pvt",Meta!$D$2:$D$400,F$3,Meta!$A$2:$A$400,"IND") | G25: =SUMIFS(Meta!$G$2:$G$400,Meta!$F$2:$F$400,"cogs_rate_pvt",Meta!$D$2:$D$400,G$3,Meta!$A$2:$A$400,"IND")
A26: 解决方案成本率 | C26: =SUMIFS(Meta!$G$2:$G$400,Meta!$F$2:$F$400,"cogs_rate_sol",Meta!$D$2:$D$400,C$3,Meta!$A$2:$A$400,"IND") | D26: =SUMIFS(Meta!$G$2:$G$400,Meta!$F$2:$F$400,"cogs_rate_sol",Meta!$D$2:$D$400,D$3,Meta!$A$2:$A$400,"IND") | E26: =SUMIFS(Meta!$G$2:$G$400,Meta!$F$2:$F$400,"cogs_rate_sol",Meta!$D$2:$D$400,E$3,Meta!$A$2:$A$400,"IND") | F26: =SUMIFS(Meta!$G$2:$G$400,Meta!$F$2:$F$400,"cogs_rate_sol",Meta!$D$2:$D$400,F$3,Meta!$A$2:$A$400,"IND") | G26: =SUMIFS(Meta!$G$2:$G$400,Meta!$F$2:$F$400,"cogs_rate_sol",Meta!$D$2:$D$400,G$3,Meta!$A$2:$A$400,"IND")
A27: 研发编制（人） | C27: =SUMIFS(Meta!$G$2:$G$400,Meta!$F$2:$F$400,"headcount_rd",Meta!$D$2:$D$400,C$3,Meta!$A$2:$A$400,"IND") | D27: =SUMIFS(Meta!$G$2:$G$400,Meta!$F$2:$F$400,"headcount_rd",Meta!$D$2:$D$400,D$3,Meta!$A$2:$A$400,"IND") | E27: =SUMIFS(Meta!$G$2:$G$400,Meta!$F$2:$F$400,"headcount_rd",Meta!$D$2:$D$400,E$3,Meta!$A$2:$A$400,"IND") | F27: =SUMIFS(Meta!$G$2:$G$400,Meta!$F$2:$F$400,"headcount_rd",Meta!$D$2:$D$400,F$3,Meta!$A$2:$A$400,"IND") | G27: =SUMIFS(Meta!$G$2:$G$400,Meta!$F$2:$F$400,"headcount_rd",Meta!$D$2:$D$400,G$3,Meta!$A$2:$A$400,"IND")
A28: 销售编制（人） | C28: =SUMIFS(Meta!$G$2:$G$400,Meta!$F$2:$F$400,"headcount_sales",Meta!$D$2:$D$400,C$3,Meta!$A$2:$A$400,"IND") | D28: =SUMIFS(Meta!$G$2:$G$400,Meta!$F$2:$F$400,"headcount_sales",Meta!$D$2:$D$400,D$3,Meta!$A$2:$A$400,"IND") | E28: =SUMIFS(Meta!$G$2:$G$400,Meta!$F$2:$F$400,"headcount_sales",Meta!$D$2:$D$400,E$3,Meta!$A$2:$A$400,"IND") | F28: =SUMIFS(Meta!$G$2:$G$400,Meta!$F$2:$F$400,"headcount_sales",Meta!$D$2:$D$400,F$3,Meta!$A$2:$A$400,"IND") | G28: =SUMIFS(Meta!$G$2:$G$400,Meta!$F$2:$F$400,"headcount_sales",Meta!$D$2:$D$400,G$3,Meta!$A$2:$A$400,"IND")
A29: 管理编制（人） | C29: =SUMIFS(Meta!$G$2:$G$400,Meta!$F$2:$F$400,"headcount_gna",Meta!$D$2:$D$400,C$3,Meta!$A$2:$A$400,"IND") | D29: =SUMIFS(Meta!$G$2:$G$400,Meta!$F$2:$F$400,"headcount_gna",Meta!$D$2:$D$400,D$3,Meta!$A$2:$A$400,"IND") | E29: =SUMIFS(Meta!$G$2:$G$400,Meta!$F$2:$F$400,"headcount_gna",Meta!$D$2:$D$400,E$3,Meta!$A$2:$A$400,"IND") | F29: =SUMIFS(Meta!$G$2:$G$400,Meta!$F$2:$F$400,"headcount_gna",Meta!$D$2:$D$400,F$3,Meta!$A$2:$A$400,"IND") | G29: =SUMIFS(Meta!$G$2:$G$400,Meta!$F$2:$F$400,"headcount_gna",Meta!$D$2:$D$400,G$3,Meta!$A$2:$A$400,"IND")
A30: ── 智擎互联 · C端 ──
A31: MAU（万人） | C31: =SUMIFS(Meta!$G$2:$G$400,Meta!$F$2:$F$400,"mau_w",Meta!$D$2:$D$400,C$3,Meta!$A$2:$A$400,"TOC") | D31: =SUMIFS(Meta!$G$2:$G$400,Meta!$F$2:$F$400,"mau_w",Meta!$D$2:$D$400,D$3,Meta!$A$2:$A$400,"TOC") | E31: =SUMIFS(Meta!$G$2:$G$400,Meta!$F$2:$F$400,"mau_w",Meta!$D$2:$D$400,E$3,Meta!$A$2:$A$400,"TOC") | F31: =SUMIFS(Meta!$G$2:$G$400,Meta!$F$2:$F$400,"mau_w",Meta!$D$2:$D$400,F$3,Meta!$A$2:$A$400,"TOC") | G31: =SUMIFS(Meta!$G$2:$G$400,Meta!$F$2:$F$400,"mau_w",Meta!$D$2:$D$400,G$3,Meta!$A$2:$A$400,"TOC")
A32: 付费转化率 | C32: =SUMIFS(Meta!$G$2:$G$400,Meta!$F$2:$F$400,"pay_rate",Meta!$D$2:$D$400,C$3,Meta!$A$2:$A$400,"TOC") | D32: =SUMIFS(Meta!$G$2:$G$400,Meta!$F$2:$F$400,"pay_rate",Meta!$D$2:$D$400,D$3,Meta!$A$2:$A$400,"TOC") | E32: =SUMIFS(Meta!$G$2:$G$400,Meta!$F$2:$F$400,"pay_rate",Meta!$D$2:$D$400,E$3,Meta!$A$2:$A$400,"TOC") | F32: =SUMIFS(Meta!$G$2:$G$400,Meta!$F$2:$F$400,"pay_rate",Meta!$D$2:$D$400,F$3,Meta!$A$2:$A$400,"TOC") | G32: =SUMIFS(Meta!$G$2:$G$400,Meta!$F$2:$F$400,"pay_rate",Meta!$D$2:$D$400,G$3,Meta!$A$2:$A$400,"TOC")
A33: ARPPU（元/付费用户/月） | C33: =SUMIFS(Meta!$G$2:$G$400,Meta!$F$2:$F$400,"arppu",Meta!$D$2:$D$400,C$3,Meta!$A$2:$A$400,"TOC") | D33: =SUMIFS(Meta!$G$2:$G$400,Meta!$F$2:$F$400,"arppu",Meta!$D$2:$D$400,D$3,Meta!$A$2:$A$400,"TOC") | E33: =SUMIFS(Meta!$G$2:$G$400,Meta!$F$2:$F$400,"arppu",Meta!$D$2:$D$400,E$3,Meta!$A$2:$A$400,"TOC") | F33: =SUMIFS(Meta!$G$2:$G$400,Meta!$F$2:$F$400,"arppu",Meta!$D$2:$D$400,F$3,Meta!$A$2:$A$400,"TOC") | G33: =SUMIFS(Meta!$G$2:$G$400,Meta!$F$2:$F$400,"arppu",Meta!$D$2:$D$400,G$3,Meta!$A$2:$A$400,"TOC")
A34: 广告收入 | C34: =SUMIFS(Meta!$G$2:$G$400,Meta!$F$2:$F$400,"ads_rev",Meta!$D$2:$D$400,C$3,Meta!$A$2:$A$400,"TOC") | D34: =SUMIFS(Meta!$G$2:$G$400,Meta!$F$2:$F$400,"ads_rev",Meta!$D$2:$D$400,D$3,Meta!$A$2:$A$400,"TOC") | E34: =SUMIFS(Meta!$G$2:$G$400,Meta!$F$2:$F$400,"ads_rev",Meta!$D$2:$D$400,E$3,Meta!$A$2:$A$400,"TOC") | F34: =SUMIFS(Meta!$G$2:$G$400,Meta!$F$2:$F$400,"ads_rev",Meta!$D$2:$D$400,F$3,Meta!$A$2:$A$400,"TOC") | G34: =SUMIFS(Meta!$G$2:$G$400,Meta!$F$2:$F$400,"ads_rev",Meta!$D$2:$D$400,G$3,Meta!$A$2:$A$400,"TOC")
A35: 单位推理+带宽成本（元/MAU/月） | C35: =SUMIFS(Meta!$G$2:$G$400,Meta!$F$2:$F$400,"ucost_toc",Meta!$D$2:$D$400,C$3,Meta!$A$2:$A$400,"TOC") | D35: =SUMIFS(Meta!$G$2:$G$400,Meta!$F$2:$F$400,"ucost_toc",Meta!$D$2:$D$400,D$3,Meta!$A$2:$A$400,"TOC") | E35: =SUMIFS(Meta!$G$2:$G$400,Meta!$F$2:$F$400,"ucost_toc",Meta!$D$2:$D$400,E$3,Meta!$A$2:$A$400,"TOC") | F35: =SUMIFS(Meta!$G$2:$G$400,Meta!$F$2:$F$400,"ucost_toc",Meta!$D$2:$D$400,F$3,Meta!$A$2:$A$400,"TOC") | G35: =SUMIFS(Meta!$G$2:$G$400,Meta!$F$2:$F$400,"ucost_toc",Meta!$D$2:$D$400,G$3,Meta!$A$2:$A$400,"TOC")
A36: 获客成本（元/新增用户） | C36: =SUMIFS(Meta!$G$2:$G$400,Meta!$F$2:$F$400,"cac",Meta!$D$2:$D$400,C$3,Meta!$A$2:$A$400,"TOC") | D36: =SUMIFS(Meta!$G$2:$G$400,Meta!$F$2:$F$400,"cac",Meta!$D$2:$D$400,D$3,Meta!$A$2:$A$400,"TOC") | E36: =SUMIFS(Meta!$G$2:$G$400,Meta!$F$2:$F$400,"cac",Meta!$D$2:$D$400,E$3,Meta!$A$2:$A$400,"TOC") | F36: =SUMIFS(Meta!$G$2:$G$400,Meta!$F$2:$F$400,"cac",Meta!$D$2:$D$400,F$3,Meta!$A$2:$A$400,"TOC") | G36: =SUMIFS(Meta!$G$2:$G$400,Meta!$F$2:$F$400,"cac",Meta!$D$2:$D$400,G$3,Meta!$A$2:$A$400,"TOC")
A37: 新增用户=MAU增量× | B37: 补流失 | C37: =SUMIFS(Meta!$G$2:$G$400,Meta!$F$2:$F$400,"new_user_mult",Meta!$D$2:$D$400,C$3,Meta!$A$2:$A$400,"TOC") | D37: =SUMIFS(Meta!$G$2:$G$400,Meta!$F$2:$F$400,"new_user_mult",Meta!$D$2:$D$400,D$3,Meta!$A$2:$A$400,"TOC") | E37: =SUMIFS(Meta!$G$2:$G$400,Meta!$F$2:$F$400,"new_user_mult",Meta!$D$2:$D$400,E$3,Meta!$A$2:$A$400,"TOC") | F37: =SUMIFS(Meta!$G$2:$G$400,Meta!$F$2:$F$400,"new_user_mult",Meta!$D$2:$D$400,F$3,Meta!$A$2:$A$400,"TOC") | G37: =SUMIFS(Meta!$G$2:$G$400,Meta!$F$2:$F$400,"new_user_mult",Meta!$D$2:$D$400,G$3,Meta!$A$2:$A$400,"TOC")
A38: 研发编制（人） | C38: =SUMIFS(Meta!$G$2:$G$400,Meta!$F$2:$F$400,"headcount_rd",Meta!$D$2:$D$400,C$3,Meta!$A$2:$A$400,"TOC") | D38: =SUMIFS(Meta!$G$2:$G$400,Meta!$F$2:$F$400,"headcount_rd",Meta!$D$2:$D$400,D$3,Meta!$A$2:$A$400,"TOC") | E38: =SUMIFS(Meta!$G$2:$G$400,Meta!$F$2:$F$400,"headcount_rd",Meta!$D$2:$D$400,E$3,Meta!$A$2:$A$400,"TOC") | F38: =SUMIFS(Meta!$G$2:$G$400,Meta!$F$2:$F$400,"headcount_rd",Meta!$D$2:$D$400,F$3,Meta!$A$2:$A$400,"TOC") | G38: =SUMIFS(Meta!$G$2:$G$400,Meta!$F$2:$F$400,"headcount_rd",Meta!$D$2:$D$400,G$3,Meta!$A$2:$A$400,"TOC")
A39: 固定销售编制（人） | C39: =SUMIFS(Meta!$G$2:$G$400,Meta!$F$2:$F$400,"headcount_sales",Meta!$D$2:$D$400,C$3,Meta!$A$2:$A$400,"TOC") | D39: =SUMIFS(Meta!$G$2:$G$400,Meta!$F$2:$F$400,"headcount_sales",Meta!$D$2:$D$400,D$3,Meta!$A$2:$A$400,"TOC") | E39: =SUMIFS(Meta!$G$2:$G$400,Meta!$F$2:$F$400,"headcount_sales",Meta!$D$2:$D$400,E$3,Meta!$A$2:$A$400,"TOC") | F39: =SUMIFS(Meta!$G$2:$G$400,Meta!$F$2:$F$400,"headcount_sales",Meta!$D$2:$D$400,F$3,Meta!$A$2:$A$400,"TOC") | G39: =SUMIFS(Meta!$G$2:$G$400,Meta!$F$2:$F$400,"headcount_sales",Meta!$D$2:$D$400,G$3,Meta!$A$2:$A$400,"TOC")
A40: 管理编制（人） | C40: =SUMIFS(Meta!$G$2:$G$400,Meta!$F$2:$F$400,"headcount_gna",Meta!$D$2:$D$400,C$3,Meta!$A$2:$A$400,"TOC") | D40: =SUMIFS(Meta!$G$2:$G$400,Meta!$F$2:$F$400,"headcount_gna",Meta!$D$2:$D$400,D$3,Meta!$A$2:$A$400,"TOC") | E40: =SUMIFS(Meta!$G$2:$G$400,Meta!$F$2:$F$400,"headcount_gna",Meta!$D$2:$D$400,E$3,Meta!$A$2:$A$400,"TOC") | F40: =SUMIFS(Meta!$G$2:$G$400,Meta!$F$2:$F$400,"headcount_gna",Meta!$D$2:$D$400,F$3,Meta!$A$2:$A$400,"TOC") | G40: =SUMIFS(Meta!$G$2:$G$400,Meta!$F$2:$F$400,"headcount_gna",Meta!$D$2:$D$400,G$3,Meta!$A$2:$A$400,"TOC")
A41: ── 智擎研究院 ──
A42: 研发编制（人） | B42: 基座模型研发 | C42: =SUMIFS(Meta!$G$2:$G$400,Meta!$F$2:$F$400,"headcount_rd",Meta!$D$2:$D$400,C$3,Meta!$A$2:$A$400,"HOLD") | D42: =SUMIFS(Meta!$G$2:$G$400,Meta!$F$2:$F$400,"headcount_rd",Meta!$D$2:$D$400,D$3,Meta!$A$2:$A$400,"HOLD") | E42: =SUMIFS(Meta!$G$2:$G$400,Meta!$F$2:$F$400,"headcount_rd",Meta!$D$2:$D$400,E$3,Meta!$A$2:$A$400,"HOLD") | F42: =SUMIFS(Meta!$G$2:$G$400,Meta!$F$2:$F$400,"headcount_rd",Meta!$D$2:$D$400,F$3,Meta!$A$2:$A$400,"HOLD") | G42: =SUMIFS(Meta!$G$2:$G$400,Meta!$F$2:$F$400,"headcount_rd",Meta!$D$2:$D$400,G$3,Meta!$A$2:$A$400,"HOLD")
A43: 人均全成本（万/年） | C43: =SUMIFS(Meta!$G$2:$G$400,Meta!$F$2:$F$400,"hold_salary",Meta!$D$2:$D$400,C$3,Meta!$A$2:$A$400,"HOLD") | D43: =SUMIFS(Meta!$G$2:$G$400,Meta!$F$2:$F$400,"hold_salary",Meta!$D$2:$D$400,D$3,Meta!$A$2:$A$400,"HOLD") | E43: =SUMIFS(Meta!$G$2:$G$400,Meta!$F$2:$F$400,"hold_salary",Meta!$D$2:$D$400,E$3,Meta!$A$2:$A$400,"HOLD") | F43: =SUMIFS(Meta!$G$2:$G$400,Meta!$F$2:$F$400,"hold_salary",Meta!$D$2:$D$400,F$3,Meta!$A$2:$A$400,"HOLD") | G43: =SUMIFS(Meta!$G$2:$G$400,Meta!$F$2:$F$400,"hold_salary",Meta!$D$2:$D$400,G$3,Meta!$A$2:$A$400,"HOLD")
A44: 其他研发费用（数据/外包） | C44: =SUMIFS(Meta!$G$2:$G$400,Meta!$F$2:$F$400,"other_rd",Meta!$D$2:$D$400,C$3,Meta!$A$2:$A$400,"HOLD") | D44: =SUMIFS(Meta!$G$2:$G$400,Meta!$F$2:$F$400,"other_rd",Meta!$D$2:$D$400,D$3,Meta!$A$2:$A$400,"HOLD") | E44: =SUMIFS(Meta!$G$2:$G$400,Meta!$F$2:$F$400,"other_rd",Meta!$D$2:$D$400,E$3,Meta!$A$2:$A$400,"HOLD") | F44: =SUMIFS(Meta!$G$2:$G$400,Meta!$F$2:$F$400,"other_rd",Meta!$D$2:$D$400,F$3,Meta!$A$2:$A$400,"HOLD") | G44: =SUMIFS(Meta!$G$2:$G$400,Meta!$F$2:$F$400,"other_rd",Meta!$D$2:$D$400,G$3,Meta!$A$2:$A$400,"HOLD")
A45: 管理编制（人） | C45: =SUMIFS(Meta!$G$2:$G$400,Meta!$F$2:$F$400,"headcount_gna",Meta!$D$2:$D$400,C$3,Meta!$A$2:$A$400,"HOLD") | D45: =SUMIFS(Meta!$G$2:$G$400,Meta!$F$2:$F$400,"headcount_gna",Meta!$D$2:$D$400,D$3,Meta!$A$2:$A$400,"HOLD") | E45: =SUMIFS(Meta!$G$2:$G$400,Meta!$F$2:$F$400,"headcount_gna",Meta!$D$2:$D$400,E$3,Meta!$A$2:$A$400,"HOLD") | F45: =SUMIFS(Meta!$G$2:$G$400,Meta!$F$2:$F$400,"headcount_gna",Meta!$D$2:$D$400,F$3,Meta!$A$2:$A$400,"HOLD") | G45: =SUMIFS(Meta!$G$2:$G$400,Meta!$F$2:$F$400,"headcount_gna",Meta!$D$2:$D$400,G$3,Meta!$A$2:$A$400,"HOLD")
A46: 管理人均全成本（万/年） | C46: =SUMIFS(Meta!$G$2:$G$400,Meta!$F$2:$F$400,"salary_gna",Meta!$D$2:$D$400,C$3,Meta!$A$2:$A$400,"HOLD") | D46: =SUMIFS(Meta!$G$2:$G$400,Meta!$F$2:$F$400,"salary_gna",Meta!$D$2:$D$400,D$3,Meta!$A$2:$A$400,"HOLD") | E46: =SUMIFS(Meta!$G$2:$G$400,Meta!$F$2:$F$400,"salary_gna",Meta!$D$2:$D$400,E$3,Meta!$A$2:$A$400,"HOLD") | F46: =SUMIFS(Meta!$G$2:$G$400,Meta!$F$2:$F$400,"salary_gna",Meta!$D$2:$D$400,F$3,Meta!$A$2:$A$400,"HOLD") | G46: =SUMIFS(Meta!$G$2:$G$400,Meta!$F$2:$F$400,"salary_gna",Meta!$D$2:$D$400,G$3,Meta!$A$2:$A$400,"HOLD")
A47: ── 关联交易定价 ──
A48: T1 license 费率 · 智擎云 | B48: 收入×费率 | C48: =SUMIFS(Meta!$G$2:$G$400,Meta!$F$2:$F$400,"t1_rate",Meta!$D$2:$D$400,C$3,Meta!$A$2:$A$400,"CLOUD") | D48: =SUMIFS(Meta!$G$2:$G$400,Meta!$F$2:$F$400,"t1_rate",Meta!$D$2:$D$400,D$3,Meta!$A$2:$A$400,"CLOUD") | E48: =SUMIFS(Meta!$G$2:$G$400,Meta!$F$2:$F$400,"t1_rate",Meta!$D$2:$D$400,E$3,Meta!$A$2:$A$400,"CLOUD") | F48: =SUMIFS(Meta!$G$2:$G$400,Meta!$F$2:$F$400,"t1_rate",Meta!$D$2:$D$400,F$3,Meta!$A$2:$A$400,"CLOUD") | G48: =SUMIFS(Meta!$G$2:$G$400,Meta!$F$2:$F$400,"t1_rate",Meta!$D$2:$D$400,G$3,Meta!$A$2:$A$400,"CLOUD")
A49: T1 license 费率 · 智擎行业 | B49: 收入×费率 | C49: =SUMIFS(Meta!$G$2:$G$400,Meta!$F$2:$F$400,"t1_rate",Meta!$D$2:$D$400,C$3,Meta!$A$2:$A$400,"IND") | D49: =SUMIFS(Meta!$G$2:$G$400,Meta!$F$2:$F$400,"t1_rate",Meta!$D$2:$D$400,D$3,Meta!$A$2:$A$400,"IND") | E49: =SUMIFS(Meta!$G$2:$G$400,Meta!$F$2:$F$400,"t1_rate",Meta!$D$2:$D$400,E$3,Meta!$A$2:$A$400,"IND") | F49: =SUMIFS(Meta!$G$2:$G$400,Meta!$F$2:$F$400,"t1_rate",Meta!$D$2:$D$400,F$3,Meta!$A$2:$A$400,"IND") | G49: =SUMIFS(Meta!$G$2:$G$400,Meta!$F$2:$F$400,"t1_rate",Meta!$D$2:$D$400,G$3,Meta!$A$2:$A$400,"IND")
A50: T1 license 费率 · 智擎互联 | B50: 收入×费率 | C50: =SUMIFS(Meta!$G$2:$G$400,Meta!$F$2:$F$400,"t1_rate",Meta!$D$2:$D$400,C$3,Meta!$A$2:$A$400,"TOC") | D50: =SUMIFS(Meta!$G$2:$G$400,Meta!$F$2:$F$400,"t1_rate",Meta!$D$2:$D$400,D$3,Meta!$A$2:$A$400,"TOC") | E50: =SUMIFS(Meta!$G$2:$G$400,Meta!$F$2:$F$400,"t1_rate",Meta!$D$2:$D$400,E$3,Meta!$A$2:$A$400,"TOC") | F50: =SUMIFS(Meta!$G$2:$G$400,Meta!$F$2:$F$400,"t1_rate",Meta!$D$2:$D$400,F$3,Meta!$A$2:$A$400,"TOC") | G50: =SUMIFS(Meta!$G$2:$G$400,Meta!$F$2:$F$400,"t1_rate",Meta!$D$2:$D$400,G$3,Meta!$A$2:$A$400,"TOC")
A51: T2 定制研发服务费（行业→研究院） | C51: =SUMIFS(Meta!$G$2:$G$400,Meta!$F$2:$F$400,"t2_fee",Meta!$D$2:$D$400,C$3,Meta!$A$2:$A$400,"HOLD") | D51: =SUMIFS(Meta!$G$2:$G$400,Meta!$F$2:$F$400,"t2_fee",Meta!$D$2:$D$400,D$3,Meta!$A$2:$A$400,"HOLD") | E51: =SUMIFS(Meta!$G$2:$G$400,Meta!$F$2:$F$400,"t2_fee",Meta!$D$2:$D$400,E$3,Meta!$A$2:$A$400,"HOLD") | F51: =SUMIFS(Meta!$G$2:$G$400,Meta!$F$2:$F$400,"t2_fee",Meta!$D$2:$D$400,F$3,Meta!$A$2:$A$400,"HOLD") | G51: =SUMIFS(Meta!$G$2:$G$400,Meta!$F$2:$F$400,"t2_fee",Meta!$D$2:$D$400,G$3,Meta!$A$2:$A$400,"HOLD")
A52: T3 互联算力结算占其推理成本 | C52: =SUMIFS(Meta!$G$2:$G$400,Meta!$F$2:$F$400,"t3_share",Meta!$D$2:$D$400,C$3,Meta!$A$2:$A$400,"GROUP") | D52: =SUMIFS(Meta!$G$2:$G$400,Meta!$F$2:$F$400,"t3_share",Meta!$D$2:$D$400,D$3,Meta!$A$2:$A$400,"GROUP") | E52: =SUMIFS(Meta!$G$2:$G$400,Meta!$F$2:$F$400,"t3_share",Meta!$D$2:$D$400,E$3,Meta!$A$2:$A$400,"GROUP") | F52: =SUMIFS(Meta!$G$2:$G$400,Meta!$F$2:$F$400,"t3_share",Meta!$D$2:$D$400,F$3,Meta!$A$2:$A$400,"GROUP") | G52: =SUMIFS(Meta!$G$2:$G$400,Meta!$F$2:$F$400,"t3_share",Meta!$D$2:$D$400,G$3,Meta!$A$2:$A$400,"GROUP")
A53: T3 云内部毛利率 | B53: 内部利润随互联对外收入实现 | C53: =SUMIFS(Meta!$G$2:$G$400,Meta!$F$2:$F$400,"t3_gm",Meta!$D$2:$D$400,C$3,Meta!$A$2:$A$400,"GROUP") | D53: =SUMIFS(Meta!$G$2:$G$400,Meta!$F$2:$F$400,"t3_gm",Meta!$D$2:$D$400,D$3,Meta!$A$2:$A$400,"GROUP") | E53: =SUMIFS(Meta!$G$2:$G$400,Meta!$F$2:$F$400,"t3_gm",Meta!$D$2:$D$400,E$3,Meta!$A$2:$A$400,"GROUP") | F53: =SUMIFS(Meta!$G$2:$G$400,Meta!$F$2:$F$400,"t3_gm",Meta!$D$2:$D$400,F$3,Meta!$A$2:$A$400,"GROUP") | G53: =SUMIFS(Meta!$G$2:$G$400,Meta!$F$2:$F$400,"t3_gm",Meta!$D$2:$D$400,G$3,Meta!$A$2:$A$400,"GROUP")
A54: cut-off 在途（互联已确认/云未开票） | B54: 仅2027年末演示 | C54: =SUMIFS(Meta!$G$2:$G$400,Meta!$F$2:$F$400,"cutoff_2027",Meta!$D$2:$D$400,C$3,Meta!$A$2:$A$400,"GROUP") | D54: =SUMIFS(Meta!$G$2:$G$400,Meta!$F$2:$F$400,"cutoff_2027",Meta!$D$2:$D$400,D$3,Meta!$A$2:$A$400,"GROUP") | E54: =SUMIFS(Meta!$G$2:$G$400,Meta!$F$2:$F$400,"cutoff_2027",Meta!$D$2:$D$400,E$3,Meta!$A$2:$A$400,"GROUP") | F54: =SUMIFS(Meta!$G$2:$G$400,Meta!$F$2:$F$400,"cutoff_2027",Meta!$D$2:$D$400,F$3,Meta!$A$2:$A$400,"GROUP") | G54: =SUMIFS(Meta!$G$2:$G$400,Meta!$F$2:$F$400,"cutoff_2027",Meta!$D$2:$D$400,G$3,Meta!$A$2:$A$400,"GROUP")
A55: ── 股权融资计划（当年新增注资）──
A56: 研究院（老股东直接增资） | C56: =SUMIFS(Meta!$G$2:$G$400,Meta!$F$2:$F$400,"equity_inject",Meta!$D$2:$D$400,C$3,Meta!$A$2:$A$400,"HOLD") | D56: =SUMIFS(Meta!$G$2:$G$400,Meta!$F$2:$F$400,"equity_inject",Meta!$D$2:$D$400,D$3,Meta!$A$2:$A$400,"HOLD") | E56: =SUMIFS(Meta!$G$2:$G$400,Meta!$F$2:$F$400,"equity_inject",Meta!$D$2:$D$400,E$3,Meta!$A$2:$A$400,"HOLD") | F56: =SUMIFS(Meta!$G$2:$G$400,Meta!$F$2:$F$400,"equity_inject",Meta!$D$2:$D$400,F$3,Meta!$A$2:$A$400,"HOLD") | G56: =SUMIFS(Meta!$G$2:$G$400,Meta!$F$2:$F$400,"equity_inject",Meta!$D$2:$D$400,G$3,Meta!$A$2:$A$400,"HOLD")
A57: 智擎云 | C57: =SUMIFS(Meta!$G$2:$G$400,Meta!$F$2:$F$400,"equity_inject",Meta!$D$2:$D$400,C$3,Meta!$A$2:$A$400,"CLOUD") | D57: =SUMIFS(Meta!$G$2:$G$400,Meta!$F$2:$F$400,"equity_inject",Meta!$D$2:$D$400,D$3,Meta!$A$2:$A$400,"CLOUD") | E57: =SUMIFS(Meta!$G$2:$G$400,Meta!$F$2:$F$400,"equity_inject",Meta!$D$2:$D$400,E$3,Meta!$A$2:$A$400,"CLOUD") | F57: =SUMIFS(Meta!$G$2:$G$400,Meta!$F$2:$F$400,"equity_inject",Meta!$D$2:$D$400,F$3,Meta!$A$2:$A$400,"CLOUD") | G57: =SUMIFS(Meta!$G$2:$G$400,Meta!$F$2:$F$400,"equity_inject",Meta!$D$2:$D$400,G$3,Meta!$A$2:$A$400,"CLOUD")
A58: 智擎行业 | C58: =SUMIFS(Meta!$G$2:$G$400,Meta!$F$2:$F$400,"equity_inject",Meta!$D$2:$D$400,C$3,Meta!$A$2:$A$400,"IND") | D58: =SUMIFS(Meta!$G$2:$G$400,Meta!$F$2:$F$400,"equity_inject",Meta!$D$2:$D$400,D$3,Meta!$A$2:$A$400,"IND") | E58: =SUMIFS(Meta!$G$2:$G$400,Meta!$F$2:$F$400,"equity_inject",Meta!$D$2:$D$400,E$3,Meta!$A$2:$A$400,"IND") | F58: =SUMIFS(Meta!$G$2:$G$400,Meta!$F$2:$F$400,"equity_inject",Meta!$D$2:$D$400,F$3,Meta!$A$2:$A$400,"IND") | G58: =SUMIFS(Meta!$G$2:$G$400,Meta!$F$2:$F$400,"equity_inject",Meta!$D$2:$D$400,G$3,Meta!$A$2:$A$400,"IND")
A59: 智擎互联（含战投20%） | C59: =SUMIFS(Meta!$G$2:$G$400,Meta!$F$2:$F$400,"equity_inject",Meta!$D$2:$D$400,C$3,Meta!$A$2:$A$400,"TOC") | D59: =SUMIFS(Meta!$G$2:$G$400,Meta!$F$2:$F$400,"equity_inject",Meta!$D$2:$D$400,D$3,Meta!$A$2:$A$400,"TOC") | E59: =SUMIFS(Meta!$G$2:$G$400,Meta!$F$2:$F$400,"equity_inject",Meta!$D$2:$D$400,E$3,Meta!$A$2:$A$400,"TOC") | F59: =SUMIFS(Meta!$G$2:$G$400,Meta!$F$2:$F$400,"equity_inject",Meta!$D$2:$D$400,F$3,Meta!$A$2:$A$400,"TOC") | G59: =SUMIFS(Meta!$G$2:$G$400,Meta!$F$2:$F$400,"equity_inject",Meta!$D$2:$D$400,G$3,Meta!$A$2:$A$400,"TOC")
A60: ── 收入地区拆分 ──
A61: 华东 占比 | C61: =SUMIFS(Meta!$G$2:$G$400,Meta!$F$2:$F$400,"region_mix",Meta!$D$2:$D$400,C$3,Meta!$A$2:$A$400,"GROUP",Meta!$C$2:$C$400,"华东") | D61: =SUMIFS(Meta!$G$2:$G$400,Meta!$F$2:$F$400,"region_mix",Meta!$D$2:$D$400,D$3,Meta!$A$2:$A$400,"GROUP",Meta!$C$2:$C$400,"华东") | E61: =SUMIFS(Meta!$G$2:$G$400,Meta!$F$2:$F$400,"region_mix",Meta!$D$2:$D$400,E$3,Meta!$A$2:$A$400,"GROUP",Meta!$C$2:$C$400,"华东") | F61: =SUMIFS(Meta!$G$2:$G$400,Meta!$F$2:$F$400,"region_mix",Meta!$D$2:$D$400,F$3,Meta!$A$2:$A$400,"GROUP",Meta!$C$2:$C$400,"华东") | G61: =SUMIFS(Meta!$G$2:$G$400,Meta!$F$2:$F$400,"region_mix",Meta!$D$2:$D$400,G$3,Meta!$A$2:$A$400,"GROUP",Meta!$C$2:$C$400,"华东")
A62: 华北 占比 | C62: =SUMIFS(Meta!$G$2:$G$400,Meta!$F$2:$F$400,"region_mix",Meta!$D$2:$D$400,C$3,Meta!$A$2:$A$400,"GROUP",Meta!$C$2:$C$400,"华北") | D62: =SUMIFS(Meta!$G$2:$G$400,Meta!$F$2:$F$400,"region_mix",Meta!$D$2:$D$400,D$3,Meta!$A$2:$A$400,"GROUP",Meta!$C$2:$C$400,"华北") | E62: =SUMIFS(Meta!$G$2:$G$400,Meta!$F$2:$F$400,"region_mix",Meta!$D$2:$D$400,E$3,Meta!$A$2:$A$400,"GROUP",Meta!$C$2:$C$400,"华北") | F62: =SUMIFS(Meta!$G$2:$G$400,Meta!$F$2:$F$400,"region_mix",Meta!$D$2:$D$400,F$3,Meta!$A$2:$A$400,"GROUP",Meta!$C$2:$C$400,"华北") | G62: =SUMIFS(Meta!$G$2:$G$400,Meta!$F$2:$F$400,"region_mix",Meta!$D$2:$D$400,G$3,Meta!$A$2:$A$400,"GROUP",Meta!$C$2:$C$400,"华北")
A63: 华南 占比 | C63: =SUMIFS(Meta!$G$2:$G$400,Meta!$F$2:$F$400,"region_mix",Meta!$D$2:$D$400,C$3,Meta!$A$2:$A$400,"GROUP",Meta!$C$2:$C$400,"华南") | D63: =SUMIFS(Meta!$G$2:$G$400,Meta!$F$2:$F$400,"region_mix",Meta!$D$2:$D$400,D$3,Meta!$A$2:$A$400,"GROUP",Meta!$C$2:$C$400,"华南") | E63: =SUMIFS(Meta!$G$2:$G$400,Meta!$F$2:$F$400,"region_mix",Meta!$D$2:$D$400,E$3,Meta!$A$2:$A$400,"GROUP",Meta!$C$2:$C$400,"华南") | F63: =SUMIFS(Meta!$G$2:$G$400,Meta!$F$2:$F$400,"region_mix",Meta!$D$2:$D$400,F$3,Meta!$A$2:$A$400,"GROUP",Meta!$C$2:$C$400,"华南") | G63: =SUMIFS(Meta!$G$2:$G$400,Meta!$F$2:$F$400,"region_mix",Meta!$D$2:$D$400,G$3,Meta!$A$2:$A$400,"GROUP",Meta!$C$2:$C$400,"华南")
A64: 海外 占比 | C64: =SUMIFS(Meta!$G$2:$G$400,Meta!$F$2:$F$400,"region_mix",Meta!$D$2:$D$400,C$3,Meta!$A$2:$A$400,"GROUP",Meta!$C$2:$C$400,"海外") | D64: =SUMIFS(Meta!$G$2:$G$400,Meta!$F$2:$F$400,"region_mix",Meta!$D$2:$D$400,D$3,Meta!$A$2:$A$400,"GROUP",Meta!$C$2:$C$400,"海外") | E64: =SUMIFS(Meta!$G$2:$G$400,Meta!$F$2:$F$400,"region_mix",Meta!$D$2:$D$400,E$3,Meta!$A$2:$A$400,"GROUP",Meta!$C$2:$C$400,"海外") | F64: =SUMIFS(Meta!$G$2:$G$400,Meta!$F$2:$F$400,"region_mix",Meta!$D$2:$D$400,F$3,Meta!$A$2:$A$400,"GROUP",Meta!$C$2:$C$400,"海外") | G64: =SUMIFS(Meta!$G$2:$G$400,Meta!$F$2:$F$400,"region_mix",Meta!$D$2:$D$400,G$3,Meta!$A$2:$A$400,"GROUP",Meta!$C$2:$C$400,"海外")
A65: ── 期初数（2023年初）──
A66: 智擎研究院 期初未分配利润 | C66: =SUMIFS(Meta!$G$2:$G$400,Meta!$F$2:$F$400,"open_re",Meta!$D$2:$D$400,C$3,Meta!$A$2:$A$400,"HOLD") | D66: =SUMIFS(Meta!$G$2:$G$400,Meta!$F$2:$F$400,"open_re",Meta!$D$2:$D$400,D$3,Meta!$A$2:$A$400,"HOLD") | E66: =SUMIFS(Meta!$G$2:$G$400,Meta!$F$2:$F$400,"open_re",Meta!$D$2:$D$400,E$3,Meta!$A$2:$A$400,"HOLD") | F66: =SUMIFS(Meta!$G$2:$G$400,Meta!$F$2:$F$400,"open_re",Meta!$D$2:$D$400,F$3,Meta!$A$2:$A$400,"HOLD") | G66: =SUMIFS(Meta!$G$2:$G$400,Meta!$F$2:$F$400,"open_re",Meta!$D$2:$D$400,G$3,Meta!$A$2:$A$400,"HOLD")
A67: 智擎研究院 期初实收资本 | C67: =SUMIFS(Meta!$G$2:$G$400,Meta!$F$2:$F$400,"open_pi",Meta!$D$2:$D$400,C$3,Meta!$A$2:$A$400,"HOLD") | D67: =SUMIFS(Meta!$G$2:$G$400,Meta!$F$2:$F$400,"open_pi",Meta!$D$2:$D$400,D$3,Meta!$A$2:$A$400,"HOLD") | E67: =SUMIFS(Meta!$G$2:$G$400,Meta!$F$2:$F$400,"open_pi",Meta!$D$2:$D$400,E$3,Meta!$A$2:$A$400,"HOLD") | F67: =SUMIFS(Meta!$G$2:$G$400,Meta!$F$2:$F$400,"open_pi",Meta!$D$2:$D$400,F$3,Meta!$A$2:$A$400,"HOLD") | G67: =SUMIFS(Meta!$G$2:$G$400,Meta!$F$2:$F$400,"open_pi",Meta!$D$2:$D$400,G$3,Meta!$A$2:$A$400,"HOLD")
A68: 智擎云 期初未分配利润 | C68: =SUMIFS(Meta!$G$2:$G$400,Meta!$F$2:$F$400,"open_re",Meta!$D$2:$D$400,C$3,Meta!$A$2:$A$400,"CLOUD") | D68: =SUMIFS(Meta!$G$2:$G$400,Meta!$F$2:$F$400,"open_re",Meta!$D$2:$D$400,D$3,Meta!$A$2:$A$400,"CLOUD") | E68: =SUMIFS(Meta!$G$2:$G$400,Meta!$F$2:$F$400,"open_re",Meta!$D$2:$D$400,E$3,Meta!$A$2:$A$400,"CLOUD") | F68: =SUMIFS(Meta!$G$2:$G$400,Meta!$F$2:$F$400,"open_re",Meta!$D$2:$D$400,F$3,Meta!$A$2:$A$400,"CLOUD") | G68: =SUMIFS(Meta!$G$2:$G$400,Meta!$F$2:$F$400,"open_re",Meta!$D$2:$D$400,G$3,Meta!$A$2:$A$400,"CLOUD")
A69: 智擎云 期初实收资本 | C69: =SUMIFS(Meta!$G$2:$G$400,Meta!$F$2:$F$400,"open_pi",Meta!$D$2:$D$400,C$3,Meta!$A$2:$A$400,"CLOUD") | D69: =SUMIFS(Meta!$G$2:$G$400,Meta!$F$2:$F$400,"open_pi",Meta!$D$2:$D$400,D$3,Meta!$A$2:$A$400,"CLOUD") | E69: =SUMIFS(Meta!$G$2:$G$400,Meta!$F$2:$F$400,"open_pi",Meta!$D$2:$D$400,E$3,Meta!$A$2:$A$400,"CLOUD") | F69: =SUMIFS(Meta!$G$2:$G$400,Meta!$F$2:$F$400,"open_pi",Meta!$D$2:$D$400,F$3,Meta!$A$2:$A$400,"CLOUD") | G69: =SUMIFS(Meta!$G$2:$G$400,Meta!$F$2:$F$400,"open_pi",Meta!$D$2:$D$400,G$3,Meta!$A$2:$A$400,"CLOUD")
A70: 智擎行业 期初未分配利润 | C70: =SUMIFS(Meta!$G$2:$G$400,Meta!$F$2:$F$400,"open_re",Meta!$D$2:$D$400,C$3,Meta!$A$2:$A$400,"IND") | D70: =SUMIFS(Meta!$G$2:$G$400,Meta!$F$2:$F$400,"open_re",Meta!$D$2:$D$400,D$3,Meta!$A$2:$A$400,"IND") | E70: =SUMIFS(Meta!$G$2:$G$400,Meta!$F$2:$F$400,"open_re",Meta!$D$2:$D$400,E$3,Meta!$A$2:$A$400,"IND") | F70: =SUMIFS(Meta!$G$2:$G$400,Meta!$F$2:$F$400,"open_re",Meta!$D$2:$D$400,F$3,Meta!$A$2:$A$400,"IND") | G70: =SUMIFS(Meta!$G$2:$G$400,Meta!$F$2:$F$400,"open_re",Meta!$D$2:$D$400,G$3,Meta!$A$2:$A$400,"IND")
A71: 智擎行业 期初实收资本 | C71: =SUMIFS(Meta!$G$2:$G$400,Meta!$F$2:$F$400,"open_pi",Meta!$D$2:$D$400,C$3,Meta!$A$2:$A$400,"IND") | D71: =SUMIFS(Meta!$G$2:$G$400,Meta!$F$2:$F$400,"open_pi",Meta!$D$2:$D$400,D$3,Meta!$A$2:$A$400,"IND") | E71: =SUMIFS(Meta!$G$2:$G$400,Meta!$F$2:$F$400,"open_pi",Meta!$D$2:$D$400,E$3,Meta!$A$2:$A$400,"IND") | F71: =SUMIFS(Meta!$G$2:$G$400,Meta!$F$2:$F$400,"open_pi",Meta!$D$2:$D$400,F$3,Meta!$A$2:$A$400,"IND") | G71: =SUMIFS(Meta!$G$2:$G$400,Meta!$F$2:$F$400,"open_pi",Meta!$D$2:$D$400,G$3,Meta!$A$2:$A$400,"IND")
A72: 智擎互联 期初未分配利润 | C72: =SUMIFS(Meta!$G$2:$G$400,Meta!$F$2:$F$400,"open_re",Meta!$D$2:$D$400,C$3,Meta!$A$2:$A$400,"TOC") | D72: =SUMIFS(Meta!$G$2:$G$400,Meta!$F$2:$F$400,"open_re",Meta!$D$2:$D$400,D$3,Meta!$A$2:$A$400,"TOC") | E72: =SUMIFS(Meta!$G$2:$G$400,Meta!$F$2:$F$400,"open_re",Meta!$D$2:$D$400,E$3,Meta!$A$2:$A$400,"TOC") | F72: =SUMIFS(Meta!$G$2:$G$400,Meta!$F$2:$F$400,"open_re",Meta!$D$2:$D$400,F$3,Meta!$A$2:$A$400,"TOC") | G72: =SUMIFS(Meta!$G$2:$G$400,Meta!$F$2:$F$400,"open_re",Meta!$D$2:$D$400,G$3,Meta!$A$2:$A$400,"TOC")
A73: 智擎互联 期初实收资本 | C73: =SUMIFS(Meta!$G$2:$G$400,Meta!$F$2:$F$400,"open_pi",Meta!$D$2:$D$400,C$3,Meta!$A$2:$A$400,"TOC") | D73: =SUMIFS(Meta!$G$2:$G$400,Meta!$F$2:$F$400,"open_pi",Meta!$D$2:$D$400,D$3,Meta!$A$2:$A$400,"TOC") | E73: =SUMIFS(Meta!$G$2:$G$400,Meta!$F$2:$F$400,"open_pi",Meta!$D$2:$D$400,E$3,Meta!$A$2:$A$400,"TOC") | F73: =SUMIFS(Meta!$G$2:$G$400,Meta!$F$2:$F$400,"open_pi",Meta!$D$2:$D$400,F$3,Meta!$A$2:$A$400,"TOC") | G73: =SUMIFS(Meta!$G$2:$G$400,Meta!$F$2:$F$400,"open_pi",Meta!$D$2:$D$400,G$3,Meta!$A$2:$A$400,"TOC")
A74: 研究院期初 GPU 原值 | B74: 并入2023批次 | C74: =SUMIFS(Meta!$G$2:$G$400,Meta!$F$2:$F$400,"open_fa",Meta!$D$2:$D$400,C$3,Meta!$A$2:$A$400,"HOLD") | D74: =SUMIFS(Meta!$G$2:$G$400,Meta!$F$2:$F$400,"open_fa",Meta!$D$2:$D$400,D$3,Meta!$A$2:$A$400,"HOLD") | E74: =SUMIFS(Meta!$G$2:$G$400,Meta!$F$2:$F$400,"open_fa",Meta!$D$2:$D$400,E$3,Meta!$A$2:$A$400,"HOLD") | F74: =SUMIFS(Meta!$G$2:$G$400,Meta!$F$2:$F$400,"open_fa",Meta!$D$2:$D$400,F$3,Meta!$A$2:$A$400,"HOLD") | G74: =SUMIFS(Meta!$G$2:$G$400,Meta!$F$2:$F$400,"open_fa",Meta!$D$2:$D$400,G$3,Meta!$A$2:$A$400,"HOLD")
A75: 智擎云期初 GPU 原值 | B75: 并入2023批次 | C75: =SUMIFS(Meta!$G$2:$G$400,Meta!$F$2:$F$400,"open_fa",Meta!$D$2:$D$400,C$3,Meta!$A$2:$A$400,"CLOUD") | D75: =SUMIFS(Meta!$G$2:$G$400,Meta!$F$2:$F$400,"open_fa",Meta!$D$2:$D$400,D$3,Meta!$A$2:$A$400,"CLOUD") | E75: =SUMIFS(Meta!$G$2:$G$400,Meta!$F$2:$F$400,"open_fa",Meta!$D$2:$D$400,E$3,Meta!$A$2:$A$400,"CLOUD") | F75: =SUMIFS(Meta!$G$2:$G$400,Meta!$F$2:$F$400,"open_fa",Meta!$D$2:$D$400,F$3,Meta!$A$2:$A$400,"CLOUD") | G75: =SUMIFS(Meta!$G$2:$G$400,Meta!$F$2:$F$400,"open_fa",Meta!$D$2:$D$400,G$3,Meta!$A$2:$A$400,"CLOUD")
A76: 研究院期初长投合计 | C76: =SUMIFS(Meta!$G$2:$G$400,Meta!$F$2:$F$400,"open_lt_inv",Meta!$D$2:$D$400,C$3,Meta!$A$2:$A$400,"HOLD") | D76: =SUMIFS(Meta!$G$2:$G$400,Meta!$F$2:$F$400,"open_lt_inv",Meta!$D$2:$D$400,D$3,Meta!$A$2:$A$400,"HOLD") | E76: =SUMIFS(Meta!$G$2:$G$400,Meta!$F$2:$F$400,"open_lt_inv",Meta!$D$2:$D$400,E$3,Meta!$A$2:$A$400,"HOLD") | F76: =SUMIFS(Meta!$G$2:$G$400,Meta!$F$2:$F$400,"open_lt_inv",Meta!$D$2:$D$400,F$3,Meta!$A$2:$A$400,"HOLD") | G76: =SUMIFS(Meta!$G$2:$G$400,Meta!$F$2:$F$400,"open_lt_inv",Meta!$D$2:$D$400,G$3,Meta!$A$2:$A$400,"HOLD")
A77: 智擎云 递延收入率 | B77: 期末递延/当年收入 | C77: =SUMIFS(Meta!$G$2:$G$400,Meta!$F$2:$F$400,"deferred_rate",Meta!$D$2:$D$400,C$3,Meta!$A$2:$A$400,"CLOUD") | D77: =SUMIFS(Meta!$G$2:$G$400,Meta!$F$2:$F$400,"deferred_rate",Meta!$D$2:$D$400,D$3,Meta!$A$2:$A$400,"CLOUD") | E77: =SUMIFS(Meta!$G$2:$G$400,Meta!$F$2:$F$400,"deferred_rate",Meta!$D$2:$D$400,E$3,Meta!$A$2:$A$400,"CLOUD") | F77: =SUMIFS(Meta!$G$2:$G$400,Meta!$F$2:$F$400,"deferred_rate",Meta!$D$2:$D$400,F$3,Meta!$A$2:$A$400,"CLOUD") | G77: =SUMIFS(Meta!$G$2:$G$400,Meta!$F$2:$F$400,"deferred_rate",Meta!$D$2:$D$400,G$3,Meta!$A$2:$A$400,"CLOUD")
A78: 智擎行业 递延收入率 | B78: 期末递延/当年收入 | C78: =SUMIFS(Meta!$G$2:$G$400,Meta!$F$2:$F$400,"deferred_rate",Meta!$D$2:$D$400,C$3,Meta!$A$2:$A$400,"IND") | D78: =SUMIFS(Meta!$G$2:$G$400,Meta!$F$2:$F$400,"deferred_rate",Meta!$D$2:$D$400,D$3,Meta!$A$2:$A$400,"IND") | E78: =SUMIFS(Meta!$G$2:$G$400,Meta!$F$2:$F$400,"deferred_rate",Meta!$D$2:$D$400,E$3,Meta!$A$2:$A$400,"IND") | F78: =SUMIFS(Meta!$G$2:$G$400,Meta!$F$2:$F$400,"deferred_rate",Meta!$D$2:$D$400,F$3,Meta!$A$2:$A$400,"IND") | G78: =SUMIFS(Meta!$G$2:$G$400,Meta!$F$2:$F$400,"deferred_rate",Meta!$D$2:$D$400,G$3,Meta!$A$2:$A$400,"IND")
A79: 智擎互联 递延收入率 | B79: 期末递延/当年收入 | C79: =SUMIFS(Meta!$G$2:$G$400,Meta!$F$2:$F$400,"deferred_rate",Meta!$D$2:$D$400,C$3,Meta!$A$2:$A$400,"TOC") | D79: =SUMIFS(Meta!$G$2:$G$400,Meta!$F$2:$F$400,"deferred_rate",Meta!$D$2:$D$400,D$3,Meta!$A$2:$A$400,"TOC") | E79: =SUMIFS(Meta!$G$2:$G$400,Meta!$F$2:$F$400,"deferred_rate",Meta!$D$2:$D$400,E$3,Meta!$A$2:$A$400,"TOC") | F79: =SUMIFS(Meta!$G$2:$G$400,Meta!$F$2:$F$400,"deferred_rate",Meta!$D$2:$D$400,F$3,Meta!$A$2:$A$400,"TOC") | G79: =SUMIFS(Meta!$G$2:$G$400,Meta!$F$2:$F$400,"deferred_rate",Meta!$D$2:$D$400,G$3,Meta!$A$2:$A$400,"TOC")

Sheet Capex_Dep
A1: GPU 资本开支与折旧引擎
A2: 批次法：购置当年起 5 年直线 | 大模型公司的资产负债表灵魂
A3: 科目（万元） | B3: 备注 | C3: 2023 | D3: 2024 | E3: 2025 | F3: 2026 | G3: 2027
A4: ── 采购计划（取自 Meta）──
A5: 训练 GPU 采购（研究院） | B5: 含期初存量并入2023批 | C5: =SUMIFS(Meta!$G$2:$G$400,Meta!$F$2:$F$400,"capex_gpu",Meta!$D$2:$D$400,C$3,Meta!$A$2:$A$400,"HOLD") | D5: =SUMIFS(Meta!$G$2:$G$400,Meta!$F$2:$F$400,"capex_gpu",Meta!$D$2:$D$400,D$3,Meta!$A$2:$A$400,"HOLD") | E5: =SUMIFS(Meta!$G$2:$G$400,Meta!$F$2:$F$400,"capex_gpu",Meta!$D$2:$D$400,E$3,Meta!$A$2:$A$400,"HOLD") | F5: =SUMIFS(Meta!$G$2:$G$400,Meta!$F$2:$F$400,"capex_gpu",Meta!$D$2:$D$400,F$3,Meta!$A$2:$A$400,"HOLD") | G5: =SUMIFS(Meta!$G$2:$G$400,Meta!$F$2:$F$400,"capex_gpu",Meta!$D$2:$D$400,G$3,Meta!$A$2:$A$400,"HOLD")
A6: 推理 GPU 采购（智擎云） | C6: =SUMIFS(Meta!$G$2:$G$400,Meta!$F$2:$F$400,"capex_gpu",Meta!$D$2:$D$400,C$3,Meta!$A$2:$A$400,"CLOUD") | D6: =SUMIFS(Meta!$G$2:$G$400,Meta!$F$2:$F$400,"capex_gpu",Meta!$D$2:$D$400,D$3,Meta!$A$2:$A$400,"CLOUD") | E6: =SUMIFS(Meta!$G$2:$G$400,Meta!$F$2:$F$400,"capex_gpu",Meta!$D$2:$D$400,E$3,Meta!$A$2:$A$400,"CLOUD") | F6: =SUMIFS(Meta!$G$2:$G$400,Meta!$F$2:$F$400,"capex_gpu",Meta!$D$2:$D$400,F$3,Meta!$A$2:$A$400,"CLOUD") | G6: =SUMIFS(Meta!$G$2:$G$400,Meta!$F$2:$F$400,"capex_gpu",Meta!$D$2:$D$400,G$3,Meta!$A$2:$A$400,"CLOUD")
A8: ── 批次折旧明细（H列=批次原值[取自Meta]，B列=购置年）──
A9: 训练卡 2023批 | B9: 2023 | C9: =IF(AND(C$3>=$B9,C$3<$B9+5),$H9/5,0) | D9: =IF(AND(D$3>=$B9,D$3<$B9+5),$H9/5,0) | E9: =IF(AND(E$3>=$B9,E$3<$B9+5),$H9/5,0) | F9: =IF(AND(F$3>=$B9,F$3<$B9+5),$H9/5,0) | G9: =IF(AND(G$3>=$B9,G$3<$B9+5),$H9/5,0) | H9: =SUMIFS(Meta!$G$2:$G$400,Meta!$F$2:$F$400,"open_fa",Meta!$D$2:$D$400,C$3,Meta!$A$2:$A$400,"HOLD")+SUMIFS(Meta!$G$2:$G$400,Meta!$F$2:$F$400,"capex_gpu",Meta!$D$2:$D$400,C$3,Meta!$A$2:$A$400,"HOLD")
A10: 训练卡 2024批 | B10: 2024 | C10: =IF(AND(C$3>=$B10,C$3<$B10+5),$H10/5,0) | D10: =IF(AND(D$3>=$B10,D$3<$B10+5),$H10/5,0) | E10: =IF(AND(E$3>=$B10,E$3<$B10+5),$H10/5,0) | F10: =IF(AND(F$3>=$B10,F$3<$B10+5),$H10/5,0) | G10: =IF(AND(G$3>=$B10,G$3<$B10+5),$H10/5,0) | H10: =SUMIFS(Meta!$G$2:$G$400,Meta!$F$2:$F$400,"capex_gpu",Meta!$D$2:$D$400,D$3,Meta!$A$2:$A$400,"HOLD")
A11: 训练卡 2025批 | B11: 2025 | C11: =IF(AND(C$3>=$B11,C$3<$B11+5),$H11/5,0) | D11: =IF(AND(D$3>=$B11,D$3<$B11+5),$H11/5,0) | E11: =IF(AND(E$3>=$B11,E$3<$B11+5),$H11/5,0) | F11: =IF(AND(F$3>=$B11,F$3<$B11+5),$H11/5,0) | G11: =IF(AND(G$3>=$B11,G$3<$B11+5),$H11/5,0) | H11: =SUMIFS(Meta!$G$2:$G$400,Meta!$F$2:$F$400,"capex_gpu",Meta!$D$2:$D$400,E$3,Meta!$A$2:$A$400,"HOLD")
A12: 训练卡 2026批 | B12: 2026 | C12: =IF(AND(C$3>=$B12,C$3<$B12+5),$H12/5,0) | D12: =IF(AND(D$3>=$B12,D$3<$B12+5),$H12/5,0) | E12: =IF(AND(E$3>=$B12,E$3<$B12+5),$H12/5,0) | F12: =IF(AND(F$3>=$B12,F$3<$B12+5),$H12/5,0) | G12: =IF(AND(G$3>=$B12,G$3<$B12+5),$H12/5,0) | H12: =SUMIFS(Meta!$G$2:$G$400,Meta!$F$2:$F$400,"capex_gpu",Meta!$D$2:$D$400,F$3,Meta!$A$2:$A$400,"HOLD")
A13: 训练卡 2027批 | B13: 2027 | C13: =IF(AND(C$3>=$B13,C$3<$B13+5),$H13/5,0) | D13: =IF(AND(D$3>=$B13,D$3<$B13+5),$H13/5,0) | E13: =IF(AND(E$3>=$B13,E$3<$B13+5),$H13/5,0) | F13: =IF(AND(F$3>=$B13,F$3<$B13+5),$H13/5,0) | G13: =IF(AND(G$3>=$B13,G$3<$B13+5),$H13/5,0) | H13: =SUMIFS(Meta!$G$2:$G$400,Meta!$F$2:$F$400,"capex_gpu",Meta!$D$2:$D$400,G$3,Meta!$A$2:$A$400,"HOLD")
A15: 推理卡 2023批 | B15: 2023 | C15: =IF(AND(C$3>=$B15,C$3<$B15+5),$H15/5,0) | D15: =IF(AND(D$3>=$B15,D$3<$B15+5),$H15/5,0) | E15: =IF(AND(E$3>=$B15,E$3<$B15+5),$H15/5,0) | F15: =IF(AND(F$3>=$B15,F$3<$B15+5),$H15/5,0) | G15: =IF(AND(G$3>=$B15,G$3<$B15+5),$H15/5,0) | H15: =SUMIFS(Meta!$G$2:$G$400,Meta!$F$2:$F$400,"open_fa",Meta!$D$2:$D$400,C$3,Meta!$A$2:$A$400,"CLOUD")+SUMIFS(Meta!$G$2:$G$400,Meta!$F$2:$F$400,"capex_gpu",Meta!$D$2:$D$400,C$3,Meta!$A$2:$A$400,"CLOUD")
A16: 推理卡 2024批 | B16: 2024 | C16: =IF(AND(C$3>=$B16,C$3<$B16+5),$H16/5,0) | D16: =IF(AND(D$3>=$B16,D$3<$B16+5),$H16/5,0) | E16: =IF(AND(E$3>=$B16,E$3<$B16+5),$H16/5,0) | F16: =IF(AND(F$3>=$B16,F$3<$B16+5),$H16/5,0) | G16: =IF(AND(G$3>=$B16,G$3<$B16+5),$H16/5,0) | H16: =SUMIFS(Meta!$G$2:$G$400,Meta!$F$2:$F$400,"capex_gpu",Meta!$D$2:$D$400,D$3,Meta!$A$2:$A$400,"CLOUD")
A17: 推理卡 2025批 | B17: 2025 | C17: =IF(AND(C$3>=$B17,C$3<$B17+5),$H17/5,0) | D17: =IF(AND(D$3>=$B17,D$3<$B17+5),$H17/5,0) | E17: =IF(AND(E$3>=$B17,E$3<$B17+5),$H17/5,0) | F17: =IF(AND(F$3>=$B17,F$3<$B17+5),$H17/5,0) | G17: =IF(AND(G$3>=$B17,G$3<$B17+5),$H17/5,0) | H17: =SUMIFS(Meta!$G$2:$G$400,Meta!$F$2:$F$400,"capex_gpu",Meta!$D$2:$D$400,E$3,Meta!$A$2:$A$400,"CLOUD")
A18: 推理卡 2026批 | B18: 2026 | C18: =IF(AND(C$3>=$B18,C$3<$B18+5),$H18/5,0) | D18: =IF(AND(D$3>=$B18,D$3<$B18+5),$H18/5,0) | E18: =IF(AND(E$3>=$B18,E$3<$B18+5),$H18/5,0) | F18: =IF(AND(F$3>=$B18,F$3<$B18+5),$H18/5,0) | G18: =IF(AND(G$3>=$B18,G$3<$B18+5),$H18/5,0) | H18: =SUMIFS(Meta!$G$2:$G$400,Meta!$F$2:$F$400,"capex_gpu",Meta!$D$2:$D$400,F$3,Meta!$A$2:$A$400,"CLOUD")
A19: 推理卡 2027批 | B19: 2027 | C19: =IF(AND(C$3>=$B19,C$3<$B19+5),$H19/5,0) | D19: =IF(AND(D$3>=$B19,D$3<$B19+5),$H19/5,0) | E19: =IF(AND(E$3>=$B19,E$3<$B19+5),$H19/5,0) | F19: =IF(AND(F$3>=$B19,F$3<$B19+5),$H19/5,0) | G19: =IF(AND(G$3>=$B19,G$3<$B19+5),$H19/5,0) | H19: =SUMIFS(Meta!$G$2:$G$400,Meta!$F$2:$F$400,"capex_gpu",Meta!$D$2:$D$400,G$3,Meta!$A$2:$A$400,"CLOUD")
A21: ── 汇总 ──
A22: 训练 GPU 当年折旧 | B22: → 研究院研发费用 | C22: =SUM(C9:C13) | D22: =SUM(D9:D13) | E22: =SUM(E9:E13) | F22: =SUM(F9:F13) | G22: =SUM(G9:G13)
A23: 训练 GPU 净值 | B23: → 研究院 BS | C23: =SUMIFS($H$9:$H$13,$B$9:$B$13,"<="&C$3)-SUM($C$22:C22) | D23: =SUMIFS($H$9:$H$13,$B$9:$B$13,"<="&D$3)-SUM($C$22:D22) | E23: =SUMIFS($H$9:$H$13,$B$9:$B$13,"<="&E$3)-SUM($C$22:E22) | F23: =SUMIFS($H$9:$H$13,$B$9:$B$13,"<="&F$3)-SUM($C$22:F22) | G23: =SUMIFS($H$9:$H$13,$B$9:$B$13,"<="&G$3)-SUM($C$22:G22)
A24: 推理 GPU 当年折旧 | B24: → 智擎云 COGS 构成 | C24: =SUM(C15:C19) | D24: =SUM(D15:D19) | E24: =SUM(E15:E19) | F24: =SUM(F15:F19) | G24: =SUM(G15:G19)
A25: 推理 GPU 净值 | B25: → 智擎云 BS | C25: =SUMIFS($H$15:$H$19,$B$15:$B$19,"<="&C$3)-SUM($C$24:C24) | D25: =SUMIFS($H$15:$H$19,$B$15:$B$19,"<="&D$3)-SUM($C$24:D24) | E25: =SUMIFS($H$15:$H$19,$B$15:$B$19,"<="&E$3)-SUM($C$24:E24) | F25: =SUMIFS($H$15:$H$19,$B$15:$B$19,"<="&F$3)-SUM($C$24:F24) | G25: =SUMIFS($H$15:$H$19,$B$15:$B$19,"<="&G$3)-SUM($C$24:G24)
A27: ★ 引擎自检（折旧/净值 vs 影子值，应全 0）
A28: diff DEP_TRAIN | B28: 绿=0 | C28: =C22-(17000.000000) | D28: =D22-(29000.000000) | E28: =E22-(35000.000000) | F28: =F22-(38000.000000) | G28: =G22-(41000.000000)
A29: diff NET_TRAIN | B29: 绿=0 | C29: =C23-(68000.000000) | D29: =D23-(99000.000000) | E29: =E23-(94000.000000) | F29: =F23-(71000.000000) | G29: =G23-(45000.000000)
A30: diff DEP_INFER | B30: 绿=0 | C30: =C24-(7000.000000) | D30: =D24-(13000.000000) | E30: =E24-(19000.000000) | F30: =F24-(22000.000000) | G30: =G24-(24000.000000)
A31: diff NET_INFER | B31: 绿=0 | C31: =C25-(28000.000000) | D31: =D25-(45000.000000) | E31: =E25-(56000.000000) | F31: =F25-(49000.000000) | G31: =G25-(35000.000000)

Sheet Cloud_IS
A1: 智擎云 · 利润表
A2: 单体 | MaaS API：token 量 × 单价 | 万元
A3: 科目（万元） | B3: 备注 | C3: 2023 | D3: 2024 | E3: 2025 | F3: 2026 | G3: 2027
A4: 对外收入 · MaaS API | B4: 日均token×365×单价/1000 | C4: =Assumptions!C11*36.5*Assumptions!C12 | D4: =Assumptions!D11*36.5*Assumptions!D12 | E4: =Assumptions!E11*36.5*Assumptions!E12 | F4: =Assumptions!F11*36.5*Assumptions!F12 | G4: =Assumptions!G11*36.5*Assumptions!G12
A5: 关联收入 · T3 算力服务（互联） | B5: 互联推理成本×70% | C5: =Assumptions!C31*Assumptions!C35*12*Assumptions!C52 | D5: =Assumptions!D31*Assumptions!D35*12*Assumptions!D52 | E5: =Assumptions!E31*Assumptions!E35*12*Assumptions!E52 | F5: =Assumptions!F31*Assumptions!F35*12*Assumptions!F52 | G5: =Assumptions!G31*Assumptions!G35*12*Assumptions!G52
A6: 营业收入合计 | C6: =Cloud_IS!C4+Cloud_IS!C5 | D6: =Cloud_IS!D4+Cloud_IS!D5 | E6: =Cloud_IS!E4+Cloud_IS!E5 | F6: =Cloud_IS!F4+Cloud_IS!F5 | G6: =Cloud_IS!G4+Cloud_IS!G5
A7: 成本 · 推理算力（对外部分） | C7: =Assumptions!C11*36.5*Assumptions!C13 | D7: =Assumptions!D11*36.5*Assumptions!D13 | E7: =Assumptions!E11*36.5*Assumptions!E13 | F7: =Assumptions!F11*36.5*Assumptions!F13 | G7: =Assumptions!G11*36.5*Assumptions!G13
A8: 成本 · T3 服务成本 | B8: 内部价毛利率45% | C8: =Cloud_IS!C5*(1-Assumptions!C53) | D8: =Cloud_IS!D5*(1-Assumptions!D53) | E8: =Cloud_IS!E5*(1-Assumptions!E53) | F8: =Cloud_IS!F5*(1-Assumptions!F53) | G8: =Cloud_IS!G5*(1-Assumptions!G53)
A9: 成本 · 带宽机房 | C9: =Assumptions!C14 | D9: =Assumptions!D14 | E9: =Assumptions!E14 | F9: =Assumptions!F14 | G9: =Assumptions!G14
A10: 成本 · T1 license 费 | C10: =Cloud_IS!C4*Assumptions!C48 | D10: =Cloud_IS!D4*Assumptions!D48 | E10: =Cloud_IS!E4*Assumptions!E48 | F10: =Cloud_IS!F4*Assumptions!F48 | G10: =Cloud_IS!G4*Assumptions!G48
A11: 营业成本合计 | C11: =SUM(Cloud_IS!C7,Cloud_IS!C8,Cloud_IS!C9,Cloud_IS!C10) | D11: =SUM(Cloud_IS!D7,Cloud_IS!D8,Cloud_IS!D9,Cloud_IS!D10) | E11: =SUM(Cloud_IS!E7,Cloud_IS!E8,Cloud_IS!E9,Cloud_IS!E10) | F11: =SUM(Cloud_IS!F7,Cloud_IS!F8,Cloud_IS!F9,Cloud_IS!F10) | G11: =SUM(Cloud_IS!G7,Cloud_IS!G8,Cloud_IS!G9,Cloud_IS!G10)
A12: 毛利润 | C12: =Cloud_IS!C6-Cloud_IS!C11 | D12: =Cloud_IS!D6-Cloud_IS!D11 | E12: =Cloud_IS!E6-Cloud_IS!E11 | F12: =Cloud_IS!F6-Cloud_IS!F11 | G12: =Cloud_IS!G6-Cloud_IS!G11
A13: 研发费用 | B13: 编制×人均70万 | C13: =Assumptions!C15*70 | D13: =Assumptions!D15*70 | E13: =Assumptions!E15*70 | F13: =Assumptions!F15*70 | G13: =Assumptions!G15*70
A14: 销售费用 | B14: ×60万 | C14: =Assumptions!C16*60 | D14: =Assumptions!D16*60 | E14: =Assumptions!E16*60 | F14: =Assumptions!F16*60 | G14: =Assumptions!G16*60
A15: 管理费用 | B15: ×55万 | C15: =Assumptions!C17*55 | D15: =Assumptions!D17*55 | E15: =Assumptions!E17*55 | F15: =Assumptions!F17*55 | G15: =Assumptions!G17*55
A16: EBIT | C16: =Cloud_IS!C12-Cloud_IS!C13-Cloud_IS!C14-Cloud_IS!C15 | D16: =Cloud_IS!D12-Cloud_IS!D13-Cloud_IS!D14-Cloud_IS!D15 | E16: =Cloud_IS!E12-Cloud_IS!E13-Cloud_IS!E14-Cloud_IS!E15 | F16: =Cloud_IS!F12-Cloud_IS!F13-Cloud_IS!F14-Cloud_IS!F15 | G16: =Cloud_IS!G12-Cloud_IS!G13-Cloud_IS!G14-Cloud_IS!G15
A17: 所得税 | C17: =MAX(0,Cloud_IS!C16)*Assumptions!C5 | D17: =MAX(0,Cloud_IS!D16)*Assumptions!D5 | E17: =MAX(0,Cloud_IS!E16)*Assumptions!E5 | F17: =MAX(0,Cloud_IS!F16)*Assumptions!F5 | G17: =MAX(0,Cloud_IS!G16)*Assumptions!G5
A18: 净利润 | C18: =Cloud_IS!C16-Cloud_IS!C17 | D18: =Cloud_IS!D16-Cloud_IS!D17 | E18: =Cloud_IS!E16-Cloud_IS!E17 | F18: =Cloud_IS!F16-Cloud_IS!F17 | G18: =Cloud_IS!G16-Cloud_IS!G17

Sheet Cloud_BS_CF
A1: 智擎云 · 资产负债表+现金流量表
A2: 单体半厚 | BS在上 CF在下 | 万元
A3: 科目（万元） | B3: 备注 | C3: 2023 | D3: 2024 | E3: 2025 | F3: 2026 | G3: 2027
A4: ── 资产负债表（关键科目）──
A5: 应收账款 | C5: =Cloud_IS!C4*Assumptions!C6/365 | D5: =Cloud_IS!D4*Assumptions!D6/365 | E5: =Cloud_IS!E4*Assumptions!E6/365 | F5: =Cloud_IS!F4*Assumptions!F6/365 | G5: =Cloud_IS!G4*Assumptions!G6/365
A6: 内部应收（互联 T3） | B6: 2027 含 cut-off 未开票 −220 | C6: =(Assumptions!C31*Assumptions!C35*12*Assumptions!C52)*Assumptions!C8/365 | D6: =(Assumptions!D31*Assumptions!D35*12*Assumptions!D52)*Assumptions!D8/365 | E6: =(Assumptions!E31*Assumptions!E35*12*Assumptions!E52)*Assumptions!E8/365 | F6: =(Assumptions!F31*Assumptions!F35*12*Assumptions!F52)*Assumptions!F8/365 | G6: =(Assumptions!G31*Assumptions!G35*12*Assumptions!G52)*Assumptions!G8/365-Assumptions!G54
A7: 固定资产 · 推理 GPU 净值 | C7: =Capex_Dep!C25 | D7: =Capex_Dep!D25 | E7: =Capex_Dep!E25 | F7: =Capex_Dep!F25 | G7: =Capex_Dep!G25
A8: 非现金资产合计 | C8: =Cloud_BS_CF!C5+Cloud_BS_CF!C6+Cloud_BS_CF!C7 | D8: =Cloud_BS_CF!D5+Cloud_BS_CF!D6+Cloud_BS_CF!D7 | E8: =Cloud_BS_CF!E5+Cloud_BS_CF!E6+Cloud_BS_CF!E7 | F8: =Cloud_BS_CF!F5+Cloud_BS_CF!F6+Cloud_BS_CF!F7 | G8: =Cloud_BS_CF!G5+Cloud_BS_CF!G6+Cloud_BS_CF!G7
A9: 应付账款 | C9: =(Cloud_IS!C11+Cloud_IS!C13+Cloud_IS!C14+Cloud_IS!C15-Capex_Dep!C24)*Assumptions!C7/365 | D9: =(Cloud_IS!D11+Cloud_IS!D13+Cloud_IS!D14+Cloud_IS!D15-Capex_Dep!D24)*Assumptions!D7/365 | E9: =(Cloud_IS!E11+Cloud_IS!E13+Cloud_IS!E14+Cloud_IS!E15-Capex_Dep!E24)*Assumptions!E7/365 | F9: =(Cloud_IS!F11+Cloud_IS!F13+Cloud_IS!F14+Cloud_IS!F15-Capex_Dep!F24)*Assumptions!F7/365 | G9: =(Cloud_IS!G11+Cloud_IS!G13+Cloud_IS!G14+Cloud_IS!G15-Capex_Dep!G24)*Assumptions!G7/365
A10: 内部应付（研究院 T1） | C10: =Cloud_IS!C10*Assumptions!C8/365 | D10: =Cloud_IS!D10*Assumptions!D8/365 | E10: =Cloud_IS!E10*Assumptions!E8/365 | F10: =Cloud_IS!F10*Assumptions!F8/365 | G10: =Cloud_IS!G10*Assumptions!G8/365
A11: 递延收益 | C11: =Cloud_IS!C6*Assumptions!C77 | D11: =Cloud_IS!D6*Assumptions!D77 | E11: =Cloud_IS!E6*Assumptions!E77 | F11: =Cloud_IS!F6*Assumptions!F77 | G11: =Cloud_IS!G6*Assumptions!G77
A12: 负债合计 | C12: =Cloud_BS_CF!C9+Cloud_BS_CF!C10+Cloud_BS_CF!C11 | D12: =Cloud_BS_CF!D9+Cloud_BS_CF!D10+Cloud_BS_CF!D11 | E12: =Cloud_BS_CF!E9+Cloud_BS_CF!E10+Cloud_BS_CF!E11 | F12: =Cloud_BS_CF!F9+Cloud_BS_CF!F10+Cloud_BS_CF!F11 | G12: =Cloud_BS_CF!G9+Cloud_BS_CF!G10+Cloud_BS_CF!G11
A13: 实收资本 | C13: =Assumptions!C69+Assumptions!C57 | D13: =C13+Assumptions!D57 | E13: =D13+Assumptions!E57 | F13: =E13+Assumptions!F57 | G13: =F13+Assumptions!G57
A14: 未分配利润 | C14: =Assumptions!C68+Cloud_IS!C18 | D14: =C14+Cloud_IS!D18 | E14: =D14+Cloud_IS!E18 | F14: =E14+Cloud_IS!F18 | G14: =F14+Cloud_IS!G18
A15: 货币资金（倒挤） | C15: =Cloud_BS_CF!C12+Cloud_BS_CF!C13+Cloud_BS_CF!C14-Cloud_BS_CF!C8 | D15: =Cloud_BS_CF!D12+Cloud_BS_CF!D13+Cloud_BS_CF!D14-Cloud_BS_CF!D8 | E15: =Cloud_BS_CF!E12+Cloud_BS_CF!E13+Cloud_BS_CF!E14-Cloud_BS_CF!E8 | F15: =Cloud_BS_CF!F12+Cloud_BS_CF!F13+Cloud_BS_CF!F14-Cloud_BS_CF!F8 | G15: =Cloud_BS_CF!G12+Cloud_BS_CF!G13+Cloud_BS_CF!G14-Cloud_BS_CF!G8
A16: ── 现金流量表（间接法）──
A17: 净利润 | C17: =Cloud_IS!C18 | D17: =Cloud_IS!D18 | E17: =Cloud_IS!E18 | F17: =Cloud_IS!F18 | G17: =Cloud_IS!G18
A18: 加：折旧 | C18: =Capex_Dep!C24 | D18: =Capex_Dep!D24 | E18: =Capex_Dep!E24 | F18: =Capex_Dep!F24 | G18: =Capex_Dep!G24
A19: 减：应收增加 | C19: =-(Cloud_BS_CF!C5-(0)) | D19: =-(Cloud_BS_CF!D5-(Cloud_BS_CF!C5)) | E19: =-(Cloud_BS_CF!E5-(Cloud_BS_CF!D5)) | F19: =-(Cloud_BS_CF!F5-(Cloud_BS_CF!E5)) | G19: =-(Cloud_BS_CF!G5-(Cloud_BS_CF!F5))
A20: 内部往来净变动 | C20: =(Cloud_BS_CF!C10-(0))-(Cloud_BS_CF!C6-(0)) | D20: =(Cloud_BS_CF!D10-(Cloud_BS_CF!C10))-(Cloud_BS_CF!D6-(Cloud_BS_CF!C6)) | E20: =(Cloud_BS_CF!E10-(Cloud_BS_CF!D10))-(Cloud_BS_CF!E6-(Cloud_BS_CF!D6)) | F20: =(Cloud_BS_CF!F10-(Cloud_BS_CF!E10))-(Cloud_BS_CF!F6-(Cloud_BS_CF!E6)) | G20: =(Cloud_BS_CF!G10-(Cloud_BS_CF!F10))-(Cloud_BS_CF!G6-(Cloud_BS_CF!F6))
A21: 加：递延增加 | C21: =Cloud_BS_CF!C11-(0) | D21: =Cloud_BS_CF!D11-(Cloud_BS_CF!C11) | E21: =Cloud_BS_CF!E11-(Cloud_BS_CF!D11) | F21: =Cloud_BS_CF!F11-(Cloud_BS_CF!E11) | G21: =Cloud_BS_CF!G11-(Cloud_BS_CF!F11)
A22: 加：应付增加 | C22: =Cloud_BS_CF!C9-(0) | D22: =Cloud_BS_CF!D9-(Cloud_BS_CF!C9) | E22: =Cloud_BS_CF!E9-(Cloud_BS_CF!D9) | F22: =Cloud_BS_CF!F9-(Cloud_BS_CF!E9) | G22: =Cloud_BS_CF!G9-(Cloud_BS_CF!F9)
A23: 经营现金流 | C23: =Cloud_BS_CF!C17+Cloud_BS_CF!C18+Cloud_BS_CF!C19+Cloud_BS_CF!C20+Cloud_BS_CF!C21+Cloud_BS_CF!C22 | D23: =Cloud_BS_CF!D17+Cloud_BS_CF!D18+Cloud_BS_CF!D19+Cloud_BS_CF!D20+Cloud_BS_CF!D21+Cloud_BS_CF!D22 | E23: =Cloud_BS_CF!E17+Cloud_BS_CF!E18+Cloud_BS_CF!E19+Cloud_BS_CF!E20+Cloud_BS_CF!E21+Cloud_BS_CF!E22 | F23: =Cloud_BS_CF!F17+Cloud_BS_CF!F18+Cloud_BS_CF!F19+Cloud_BS_CF!F20+Cloud_BS_CF!F21+Cloud_BS_CF!F22 | G23: =Cloud_BS_CF!G17+Cloud_BS_CF!G18+Cloud_BS_CF!G19+Cloud_BS_CF!G20+Cloud_BS_CF!G21+Cloud_BS_CF!G22
A24: 投资现金流 | C24: =-Capex_Dep!C6 | D24: =-Capex_Dep!D6 | E24: =-Capex_Dep!E6 | F24: =-Capex_Dep!F6 | G24: =-Capex_Dep!G6
A25: 筹资：股权注资 | C25: =Assumptions!C57 | D25: =Assumptions!D57 | E25: =Assumptions!E57 | F25: =Assumptions!F57 | G25: =Assumptions!G57
A26: 现金净变动 | C26: =Cloud_BS_CF!C23+Cloud_BS_CF!C24+Cloud_BS_CF!C25 | D26: =Cloud_BS_CF!D23+Cloud_BS_CF!D24+Cloud_BS_CF!D25 | E26: =Cloud_BS_CF!E23+Cloud_BS_CF!E24+Cloud_BS_CF!E25 | F26: =Cloud_BS_CF!F23+Cloud_BS_CF!F24+Cloud_BS_CF!F25 | G26: =Cloud_BS_CF!G23+Cloud_BS_CF!G24+Cloud_BS_CF!G25
A27: 期末现金（CF） | C27: =10000+Cloud_BS_CF!C26 | D27: =C27+Cloud_BS_CF!D26 | E27: =D27+Cloud_BS_CF!E26 | F27: =E27+Cloud_BS_CF!F26 | G27: =F27+Cloud_BS_CF!G26
A28: ★ CF=BS 差异（应全 0）
A29: CF推导 − BS倒挤 | C29: =Cloud_BS_CF!C27-Cloud_BS_CF!C15 | D29: =Cloud_BS_CF!D27-Cloud_BS_CF!D15 | E29: =Cloud_BS_CF!E27-Cloud_BS_CF!E15 | F29: =Cloud_BS_CF!F27-Cloud_BS_CF!F15 | G29: =Cloud_BS_CF!G27-Cloud_BS_CF!G15

Sheet Ind_IS
A1: 智擎行业 · 利润表
A2: 单体 | 私有化部署 + 行业解决方案 双业务线 | 万元
A3: 科目（万元） | B3: 备注 | C3: 2023 | D3: 2024 | E3: 2025 | F3: 2026 | G3: 2027
A4: 收入 · 私有化部署 | B4: 项目数×合同额 | C4: =Assumptions!C21*Assumptions!C22 | D4: =Assumptions!D21*Assumptions!D22 | E4: =Assumptions!E21*Assumptions!E22 | F4: =Assumptions!F21*Assumptions!F22 | G4: =Assumptions!G21*Assumptions!G22
A5: 收入 · 行业解决方案 | B5: 签约客户×年费 | C5: =Assumptions!C23*Assumptions!C24 | D5: =Assumptions!D23*Assumptions!D24 | E5: =Assumptions!E23*Assumptions!E24 | F5: =Assumptions!F23*Assumptions!F24 | G5: =Assumptions!G23*Assumptions!G24
A6: 对外收入合计 | C6: =Ind_IS!C4+Ind_IS!C5 | D6: =Ind_IS!D4+Ind_IS!D5 | E6: =Ind_IS!E4+Ind_IS!E5 | F6: =Ind_IS!F4+Ind_IS!F5 | G6: =Ind_IS!G4+Ind_IS!G5
A7: 成本 · 私有化（硬件+人力） | C7: =Ind_IS!C4*Assumptions!C25 | D7: =Ind_IS!D4*Assumptions!D25 | E7: =Ind_IS!E4*Assumptions!E25 | F7: =Ind_IS!F4*Assumptions!F25 | G7: =Ind_IS!G4*Assumptions!G25
A8: 成本 · 解决方案 | C8: =Ind_IS!C5*Assumptions!C26 | D8: =Ind_IS!D5*Assumptions!D26 | E8: =Ind_IS!E5*Assumptions!E26 | F8: =Ind_IS!F5*Assumptions!F26 | G8: =Ind_IS!G5*Assumptions!G26
A9: 成本 · T1 license 费 | C9: =Ind_IS!C6*Assumptions!C49 | D9: =Ind_IS!D6*Assumptions!D49 | E9: =Ind_IS!E6*Assumptions!E49 | F9: =Ind_IS!F6*Assumptions!F49 | G9: =Ind_IS!G6*Assumptions!G49
A10: 成本 · T2 定制研发 | C10: =Assumptions!C51 | D10: =Assumptions!D51 | E10: =Assumptions!E51 | F10: =Assumptions!F51 | G10: =Assumptions!G51
A11: 营业成本合计 | C11: =SUM(Ind_IS!C7,Ind_IS!C8,Ind_IS!C9,Ind_IS!C10) | D11: =SUM(Ind_IS!D7,Ind_IS!D8,Ind_IS!D9,Ind_IS!D10) | E11: =SUM(Ind_IS!E7,Ind_IS!E8,Ind_IS!E9,Ind_IS!E10) | F11: =SUM(Ind_IS!F7,Ind_IS!F8,Ind_IS!F9,Ind_IS!F10) | G11: =SUM(Ind_IS!G7,Ind_IS!G8,Ind_IS!G9,Ind_IS!G10)
A12: 毛利润 | C12: =Ind_IS!C6-Ind_IS!C11 | D12: =Ind_IS!D6-Ind_IS!D11 | E12: =Ind_IS!E6-Ind_IS!E11 | F12: =Ind_IS!F6-Ind_IS!F11 | G12: =Ind_IS!G6-Ind_IS!G11
A13: 研发费用 | B13: ×70万 | C13: =Assumptions!C27*70 | D13: =Assumptions!D27*70 | E13: =Assumptions!E27*70 | F13: =Assumptions!F27*70 | G13: =Assumptions!G27*70
A14: 销售费用 | B14: ×60万 | C14: =Assumptions!C28*60 | D14: =Assumptions!D28*60 | E14: =Assumptions!E28*60 | F14: =Assumptions!F28*60 | G14: =Assumptions!G28*60
A15: 管理费用 | B15: ×55万 | C15: =Assumptions!C29*55 | D15: =Assumptions!D29*55 | E15: =Assumptions!E29*55 | F15: =Assumptions!F29*55 | G15: =Assumptions!G29*55
A16: EBIT | C16: =Ind_IS!C12-Ind_IS!C13-Ind_IS!C14-Ind_IS!C15 | D16: =Ind_IS!D12-Ind_IS!D13-Ind_IS!D14-Ind_IS!D15 | E16: =Ind_IS!E12-Ind_IS!E13-Ind_IS!E14-Ind_IS!E15 | F16: =Ind_IS!F12-Ind_IS!F13-Ind_IS!F14-Ind_IS!F15 | G16: =Ind_IS!G12-Ind_IS!G13-Ind_IS!G14-Ind_IS!G15
A17: 所得税 | C17: =MAX(0,Ind_IS!C16)*Assumptions!C5 | D17: =MAX(0,Ind_IS!D16)*Assumptions!D5 | E17: =MAX(0,Ind_IS!E16)*Assumptions!E5 | F17: =MAX(0,Ind_IS!F16)*Assumptions!F5 | G17: =MAX(0,Ind_IS!G16)*Assumptions!G5
A18: 净利润 | C18: =Ind_IS!C16-Ind_IS!C17 | D18: =Ind_IS!D16-Ind_IS!D17 | E18: =Ind_IS!E16-Ind_IS!E17 | F18: =Ind_IS!F16-Ind_IS!F17 | G18: =Ind_IS!G16-Ind_IS!G17

Sheet Ind_BS_CF
A1: 智擎行业 · 资产负债表+现金流量表
A2: 单体半厚 | 无 GPU 资产 | 万元
A3: 科目（万元） | B3: 备注 | C3: 2023 | D3: 2024 | E3: 2025 | F3: 2026 | G3: 2027
A4: ── 资产负债表（关键科目）──
A5: 应收账款 | C5: =Ind_IS!C6*Assumptions!C6/365 | D5: =Ind_IS!D6*Assumptions!D6/365 | E5: =Ind_IS!E6*Assumptions!E6/365 | F5: =Ind_IS!F6*Assumptions!F6/365 | G5: =Ind_IS!G6*Assumptions!G6/365
A6: 内部应付（T1+T2） | C6: =(Ind_IS!C9+Ind_IS!C10)*Assumptions!C8/365 | D6: =(Ind_IS!D9+Ind_IS!D10)*Assumptions!D8/365 | E6: =(Ind_IS!E9+Ind_IS!E10)*Assumptions!E8/365 | F6: =(Ind_IS!F9+Ind_IS!F10)*Assumptions!F8/365 | G6: =(Ind_IS!G9+Ind_IS!G10)*Assumptions!G8/365
A7: 应付账款 | B7: 无折旧 | C7: =(Ind_IS!C11+Ind_IS!C13+Ind_IS!C14+Ind_IS!C15)*Assumptions!C7/365 | D7: =(Ind_IS!D11+Ind_IS!D13+Ind_IS!D14+Ind_IS!D15)*Assumptions!D7/365 | E7: =(Ind_IS!E11+Ind_IS!E13+Ind_IS!E14+Ind_IS!E15)*Assumptions!E7/365 | F7: =(Ind_IS!F11+Ind_IS!F13+Ind_IS!F14+Ind_IS!F15)*Assumptions!F7/365 | G7: =(Ind_IS!G11+Ind_IS!G13+Ind_IS!G14+Ind_IS!G15)*Assumptions!G7/365
A8: 递延收益 | C8: =Ind_IS!C6*Assumptions!C78 | D8: =Ind_IS!D6*Assumptions!D78 | E8: =Ind_IS!E6*Assumptions!E78 | F8: =Ind_IS!F6*Assumptions!F78 | G8: =Ind_IS!G6*Assumptions!G78
A9: 负债合计 | C9: =Ind_BS_CF!C7+Ind_BS_CF!C6+Ind_BS_CF!C8 | D9: =Ind_BS_CF!D7+Ind_BS_CF!D6+Ind_BS_CF!D8 | E9: =Ind_BS_CF!E7+Ind_BS_CF!E6+Ind_BS_CF!E8 | F9: =Ind_BS_CF!F7+Ind_BS_CF!F6+Ind_BS_CF!F8 | G9: =Ind_BS_CF!G7+Ind_BS_CF!G6+Ind_BS_CF!G8
A10: 实收资本 | C10: =Assumptions!C71+Assumptions!C58 | D10: =C10+Assumptions!D58 | E10: =D10+Assumptions!E58 | F10: =E10+Assumptions!F58 | G10: =F10+Assumptions!G58
A11: 未分配利润 | C11: =Assumptions!C70+Ind_IS!C18 | D11: =C11+Ind_IS!D18 | E11: =D11+Ind_IS!E18 | F11: =E11+Ind_IS!F18 | G11: =F11+Ind_IS!G18
A12: 货币资金（倒挤） | C12: =Ind_BS_CF!C9+Ind_BS_CF!C10+Ind_BS_CF!C11-Ind_BS_CF!C5 | D12: =Ind_BS_CF!D9+Ind_BS_CF!D10+Ind_BS_CF!D11-Ind_BS_CF!D5 | E12: =Ind_BS_CF!E9+Ind_BS_CF!E10+Ind_BS_CF!E11-Ind_BS_CF!E5 | F12: =Ind_BS_CF!F9+Ind_BS_CF!F10+Ind_BS_CF!F11-Ind_BS_CF!F5 | G12: =Ind_BS_CF!G9+Ind_BS_CF!G10+Ind_BS_CF!G11-Ind_BS_CF!G5
A13: ── 现金流量表（间接法）──
A14: 净利润 | C14: =Ind_IS!C18 | D14: =Ind_IS!D18 | E14: =Ind_IS!E18 | F14: =Ind_IS!F18 | G14: =Ind_IS!G18
A15: 减：应收增加 | C15: =-(Ind_BS_CF!C5-(0)) | D15: =-(Ind_BS_CF!D5-(Ind_BS_CF!C5)) | E15: =-(Ind_BS_CF!E5-(Ind_BS_CF!D5)) | F15: =-(Ind_BS_CF!F5-(Ind_BS_CF!E5)) | G15: =-(Ind_BS_CF!G5-(Ind_BS_CF!F5))
A16: 内部往来净变动 | C16: =(Ind_BS_CF!C6-(0)) | D16: =(Ind_BS_CF!D6-(Ind_BS_CF!C6)) | E16: =(Ind_BS_CF!E6-(Ind_BS_CF!D6)) | F16: =(Ind_BS_CF!F6-(Ind_BS_CF!E6)) | G16: =(Ind_BS_CF!G6-(Ind_BS_CF!F6))
A17: 加：递延增加 | C17: =Ind_BS_CF!C8-(0) | D17: =Ind_BS_CF!D8-(Ind_BS_CF!C8) | E17: =Ind_BS_CF!E8-(Ind_BS_CF!D8) | F17: =Ind_BS_CF!F8-(Ind_BS_CF!E8) | G17: =Ind_BS_CF!G8-(Ind_BS_CF!F8)
A18: 加：应付增加 | C18: =Ind_BS_CF!C7-(0) | D18: =Ind_BS_CF!D7-(Ind_BS_CF!C7) | E18: =Ind_BS_CF!E7-(Ind_BS_CF!D7) | F18: =Ind_BS_CF!F7-(Ind_BS_CF!E7) | G18: =Ind_BS_CF!G7-(Ind_BS_CF!F7)
A19: 经营现金流 | C19: =Ind_BS_CF!C14+Ind_BS_CF!C15+Ind_BS_CF!C16+Ind_BS_CF!C17+Ind_BS_CF!C18 | D19: =Ind_BS_CF!D14+Ind_BS_CF!D15+Ind_BS_CF!D16+Ind_BS_CF!D17+Ind_BS_CF!D18 | E19: =Ind_BS_CF!E14+Ind_BS_CF!E15+Ind_BS_CF!E16+Ind_BS_CF!E17+Ind_BS_CF!E18 | F19: =Ind_BS_CF!F14+Ind_BS_CF!F15+Ind_BS_CF!F16+Ind_BS_CF!F17+Ind_BS_CF!F18 | G19: =Ind_BS_CF!G14+Ind_BS_CF!G15+Ind_BS_CF!G16+Ind_BS_CF!G17+Ind_BS_CF!G18
A20: 筹资：股权注资 | C20: =Assumptions!C58 | D20: =Assumptions!D58 | E20: =Assumptions!E58 | F20: =Assumptions!F58 | G20: =Assumptions!G58
A21: 现金净变动 | C21: =Ind_BS_CF!C19+Ind_BS_CF!C20 | D21: =Ind_BS_CF!D19+Ind_BS_CF!D20 | E21: =Ind_BS_CF!E19+Ind_BS_CF!E20 | F21: =Ind_BS_CF!F19+Ind_BS_CF!F20 | G21: =Ind_BS_CF!G19+Ind_BS_CF!G20
A22: 期末现金（CF） | C22: =14000+Ind_BS_CF!C19+Ind_BS_CF!C20 | D22: =C22+Ind_BS_CF!D19+Ind_BS_CF!D20 | E22: =D22+Ind_BS_CF!E19+Ind_BS_CF!E20 | F22: =E22+Ind_BS_CF!F19+Ind_BS_CF!F20 | G22: =F22+Ind_BS_CF!G19+Ind_BS_CF!G20
A23: ★ CF=BS 差异（应全 0）
A24: CF推导 − BS倒挤 | C24: =Ind_BS_CF!C22-Ind_BS_CF!C12 | D24: =Ind_BS_CF!D22-Ind_BS_CF!D12 | E24: =Ind_BS_CF!E22-Ind_BS_CF!E12 | F24: =Ind_BS_CF!F22-Ind_BS_CF!F12 | G24: =Ind_BS_CF!G22-Ind_BS_CF!G12

Sheet Toc_IS
A1: 智擎互联 · 利润表
A2: 单体 | C端：MAU×转化×ARPPU + 广告 | 万元
A3: 科目（万元） | B3: 备注 | C3: 2023 | D3: 2024 | E3: 2025 | F3: 2026 | G3: 2027
A4: 收入 · C端订阅 | C4: =Assumptions!C31*Assumptions!C32*Assumptions!C33*12 | D4: =Assumptions!D31*Assumptions!D32*Assumptions!D33*12 | E4: =Assumptions!E31*Assumptions!E32*Assumptions!E33*12 | F4: =Assumptions!F31*Assumptions!F32*Assumptions!F33*12 | G4: =Assumptions!G31*Assumptions!G32*Assumptions!G33*12
A5: 收入 · 广告 | C5: =Assumptions!C34 | D5: =Assumptions!D34 | E5: =Assumptions!E34 | F5: =Assumptions!F34 | G5: =Assumptions!G34
A6: 对外收入合计 | C6: =Toc_IS!C4+Toc_IS!C5 | D6: =Toc_IS!D4+Toc_IS!D5 | E6: =Toc_IS!E4+Toc_IS!E5 | F6: =Toc_IS!F4+Toc_IS!F5 | G6: =Toc_IS!G4+Toc_IS!G5
A7: 成本 · 推理+带宽 | B7: 含付云 T3（70%） | C7: =Assumptions!C31*Assumptions!C35*12 | D7: =Assumptions!D31*Assumptions!D35*12 | E7: =Assumptions!E31*Assumptions!E35*12 | F7: =Assumptions!F31*Assumptions!F35*12 | G7: =Assumptions!G31*Assumptions!G35*12
A8: 成本 · T1 license 费 | C8: =Toc_IS!C6*Assumptions!C50 | D8: =Toc_IS!D6*Assumptions!D50 | E8: =Toc_IS!E6*Assumptions!E50 | F8: =Toc_IS!F6*Assumptions!F50 | G8: =Toc_IS!G6*Assumptions!G50
A9: 营业成本合计 | C9: =Toc_IS!C7+Toc_IS!C8 | D9: =Toc_IS!D7+Toc_IS!D8 | E9: =Toc_IS!E7+Toc_IS!E8 | F9: =Toc_IS!F7+Toc_IS!F8 | G9: =Toc_IS!G7+Toc_IS!G8
A10: 毛利润 | C10: =Toc_IS!C6-Toc_IS!C9 | D10: =Toc_IS!D6-Toc_IS!D9 | E10: =Toc_IS!E6-Toc_IS!E9 | F10: =Toc_IS!F6-Toc_IS!F9 | G10: =Toc_IS!G6-Toc_IS!G9
A11: 研发费用 | B11: ×70万 | C11: =Assumptions!C38*70 | D11: =Assumptions!D38*70 | E11: =Assumptions!E38*70 | F11: =Assumptions!F38*70 | G11: =Assumptions!G38*70
A12: 销售费用 · 获客 | B12: 新增用户×CAC | C12: =(Assumptions!C31-0)*Assumptions!C37*Assumptions!C36 | D12: =(Assumptions!D31-Assumptions!C31)*Assumptions!C37*Assumptions!D36 | E12: =(Assumptions!E31-Assumptions!D31)*Assumptions!C37*Assumptions!E36 | F12: =(Assumptions!F31-Assumptions!E31)*Assumptions!C37*Assumptions!F36 | G12: =(Assumptions!G31-Assumptions!F31)*Assumptions!C37*Assumptions!G36
A13: 销售费用合计 | C13: =Toc_IS!C12+Assumptions!C39*55 | D13: =Toc_IS!D12+Assumptions!D39*55 | E13: =Toc_IS!E12+Assumptions!E39*55 | F13: =Toc_IS!F12+Assumptions!F39*55 | G13: =Toc_IS!G12+Assumptions!G39*55
A14: 管理费用 | B14: ×55万 | C14: =Assumptions!C40*55 | D14: =Assumptions!D40*55 | E14: =Assumptions!E40*55 | F14: =Assumptions!F40*55 | G14: =Assumptions!G40*55
A15: EBIT | C15: =Toc_IS!C10-Toc_IS!C11-Toc_IS!C13-Toc_IS!C14 | D15: =Toc_IS!D10-Toc_IS!D11-Toc_IS!D13-Toc_IS!D14 | E15: =Toc_IS!E10-Toc_IS!E11-Toc_IS!E13-Toc_IS!E14 | F15: =Toc_IS!F10-Toc_IS!F11-Toc_IS!F13-Toc_IS!F14 | G15: =Toc_IS!G10-Toc_IS!G11-Toc_IS!G13-Toc_IS!G14
A16: 所得税 | C16: =MAX(0,Toc_IS!C15)*Assumptions!C5 | D16: =MAX(0,Toc_IS!D15)*Assumptions!D5 | E16: =MAX(0,Toc_IS!E15)*Assumptions!E5 | F16: =MAX(0,Toc_IS!F15)*Assumptions!F5 | G16: =MAX(0,Toc_IS!G15)*Assumptions!G5
A17: 净利润 | B17: 归母80% | C17: =Toc_IS!C15-Toc_IS!C16 | D17: =Toc_IS!D15-Toc_IS!D16 | E17: =Toc_IS!E15-Toc_IS!E16 | F17: =Toc_IS!F15-Toc_IS!F16 | G17: =Toc_IS!G15-Toc_IS!G16

Sheet Toc_BS_CF
A1: 智擎互联 · 资产负债表+现金流量表
A2: 单体半厚 | 母公司持股80% | 万元
A3: 科目（万元） | B3: 备注 | C3: 2023 | D3: 2024 | E3: 2025 | F3: 2026 | G3: 2027
A4: ── 资产负债表（关键科目）──
A5: 应收账款 | B5: 广告主账期 | C5: =Toc_IS!C6*Assumptions!C6/365 | D5: =Toc_IS!D6*Assumptions!D6/365 | E5: =Toc_IS!E6*Assumptions!E6/365 | F5: =Toc_IS!F6*Assumptions!F6/365 | G5: =Toc_IS!G6*Assumptions!G6/365
A6: 内部应付（T3+T1） | B6: 含在途，全挂 | C6: =(Assumptions!C31*Assumptions!C35*12*Assumptions!C52+Toc_IS!C8)*Assumptions!C8/365 | D6: =(Assumptions!D31*Assumptions!D35*12*Assumptions!D52+Toc_IS!D8)*Assumptions!D8/365 | E6: =(Assumptions!E31*Assumptions!E35*12*Assumptions!E52+Toc_IS!E8)*Assumptions!E8/365 | F6: =(Assumptions!F31*Assumptions!F35*12*Assumptions!F52+Toc_IS!F8)*Assumptions!F8/365 | G6: =(Assumptions!G31*Assumptions!G35*12*Assumptions!G52+Toc_IS!G8)*Assumptions!G8/365
A7: 应付账款 | C7: =(Toc_IS!C9+Toc_IS!C11+Toc_IS!C13+Toc_IS!C14)*Assumptions!C7/365 | D7: =(Toc_IS!D9+Toc_IS!D11+Toc_IS!D13+Toc_IS!D14)*Assumptions!D7/365 | E7: =(Toc_IS!E9+Toc_IS!E11+Toc_IS!E13+Toc_IS!E14)*Assumptions!E7/365 | F7: =(Toc_IS!F9+Toc_IS!F11+Toc_IS!F13+Toc_IS!F14)*Assumptions!F7/365 | G7: =(Toc_IS!G9+Toc_IS!G11+Toc_IS!G13+Toc_IS!G14)*Assumptions!G7/365
A8: 递延收益 | B8: 订阅年费预收 | C8: =Toc_IS!C4*Assumptions!C79 | D8: =Toc_IS!D4*Assumptions!D79 | E8: =Toc_IS!E4*Assumptions!E79 | F8: =Toc_IS!F4*Assumptions!F79 | G8: =Toc_IS!G4*Assumptions!G79
A9: 负债合计 | C9: =Toc_BS_CF!C7+Toc_BS_CF!C6+Toc_BS_CF!C8 | D9: =Toc_BS_CF!D7+Toc_BS_CF!D6+Toc_BS_CF!D8 | E9: =Toc_BS_CF!E7+Toc_BS_CF!E6+Toc_BS_CF!E8 | F9: =Toc_BS_CF!F7+Toc_BS_CF!F6+Toc_BS_CF!F8 | G9: =Toc_BS_CF!G7+Toc_BS_CF!G6+Toc_BS_CF!G8
A10: 实收资本 | B10: 母80%+战投20% | C10: =Assumptions!C73+Assumptions!C59 | D10: =C10+Assumptions!D59 | E10: =D10+Assumptions!E59 | F10: =E10+Assumptions!F59 | G10: =F10+Assumptions!G59
A11: 未分配利润 | C11: =Assumptions!C72+Toc_IS!C17 | D11: =C11+Toc_IS!D17 | E11: =D11+Toc_IS!E17 | F11: =E11+Toc_IS!F17 | G11: =F11+Toc_IS!G17
A12: 货币资金（倒挤） | C12: =Toc_BS_CF!C9+Toc_BS_CF!C10+Toc_BS_CF!C11-Toc_BS_CF!C5 | D12: =Toc_BS_CF!D9+Toc_BS_CF!D10+Toc_BS_CF!D11-Toc_BS_CF!D5 | E12: =Toc_BS_CF!E9+Toc_BS_CF!E10+Toc_BS_CF!E11-Toc_BS_CF!E5 | F12: =Toc_BS_CF!F9+Toc_BS_CF!F10+Toc_BS_CF!F11-Toc_BS_CF!F5 | G12: =Toc_BS_CF!G9+Toc_BS_CF!G10+Toc_BS_CF!G11-Toc_BS_CF!G5
A13: ── 现金流量表（间接法）──
A14: 净利润 | C14: =Toc_IS!C17 | D14: =Toc_IS!D17 | E14: =Toc_IS!E17 | F14: =Toc_IS!F17 | G14: =Toc_IS!G17
A15: 减：应收增加 | C15: =-(Toc_BS_CF!C5-(0)) | D15: =-(Toc_BS_CF!D5-(Toc_BS_CF!C5)) | E15: =-(Toc_BS_CF!E5-(Toc_BS_CF!D5)) | F15: =-(Toc_BS_CF!F5-(Toc_BS_CF!E5)) | G15: =-(Toc_BS_CF!G5-(Toc_BS_CF!F5))
A16: 内部往来净变动 | C16: =(Toc_BS_CF!C6-(0)) | D16: =(Toc_BS_CF!D6-(Toc_BS_CF!C6)) | E16: =(Toc_BS_CF!E6-(Toc_BS_CF!D6)) | F16: =(Toc_BS_CF!F6-(Toc_BS_CF!E6)) | G16: =(Toc_BS_CF!G6-(Toc_BS_CF!F6))
A17: 加：递延增加 | C17: =Toc_BS_CF!C8-(0) | D17: =Toc_BS_CF!D8-(Toc_BS_CF!C8) | E17: =Toc_BS_CF!E8-(Toc_BS_CF!D8) | F17: =Toc_BS_CF!F8-(Toc_BS_CF!E8) | G17: =Toc_BS_CF!G8-(Toc_BS_CF!F8)
A18: 加：应付增加 | C18: =Toc_BS_CF!C7-(0) | D18: =Toc_BS_CF!D7-(Toc_BS_CF!C7) | E18: =Toc_BS_CF!E7-(Toc_BS_CF!D7) | F18: =Toc_BS_CF!F7-(Toc_BS_CF!E7) | G18: =Toc_BS_CF!G7-(Toc_BS_CF!F7)
A19: 经营现金流 | C19: =Toc_BS_CF!C14+Toc_BS_CF!C15+Toc_BS_CF!C16+Toc_BS_CF!C17+Toc_BS_CF!C18 | D19: =Toc_BS_CF!D14+Toc_BS_CF!D15+Toc_BS_CF!D16+Toc_BS_CF!D17+Toc_BS_CF!D18 | E19: =Toc_BS_CF!E14+Toc_BS_CF!E15+Toc_BS_CF!E16+Toc_BS_CF!E17+Toc_BS_CF!E18 | F19: =Toc_BS_CF!F14+Toc_BS_CF!F15+Toc_BS_CF!F16+Toc_BS_CF!F17+Toc_BS_CF!F18 | G19: =Toc_BS_CF!G14+Toc_BS_CF!G15+Toc_BS_CF!G16+Toc_BS_CF!G17+Toc_BS_CF!G18
A20: 筹资：股权注资（含战投） | C20: =Assumptions!C59 | D20: =Assumptions!D59 | E20: =Assumptions!E59 | F20: =Assumptions!F59 | G20: =Assumptions!G59
A21: 现金净变动 | C21: =Toc_BS_CF!C19+Toc_BS_CF!C20 | D21: =Toc_BS_CF!D19+Toc_BS_CF!D20 | E21: =Toc_BS_CF!E19+Toc_BS_CF!E20 | F21: =Toc_BS_CF!F19+Toc_BS_CF!F20 | G21: =Toc_BS_CF!G19+Toc_BS_CF!G20
A22: 期末现金（CF） | C22: =7000+Toc_BS_CF!C19+Toc_BS_CF!C20 | D22: =C22+Toc_BS_CF!D19+Toc_BS_CF!D20 | E22: =D22+Toc_BS_CF!E19+Toc_BS_CF!E20 | F22: =E22+Toc_BS_CF!F19+Toc_BS_CF!F20 | G22: =F22+Toc_BS_CF!G19+Toc_BS_CF!G20
A23: ★ CF=BS 差异（应全 0）
A24: CF推导 − BS倒挤 | C24: =Toc_BS_CF!C22-Toc_BS_CF!C12 | D24: =Toc_BS_CF!D22-Toc_BS_CF!D12 | E24: =Toc_BS_CF!E22-Toc_BS_CF!E12 | F24: =Toc_BS_CF!F22-Toc_BS_CF!F12 | G24: =Toc_BS_CF!G22-Toc_BS_CF!G12

Sheet HoldCo_IS
A1: 智擎研究院 · 利润表
A2: 单体 | 全关联收入，无对外收入 | 万元
A3: 科目（万元） | B3: 备注 | C3: 2023 | D3: 2024 | E3: 2025 | F3: 2026 | G3: 2027
A4: 关联收入 · T1 模型 license | B4: 三家子公司对外收入×费率 | C4: =Cloud_IS!C4*Assumptions!C48+Ind_IS!C6*Assumptions!C49+Toc_IS!C6*Assumptions!C50 | D4: =Cloud_IS!D4*Assumptions!D48+Ind_IS!D6*Assumptions!D49+Toc_IS!D6*Assumptions!D50 | E4: =Cloud_IS!E4*Assumptions!E48+Ind_IS!E6*Assumptions!E49+Toc_IS!E6*Assumptions!E50 | F4: =Cloud_IS!F4*Assumptions!F48+Ind_IS!F6*Assumptions!F49+Toc_IS!F6*Assumptions!F50 | G4: =Cloud_IS!G4*Assumptions!G48+Ind_IS!G6*Assumptions!G49+Toc_IS!G6*Assumptions!G50
A5: 关联收入 · T2 定制研发服务 | B5: 行业子公司 | C5: =Assumptions!C51 | D5: =Assumptions!D51 | E5: =Assumptions!E51 | F5: =Assumptions!F51 | G5: =Assumptions!G51
A6: 营业收入合计 | C6: =HoldCo_IS!C4+HoldCo_IS!C5 | D6: =HoldCo_IS!D4+HoldCo_IS!D5 | E6: =HoldCo_IS!E4+HoldCo_IS!E5 | F6: =HoldCo_IS!F4+HoldCo_IS!F5 | G6: =HoldCo_IS!G4+HoldCo_IS!G5
A7: 营业成本 | B7: 研究院无直接 COGS | C7: 0 | D7: 0 | E7: 0 | F7: 0 | G7: 0
A8: 毛利润 | C8: =HoldCo_IS!C6-HoldCo_IS!C7 | D8: =HoldCo_IS!D6-HoldCo_IS!D7 | E8: =HoldCo_IS!E6-HoldCo_IS!E7 | F8: =HoldCo_IS!F6-HoldCo_IS!F7 | G8: =HoldCo_IS!G6-HoldCo_IS!G7
A9: 研发费用 | B9: 编制+训练折旧+其他 | C9: =Assumptions!C42*Assumptions!C43+Capex_Dep!C22+Assumptions!C44 | D9: =Assumptions!D42*Assumptions!D43+Capex_Dep!D22+Assumptions!D44 | E9: =Assumptions!E42*Assumptions!E43+Capex_Dep!E22+Assumptions!E44 | F9: =Assumptions!F42*Assumptions!F43+Capex_Dep!F22+Assumptions!F44 | G9: =Assumptions!G42*Assumptions!G43+Capex_Dep!G22+Assumptions!G44
A10: 销售费用 | C10: 0 | D10: 0 | E10: 0 | F10: 0 | G10: 0
A11: 管理费用 | C11: =Assumptions!C45*Assumptions!C46 | D11: =Assumptions!D45*Assumptions!D46 | E11: =Assumptions!E45*Assumptions!E46 | F11: =Assumptions!F45*Assumptions!F46 | G11: =Assumptions!G45*Assumptions!G46
A12: EBIT | C12: =HoldCo_IS!C8-HoldCo_IS!C9-HoldCo_IS!C10-HoldCo_IS!C11 | D12: =HoldCo_IS!D8-HoldCo_IS!D9-HoldCo_IS!D10-HoldCo_IS!D11 | E12: =HoldCo_IS!E8-HoldCo_IS!E9-HoldCo_IS!E10-HoldCo_IS!E11 | F12: =HoldCo_IS!F8-HoldCo_IS!F9-HoldCo_IS!F10-HoldCo_IS!F11 | G12: =HoldCo_IS!G8-HoldCo_IS!G9-HoldCo_IS!G10-HoldCo_IS!G11
A13: 所得税（亏损不确认） | C13: =MAX(0,HoldCo_IS!C12)*Assumptions!C5 | D13: =MAX(0,HoldCo_IS!D12)*Assumptions!D5 | E13: =MAX(0,HoldCo_IS!E12)*Assumptions!E5 | F13: =MAX(0,HoldCo_IS!F12)*Assumptions!F5 | G13: =MAX(0,HoldCo_IS!G12)*Assumptions!G5
A14: 净利润 | C14: =HoldCo_IS!C12-HoldCo_IS!C13 | D14: =HoldCo_IS!D12-HoldCo_IS!D13 | E14: =HoldCo_IS!E12-HoldCo_IS!E13 | F14: =HoldCo_IS!F12-HoldCo_IS!F13 | G14: =HoldCo_IS!G12-HoldCo_IS!G13

Sheet HoldCo_BS
A1: 智擎研究院 · 资产负债表
A2: 单体 | 现金=倒挤项 → 结构性平衡 | 万元
A3: 科目（万元） | B3: 备注 | C3: 2023 | D3: 2024 | E3: 2025 | F3: 2026 | G3: 2027
A4: 应收账款 | B4: 无对外收入，应收为 0 | C4: 0 | D4: 0 | E4: 0 | F4: 0 | G4: 0
A5: 内部应收（关联往来） | B5: T1+T2 × 60天 | C5: =(HoldCo_IS!C4+HoldCo_IS!C5)*Assumptions!C8/365 | D5: =(HoldCo_IS!D4+HoldCo_IS!D5)*Assumptions!D8/365 | E5: =(HoldCo_IS!E4+HoldCo_IS!E5)*Assumptions!E8/365 | F5: =(HoldCo_IS!F4+HoldCo_IS!F5)*Assumptions!F8/365 | G5: =(HoldCo_IS!G4+HoldCo_IS!G5)*Assumptions!G8/365
A6: 固定资产 · GPU 净值 | B6: 训练算力 | C6: =Capex_Dep!C23 | D6: =Capex_Dep!D23 | E6: =Capex_Dep!E23 | F6: =Capex_Dep!F23 | G6: =Capex_Dep!G23
A7: 长期股权投资 | B7: 成本法：期初+对子公司注资 | C7: =Assumptions!C76+(Assumptions!C57+Assumptions!C58+Assumptions!C59*0.8) | D7: =C7+(Assumptions!D57+Assumptions!D58+Assumptions!D59*0.8) | E7: =D7+(Assumptions!E57+Assumptions!E58+Assumptions!E59*0.8) | F7: =E7+(Assumptions!F57+Assumptions!F58+Assumptions!F59*0.8) | G7: =F7+(Assumptions!G57+Assumptions!G58+Assumptions!G59*0.8)
A8: 非现金资产合计 | B8: （辅助行） | C8: =HoldCo_BS!C4+HoldCo_BS!C5+HoldCo_BS!C6+HoldCo_BS!C7 | D8: =HoldCo_BS!D4+HoldCo_BS!D5+HoldCo_BS!D6+HoldCo_BS!D7 | E8: =HoldCo_BS!E4+HoldCo_BS!E5+HoldCo_BS!E6+HoldCo_BS!E7 | F8: =HoldCo_BS!F4+HoldCo_BS!F5+HoldCo_BS!F6+HoldCo_BS!F7 | G8: =HoldCo_BS!G4+HoldCo_BS!G5+HoldCo_BS!G6+HoldCo_BS!G7
A10: 应付账款 | B10: 现金成本×DPO | C10: =(HoldCo_IS!C7+HoldCo_IS!C9+HoldCo_IS!C10+HoldCo_IS!C11-Capex_Dep!C22)*Assumptions!C7/365 | D10: =(HoldCo_IS!D7+HoldCo_IS!D9+HoldCo_IS!D10+HoldCo_IS!D11-Capex_Dep!D22)*Assumptions!D7/365 | E10: =(HoldCo_IS!E7+HoldCo_IS!E9+HoldCo_IS!E10+HoldCo_IS!E11-Capex_Dep!E22)*Assumptions!E7/365 | F10: =(HoldCo_IS!F7+HoldCo_IS!F9+HoldCo_IS!F10+HoldCo_IS!F11-Capex_Dep!F22)*Assumptions!F7/365 | G10: =(HoldCo_IS!G7+HoldCo_IS!G9+HoldCo_IS!G10+HoldCo_IS!G11-Capex_Dep!G22)*Assumptions!G7/365
A11: 内部应付 | C11: 0 | D11: 0 | E11: 0 | F11: 0 | G11: 0
A12: 递延收益 | C12: 0 | D12: 0 | E12: 0 | F12: 0 | G12: 0
A13: 负债合计 | C13: =HoldCo_BS!C10+HoldCo_BS!C11+HoldCo_BS!C12 | D13: =HoldCo_BS!D10+HoldCo_BS!D11+HoldCo_BS!D12 | E13: =HoldCo_BS!E10+HoldCo_BS!E11+HoldCo_BS!E12 | F13: =HoldCo_BS!F10+HoldCo_BS!F11+HoldCo_BS!F12 | G13: =HoldCo_BS!G10+HoldCo_BS!G11+HoldCo_BS!G12
A14: 实收资本 | C14: =Assumptions!C67+Assumptions!C56 | D14: =C14+Assumptions!D56 | E14: =D14+Assumptions!E56 | F14: =E14+Assumptions!F56 | G14: =F14+Assumptions!G56
A15: 未分配利润 | B15: 期初+NI，无分红 | C15: =Assumptions!C66+HoldCo_IS!C14 | D15: =C15+HoldCo_IS!D14 | E15: =D15+HoldCo_IS!E14 | F15: =E15+HoldCo_IS!F14 | G15: =F15+HoldCo_IS!G14
A16: 所有者权益合计 | C16: =HoldCo_BS!C14+HoldCo_BS!C15 | D16: =HoldCo_BS!D14+HoldCo_BS!D15 | E16: =HoldCo_BS!E14+HoldCo_BS!E15 | F16: =HoldCo_BS!F14+HoldCo_BS!F15 | G16: =HoldCo_BS!G14+HoldCo_BS!G15
A17: 负债+权益合计 | C17: =HoldCo_BS!C13+HoldCo_BS!C16 | D17: =HoldCo_BS!D13+HoldCo_BS!D16 | E17: =HoldCo_BS!E13+HoldCo_BS!E16 | F17: =HoldCo_BS!F13+HoldCo_BS!F16 | G17: =HoldCo_BS!G13+HoldCo_BS!G16
A18: 货币资金（倒挤） | B18: 负债+权益−非现金资产 | C18: =HoldCo_BS!C17-HoldCo_BS!C8 | D18: =HoldCo_BS!D17-HoldCo_BS!D8 | E18: =HoldCo_BS!E17-HoldCo_BS!E8 | F18: =HoldCo_BS!F17-HoldCo_BS!F8 | G18: =HoldCo_BS!G17-HoldCo_BS!G8
A19: 资产总计 | C19: =HoldCo_BS!C18+HoldCo_BS!C8 | D19: =HoldCo_BS!D18+HoldCo_BS!D8 | E19: =HoldCo_BS!E18+HoldCo_BS!E8 | F19: =HoldCo_BS!F18+HoldCo_BS!F8 | G19: =HoldCo_BS!G18+HoldCo_BS!G8
A20: ★ BS 平衡差（应全 0）
A21: 资产 − 负债 − 权益 | C21: =HoldCo_BS!C19-HoldCo_BS!C17 | D21: =HoldCo_BS!D19-HoldCo_BS!D17 | E21: =HoldCo_BS!E19-HoldCo_BS!E17 | F21: =HoldCo_BS!F19-HoldCo_BS!F17 | G21: =HoldCo_BS!G19-HoldCo_BS!G17

Sheet HoldCo_CF
A1: 智擎研究院 · 现金流量表（间接法）
A2: 单体 | 独立推导期末现金，与 BS 倒挤现金互为勾稽 | 万元
A3: 科目（万元） | B3: 备注 | C3: 2023 | D3: 2024 | E3: 2025 | F3: 2026 | G3: 2027
A4: 净利润 | C4: =HoldCo_IS!C14 | D4: =HoldCo_IS!D14 | E4: =HoldCo_IS!E14 | F4: =HoldCo_IS!F14 | G4: =HoldCo_IS!G14
A5: 加：折旧摊销 | C5: =Capex_Dep!C22 | D5: =Capex_Dep!D22 | E5: =Capex_Dep!E22 | F5: =Capex_Dep!F22 | G5: =Capex_Dep!G22
A6: 减：应收账款增加 | C6: =-(HoldCo_BS!C4-(0)) | D6: =-(HoldCo_BS!D4-(HoldCo_BS!C4)) | E6: =-(HoldCo_BS!E4-(HoldCo_BS!D4)) | F6: =-(HoldCo_BS!F4-(HoldCo_BS!E4)) | G6: =-(HoldCo_BS!G4-(HoldCo_BS!F4))
A7: 内部往来净变动 | B7: Δ应付−Δ应收 | C7: =(HoldCo_BS!C11-(0))-(HoldCo_BS!C5-(0)) | D7: =(HoldCo_BS!D11-(HoldCo_BS!C11))-(HoldCo_BS!D5-(HoldCo_BS!C5)) | E7: =(HoldCo_BS!E11-(HoldCo_BS!D11))-(HoldCo_BS!E5-(HoldCo_BS!D5)) | F7: =(HoldCo_BS!F11-(HoldCo_BS!E11))-(HoldCo_BS!F5-(HoldCo_BS!E5)) | G7: =(HoldCo_BS!G11-(HoldCo_BS!F11))-(HoldCo_BS!G5-(HoldCo_BS!F5))
A8: 加：递延收益增加 | C8: =HoldCo_BS!C12-(0) | D8: =HoldCo_BS!D12-(HoldCo_BS!C12) | E8: =HoldCo_BS!E12-(HoldCo_BS!D12) | F8: =HoldCo_BS!F12-(HoldCo_BS!E12) | G8: =HoldCo_BS!G12-(HoldCo_BS!F12)
A9: 加：应付账款增加 | C9: =HoldCo_BS!C10-(0) | D9: =HoldCo_BS!D10-(HoldCo_BS!C10) | E9: =HoldCo_BS!E10-(HoldCo_BS!D10) | F9: =HoldCo_BS!F10-(HoldCo_BS!E10) | G9: =HoldCo_BS!G10-(HoldCo_BS!F10)
A10: 经营活动现金流净额 | C10: =HoldCo_CF!C4+HoldCo_CF!C5+HoldCo_CF!C6+HoldCo_CF!C7+HoldCo_CF!C8+HoldCo_CF!C9 | D10: =HoldCo_CF!D4+HoldCo_CF!D5+HoldCo_CF!D6+HoldCo_CF!D7+HoldCo_CF!D8+HoldCo_CF!D9 | E10: =HoldCo_CF!E4+HoldCo_CF!E5+HoldCo_CF!E6+HoldCo_CF!E7+HoldCo_CF!E8+HoldCo_CF!E9 | F10: =HoldCo_CF!F4+HoldCo_CF!F5+HoldCo_CF!F6+HoldCo_CF!F7+HoldCo_CF!F8+HoldCo_CF!F9 | G10: =HoldCo_CF!G4+HoldCo_CF!G5+HoldCo_CF!G6+HoldCo_CF!G7+HoldCo_CF!G8+HoldCo_CF!G9
A11: 购建固定资产 | C11: =-Capex_Dep!C5 | D11: =-Capex_Dep!D5 | E11: =-Capex_Dep!E5 | F11: =-Capex_Dep!F5 | G11: =-Capex_Dep!G5
A12: 对子公司增资 | B12: 长投增加 | C12: =-(Assumptions!C57+Assumptions!C58+Assumptions!C59*0.8) | D12: =-(Assumptions!D57+Assumptions!D58+Assumptions!D59*0.8) | E12: =-(Assumptions!E57+Assumptions!E58+Assumptions!E59*0.8) | F12: =-(Assumptions!F57+Assumptions!F58+Assumptions!F59*0.8) | G12: =-(Assumptions!G57+Assumptions!G58+Assumptions!G59*0.8)
A13: 投资活动现金流净额 | C13: =HoldCo_CF!C11+HoldCo_CF!C12 | D13: =HoldCo_CF!D11+HoldCo_CF!D12 | E13: =HoldCo_CF!E11+HoldCo_CF!E12 | F13: =HoldCo_CF!F11+HoldCo_CF!F12 | G13: =HoldCo_CF!G11+HoldCo_CF!G12
A14: 筹资：股权注资 | C14: =Assumptions!C56 | D14: =Assumptions!D56 | E14: =Assumptions!E56 | F14: =Assumptions!F56 | G14: =Assumptions!G56
A15: 现金净变动 | C15: =HoldCo_CF!C10+HoldCo_CF!C13+HoldCo_CF!C14 | D15: =HoldCo_CF!D10+HoldCo_CF!D13+HoldCo_CF!D14 | E15: =HoldCo_CF!E10+HoldCo_CF!E13+HoldCo_CF!E14 | F15: =HoldCo_CF!F10+HoldCo_CF!F13+HoldCo_CF!F14 | G15: =HoldCo_CF!G10+HoldCo_CF!G13+HoldCo_CF!G14
A16: 期末现金（CF 推导） | C16: =37000+HoldCo_CF!C15 | D16: =C16+HoldCo_CF!D15 | E16: =D16+HoldCo_CF!E15 | F16: =E16+HoldCo_CF!F15 | G16: =F16+HoldCo_CF!G15
A17: 期末现金（BS 倒挤） | C17: =HoldCo_BS!C18 | D17: =HoldCo_BS!D18 | E17: =HoldCo_BS!E18 | F17: =HoldCo_BS!F18 | G17: =HoldCo_BS!G18
A18: ★ CF=BS 现金差异（应全 0）
A19: CF推导 − BS倒挤 | C19: =HoldCo_CF!C16-HoldCo_CF!C17 | D19: =HoldCo_CF!D16-HoldCo_CF!D17 | E19: =HoldCo_CF!E16-HoldCo_CF!E17 | F19: =HoldCo_CF!F16-HoldCo_CF!F17 | G19: =HoldCo_CF!G16-HoldCo_CF!G17

Sheet IC_Register
A1: 内部交易登记簿
A2: 四类关联交易 · 金额公式全链接单体表 | 万元
A3: 科目（万元） | B3: 备注 | C3: 2023 | D3: 2024 | E3: 2025 | F3: 2026 | G3: 2027
A4: ── 当年交易额 ──
A5: T1 license · 研究院 → 智擎云 | C5: =Cloud_IS!C4*Assumptions!C48 | D5: =Cloud_IS!D4*Assumptions!D48 | E5: =Cloud_IS!E4*Assumptions!E48 | F5: =Cloud_IS!F4*Assumptions!F48 | G5: =Cloud_IS!G4*Assumptions!G48
A6: T1 license · 研究院 → 智擎行业 | C6: =Ind_IS!C6*Assumptions!C49 | D6: =Ind_IS!D6*Assumptions!D49 | E6: =Ind_IS!E6*Assumptions!E49 | F6: =Ind_IS!F6*Assumptions!F49 | G6: =Ind_IS!G6*Assumptions!G49
A7: T1 license · 研究院 → 智擎互联 | C7: =Toc_IS!C6*Assumptions!C50 | D7: =Toc_IS!D6*Assumptions!D50 | E7: =Toc_IS!E6*Assumptions!E50 | F7: =Toc_IS!F6*Assumptions!F50 | G7: =Toc_IS!G6*Assumptions!G50
A8: T2 定制研发 · 研究院 → 智擎行业 | C8: =Assumptions!C51 | D8: =Assumptions!D51 | E8: =Assumptions!E51 | F8: =Assumptions!F51 | G8: =Assumptions!G51
A9: T3 算力服务 · 智擎云 → 智擎互联 | C9: =Assumptions!C31*Assumptions!C35*12*Assumptions!C52 | D9: =Assumptions!D31*Assumptions!D35*12*Assumptions!D52 | E9: =Assumptions!E31*Assumptions!E35*12*Assumptions!E52 | F9: =Assumptions!F31*Assumptions!F35*12*Assumptions!F52 | G9: =Assumptions!G31*Assumptions!G35*12*Assumptions!G52
A10: 关联交易合计 | C10: =SUM(IC_Register!C5,IC_Register!C6,IC_Register!C7,IC_Register!C8,IC_Register!C9) | D10: =SUM(IC_Register!D5,IC_Register!D6,IC_Register!D7,IC_Register!D8,IC_Register!D9) | E10: =SUM(IC_Register!E5,IC_Register!E6,IC_Register!E7,IC_Register!E8,IC_Register!E9) | F10: =SUM(IC_Register!F5,IC_Register!F6,IC_Register!F7,IC_Register!F8,IC_Register!F9) | G10: =SUM(IC_Register!G5,IC_Register!G6,IC_Register!G7,IC_Register!G8,IC_Register!G9)
A11: ── 期末往来余额（账期60天挂账）──
A12: 研究院 应收三家（借方） | C12: =(IC_Register!C5+IC_Register!C6+IC_Register!C7+IC_Register!C8)*Assumptions!C8/365 | D12: =(IC_Register!D5+IC_Register!D6+IC_Register!D7+IC_Register!D8)*Assumptions!D8/365 | E12: =(IC_Register!E5+IC_Register!E6+IC_Register!E7+IC_Register!E8)*Assumptions!E8/365 | F12: =(IC_Register!F5+IC_Register!F6+IC_Register!F7+IC_Register!F8)*Assumptions!F8/365 | G12: =(IC_Register!G5+IC_Register!G6+IC_Register!G7+IC_Register!G8)*Assumptions!G8/365
A13: 智擎云 应收互联（T3） | B13: 2027 未含未开票 220 | C13: =IC_Register!C9*Assumptions!C8/365 | D13: =IC_Register!D9*Assumptions!D8/365 | E13: =IC_Register!E9*Assumptions!E8/365 | F13: =IC_Register!F9*Assumptions!F8/365 | G13: =IC_Register!G9*Assumptions!G8/365-Assumptions!G54
A14: 智擎云 应付研究院（T1） | C14: =IC_Register!C5*Assumptions!C8/365 | D14: =IC_Register!D5*Assumptions!D8/365 | E14: =IC_Register!E5*Assumptions!E8/365 | F14: =IC_Register!F5*Assumptions!F8/365 | G14: =IC_Register!G5*Assumptions!G8/365
A15: 智擎行业 应付研究院（T1+T2） | C15: =(IC_Register!C6+IC_Register!C8)*Assumptions!C8/365 | D15: =(IC_Register!D6+IC_Register!D8)*Assumptions!D8/365 | E15: =(IC_Register!E6+IC_Register!E8)*Assumptions!E8/365 | F15: =(IC_Register!F6+IC_Register!F8)*Assumptions!F8/365 | G15: =(IC_Register!G6+IC_Register!G8)*Assumptions!G8/365
A16: 智擎互联 应付（T3+T1，含在途） | C16: =(IC_Register!C9+IC_Register!C7)*Assumptions!C8/365 | D16: =(IC_Register!D9+IC_Register!D7)*Assumptions!D8/365 | E16: =(IC_Register!E9+IC_Register!E7)*Assumptions!E8/365 | F16: =(IC_Register!F9+IC_Register!F7)*Assumptions!F8/365 | G16: =(IC_Register!G9+IC_Register!G7)*Assumptions!G8/365
A17: 内部应收合计 | C17: =IC_Register!C12+IC_Register!C13 | D17: =IC_Register!D12+IC_Register!D13 | E17: =IC_Register!E12+IC_Register!E13 | F17: =IC_Register!F12+IC_Register!F13 | G17: =IC_Register!G12+IC_Register!G13
A18: 内部应付合计 | C18: =IC_Register!C14+IC_Register!C15+IC_Register!C16 | D18: =IC_Register!D14+IC_Register!D15+IC_Register!D16 | E18: =IC_Register!E14+IC_Register!E15+IC_Register!E16 | F18: =IC_Register!F14+IC_Register!F15+IC_Register!F16 | G18: =IC_Register!G14+IC_Register!G15+IC_Register!G16

Sheet IC_Recon
A1: 关联方对账矩阵 · 双边核对 + 在途调节
A2: 差异可见 → 调节 → 归零 | 万元
A3: 科目（万元） | B3: 备注 | C3: 2023 | D3: 2024 | E3: 2025 | F3: 2026 | G3: 2027
A4: ── 双边核对（A 账上应收 B vs B 账上应付 A）──
A5: 研究院 ↔ 智擎云：研究院应收 | C5: =IC_Register!C5*Assumptions!C8/365 | D5: =IC_Register!D5*Assumptions!D8/365 | E5: =IC_Register!E5*Assumptions!E8/365 | F5: =IC_Register!F5*Assumptions!F8/365 | G5: =IC_Register!G5*Assumptions!G8/365
A6: 研究院 ↔ 智擎云：云应付 | C6: =IC_Register!C14 | D6: =IC_Register!D14 | E6: =IC_Register!E14 | F6: =IC_Register!F14 | G6: =IC_Register!G14
A7: 差异 | C7: =IC_Recon!C5-IC_Recon!C6 | D7: =IC_Recon!D5-IC_Recon!D6 | E7: =IC_Recon!E5-IC_Recon!E6 | F7: =IC_Recon!F5-IC_Recon!F6 | G7: =IC_Recon!G5-IC_Recon!G6
A9: 研究院 ↔ 智擎行业：研究院应收 | C9: =(IC_Register!C6+IC_Register!C8)*Assumptions!C8/365 | D9: =(IC_Register!D6+IC_Register!D8)*Assumptions!D8/365 | E9: =(IC_Register!E6+IC_Register!E8)*Assumptions!E8/365 | F9: =(IC_Register!F6+IC_Register!F8)*Assumptions!F8/365 | G9: =(IC_Register!G6+IC_Register!G8)*Assumptions!G8/365
A10: 研究院 ↔ 智擎行业：行业应付 | C10: =IC_Register!C15 | D10: =IC_Register!D15 | E10: =IC_Register!E15 | F10: =IC_Register!F15 | G10: =IC_Register!G15
A11: 差异 | C11: =IC_Recon!C9-IC_Recon!C10 | D11: =IC_Recon!D9-IC_Recon!D10 | E11: =IC_Recon!E9-IC_Recon!E10 | F11: =IC_Recon!F9-IC_Recon!F10 | G11: =IC_Recon!G9-IC_Recon!G10
A13: 研究院 ↔ 智擎互联：研究院应收 | C13: =IC_Register!C7*Assumptions!C8/365 | D13: =IC_Register!D7*Assumptions!D8/365 | E13: =IC_Register!E7*Assumptions!E8/365 | F13: =IC_Register!F7*Assumptions!F8/365 | G13: =IC_Register!G7*Assumptions!G8/365
A14: 研究院 ↔ 智擎互联：互联应付（T1部分） | C14: =IC_Register!C7*Assumptions!C8/365 | D14: =IC_Register!D7*Assumptions!D8/365 | E14: =IC_Register!E7*Assumptions!E8/365 | F14: =IC_Register!F7*Assumptions!F8/365 | G14: =IC_Register!G7*Assumptions!G8/365
A15: 差异 | C15: =IC_Recon!C13-IC_Recon!C14 | D15: =IC_Recon!D13-IC_Recon!D14 | E15: =IC_Recon!E13-IC_Recon!E14 | F15: =IC_Recon!F13-IC_Recon!F14 | G15: =IC_Recon!G13-IC_Recon!G14
A17: 智擎云 ↔ 智擎互联：云应收（未开票−220） | C17: =IC_Register!C13 | D17: =IC_Register!D13 | E17: =IC_Register!E13 | F17: =IC_Register!F13 | G17: =IC_Register!G13
A18: 智擎云 ↔ 智擎互联：互联应付（全额挂账） | C18: =IC_Register!C9*Assumptions!C8/365 | D18: =IC_Register!D9*Assumptions!D8/365 | E18: =IC_Register!E9*Assumptions!E8/365 | F18: =IC_Register!F9*Assumptions!F8/365 | G18: =IC_Register!G9*Assumptions!G8/365
A19: 差异（2027 = 在途 220） | C19: =IC_Recon!C17-IC_Recon!C18 | D19: =IC_Recon!D17-IC_Recon!D18 | E19: =IC_Recon!E17-IC_Recon!E18 | F19: =IC_Recon!F17-IC_Recon!F18 | G19: =IC_Recon!G17-IC_Recon!G18
A20: ── 在途调节表（cut-off：互联12月已确认，云次年1月开票）──
A21: 调节前差异 | C21: =IC_Recon!C19 | D21: =IC_Recon!D19 | E21: =IC_Recon!E19 | F21: =IC_Recon!F19 | G21: =IC_Recon!G19
A22: 加：云未开票在途服务 | B22: 服务已提供、发票在途 | C22: 0 | D22: 0 | E22: 0 | F22: 0 | G22: =Assumptions!G54
A23: 调节后差异（应全 0） | C23: =IC_Recon!C21+IC_Recon!C22 | D23: =IC_Recon!D21+IC_Recon!D22 | E23: =IC_Recon!E21+IC_Recon!E22 | F23: =IC_Recon!F21+IC_Recon!F22 | G23: =IC_Recon!G21+IC_Recon!G22
A25: 合并抵消口径（双边孰低=调节后应收方） | B25: Eliminations E2 引用此行 | C25: =IC_Recon!C17+IC_Recon!C22 | D25: =IC_Recon!D17+IC_Recon!D22 | E25: =IC_Recon!E17+IC_Recon!E22 | F25: =IC_Recon!F17+IC_Recon!F22 | G25: =IC_Recon!G17+IC_Recon!G22

Sheet Eliminations
A1: 合并抵消分录底稿
A2: E0 长投×权益 · E1 关联交易 · E2 内部往来 · E3 少数股东 | 万元
A3: 科目（万元） | B3: 备注 | C3: 2023 | D3: 2024 | E3: 2025 | F3: 2026 | G3: 2027
A4: ── E0 长期股权投资 × 子公司权益（母公司份额）──
A5: 借：实收资本 · 智擎云 | C5: =Cloud_BS_CF!C13 | D5: =Cloud_BS_CF!D13 | E5: =Cloud_BS_CF!E13 | F5: =Cloud_BS_CF!F13 | G5: =Cloud_BS_CF!G13
A6: 借：未分配利润 · 智擎云 | C6: =Cloud_BS_CF!C14 | D6: =Cloud_BS_CF!D14 | E6: =Cloud_BS_CF!E14 | F6: =Cloud_BS_CF!F14 | G6: =Cloud_BS_CF!G14
A7: 贷：长投 · 智擎云（成本法） | C7: =10000+SUM(Assumptions!$C57:C57) | D7: =10000+SUM(Assumptions!$C57:D57) | E7: =10000+SUM(Assumptions!$C57:E57) | F7: =10000+SUM(Assumptions!$C57:F57) | G7: =10000+SUM(Assumptions!$C57:G57)
A8: 借：实收资本 · 智擎行业 | C8: =Ind_BS_CF!C10 | D8: =Ind_BS_CF!D10 | E8: =Ind_BS_CF!E10 | F8: =Ind_BS_CF!F10 | G8: =Ind_BS_CF!G10
A9: 借：未分配利润 · 智擎行业 | C9: =Ind_BS_CF!C11 | D9: =Ind_BS_CF!D11 | E9: =Ind_BS_CF!E11 | F9: =Ind_BS_CF!F11 | G9: =Ind_BS_CF!G11
A10: 贷：长投 · 智擎行业（成本法） | C10: =8000+SUM(Assumptions!$C58:C58) | D10: =8000+SUM(Assumptions!$C58:D58) | E10: =8000+SUM(Assumptions!$C58:E58) | F10: =8000+SUM(Assumptions!$C58:F58) | G10: =8000+SUM(Assumptions!$C58:G58)
A11: 借：实收资本 · 智擎互联 | C11: =Toc_BS_CF!C10*0.8 | D11: =Toc_BS_CF!D10*0.8 | E11: =Toc_BS_CF!E10*0.8 | F11: =Toc_BS_CF!F10*0.8 | G11: =Toc_BS_CF!G10*0.8
A12: 借：未分配利润 · 智擎互联 | C12: =Toc_BS_CF!C11*0.8 | D12: =Toc_BS_CF!D11*0.8 | E12: =Toc_BS_CF!E11*0.8 | F12: =Toc_BS_CF!F11*0.8 | G12: =Toc_BS_CF!G11*0.8
A13: 贷：长投 · 智擎互联（成本法） | C13: =5000+SUM(Assumptions!$C59:C59)*0.8 | D13: =5000+SUM(Assumptions!$C59:D59)*0.8 | E13: =5000+SUM(Assumptions!$C59:E59)*0.8 | F13: =5000+SUM(Assumptions!$C59:F59)*0.8 | G13: =5000+SUM(Assumptions!$C59:G59)*0.8
A14: E0 差额 → 合并资本公积（Σ借−Σ贷） | C14: =Eliminations!C5+Eliminations!C6-Eliminations!C7+Eliminations!C8+Eliminations!C9-Eliminations!C10+Eliminations!C11+Eliminations!C12-Eliminations!C13 | D14: =Eliminations!D5+Eliminations!D6-Eliminations!D7+Eliminations!D8+Eliminations!D9-Eliminations!D10+Eliminations!D11+Eliminations!D12-Eliminations!D13 | E14: =Eliminations!E5+Eliminations!E6-Eliminations!E7+Eliminations!E8+Eliminations!E9-Eliminations!E10+Eliminations!E11+Eliminations!E12-Eliminations!E13 | F14: =Eliminations!F5+Eliminations!F6-Eliminations!F7+Eliminations!F8+Eliminations!F9-Eliminations!F10+Eliminations!F11+Eliminations!F12-Eliminations!F13 | G14: =Eliminations!G5+Eliminations!G6-Eliminations!G7+Eliminations!G8+Eliminations!G9-Eliminations!G10+Eliminations!G11+Eliminations!G12-Eliminations!G13
A15: ── E1 关联收入 × 关联成本对冲 ──
A16: 借：关联收入 / 贷：关联成本（全额） | C16: =IC_Register!C10 | D16: =IC_Register!D10 | E16: =IC_Register!E10 | F16: =IC_Register!F10 | G16: =IC_Register!G10
A17: ── E2 内部往来对冲（双边孰低=调节后）──
A18: 借：内部应付合计 | C18: =IC_Register!C18 | D18: =IC_Register!D18 | E18: =IC_Register!E18 | F18: =IC_Register!F18 | G18: =IC_Register!G18
A19: 贷：内部应收合计（孰低=ΣAR） | C19: =IC_Register!C17 | D19: =IC_Register!D17 | E19: =IC_Register!E17 | F19: =IC_Register!F17 | G19: =IC_Register!G17
A20: 差额 → 其他应付款·内部在途（=ΣAP−ΣAR） | B20: cut-off 在途挂账 | C20: =Eliminations!C18-Eliminations!C19 | D20: =Eliminations!D18-Eliminations!D19 | E20: =Eliminations!E18-Eliminations!E19 | F20: =Eliminations!F18-Eliminations!F19 | G20: =Eliminations!G18-Eliminations!G19
A21: ── E3 少数股东（利润拆分，非借贷）──
A22: 少数股东损益 = 互联 NI × 20% | C22: =Toc_IS!C17*0.2 | D22: =Toc_IS!D17*0.2 | E22: =Toc_IS!E17*0.2 | F22: =Toc_IS!F17*0.2 | G22: =Toc_IS!G17*0.2
A23: 少数股东权益 = 互联净资产 × 20% | C23: =(Toc_BS_CF!C10+Toc_BS_CF!C11)*0.2 | D23: =(Toc_BS_CF!D10+Toc_BS_CF!D11)*0.2 | E23: =(Toc_BS_CF!E10+Toc_BS_CF!E11)*0.2 | F23: =(Toc_BS_CF!F10+Toc_BS_CF!F11)*0.2 | G23: =(Toc_BS_CF!G10+Toc_BS_CF!G11)*0.2

Sheet Consol_IS
A1: 智擎集团 · 合并利润表
A2: Σ四主体 − E1 关联对冲 − E3 归属拆分 | 万元
A3: 科目（万元） | B3: 备注 | C3: 2023 | D3: 2024 | E3: 2025 | F3: 2026 | G3: 2027
A4: 对外收入合计（云+行业+互联） | C4: =Cloud_IS!C4+Ind_IS!C6+Toc_IS!C6 | D4: =Cloud_IS!D4+Ind_IS!D6+Toc_IS!D6 | E4: =Cloud_IS!E4+Ind_IS!E6+Toc_IS!E6 | F4: =Cloud_IS!F4+Ind_IS!F6+Toc_IS!F6 | G4: =Cloud_IS!G4+Ind_IS!G6+Toc_IS!G6
A5: 减：关联收入抵消（E1） | B5: T1+T2+T3 全消 | C5: =-Eliminations!C16 | D5: =-Eliminations!D16 | E5: =-Eliminations!E16 | F5: =-Eliminations!F16 | G5: =-Eliminations!G16
A6: 合并营业收入 | C6: =Consol_IS!C4 | D6: =Consol_IS!D4 | E6: =Consol_IS!E4 | F6: =Consol_IS!F4 | G6: =Consol_IS!G4
A7: Σ四主体营业成本 | C7: =HoldCo_IS!C7+Cloud_IS!C11+Ind_IS!C11+Toc_IS!C9 | D7: =HoldCo_IS!D7+Cloud_IS!D11+Ind_IS!D11+Toc_IS!D9 | E7: =HoldCo_IS!E7+Cloud_IS!E11+Ind_IS!E11+Toc_IS!E9 | F7: =HoldCo_IS!F7+Cloud_IS!F11+Ind_IS!F11+Toc_IS!F9 | G7: =HoldCo_IS!G7+Cloud_IS!G11+Ind_IS!G11+Toc_IS!G9
A8: 减：关联成本对冲（E1） | B8: 含保留云真实服务成本，净效应=−0.45×T3 | C8: =-Eliminations!C16 | D8: =-Eliminations!D16 | E8: =-Eliminations!E16 | F8: =-Eliminations!F16 | G8: =-Eliminations!G16
A9: 合并营业成本 | C9: =Consol_IS!C7+Consol_IS!C8 | D9: =Consol_IS!D7+Consol_IS!D8 | E9: =Consol_IS!E7+Consol_IS!E8 | F9: =Consol_IS!F7+Consol_IS!F8 | G9: =Consol_IS!G7+Consol_IS!G8
A10: 合并毛利润 | C10: =Consol_IS!C6-Consol_IS!C9 | D10: =Consol_IS!D6-Consol_IS!D9 | E10: =Consol_IS!E6-Consol_IS!E9 | F10: =Consol_IS!F6-Consol_IS!F9 | G10: =Consol_IS!G6-Consol_IS!G9
A11: 研发费用 | C11: =Cloud_IS!C13+Ind_IS!C13+Toc_IS!C11+HoldCo_IS!C9 | D11: =Cloud_IS!D13+Ind_IS!D13+Toc_IS!D11+HoldCo_IS!D9 | E11: =Cloud_IS!E13+Ind_IS!E13+Toc_IS!E11+HoldCo_IS!E9 | F11: =Cloud_IS!F13+Ind_IS!F13+Toc_IS!F11+HoldCo_IS!F9 | G11: =Cloud_IS!G13+Ind_IS!G13+Toc_IS!G11+HoldCo_IS!G9
A12: 销售费用 | C12: =Cloud_IS!C14+Ind_IS!C14+Toc_IS!C13+HoldCo_IS!C10 | D12: =Cloud_IS!D14+Ind_IS!D14+Toc_IS!D13+HoldCo_IS!D10 | E12: =Cloud_IS!E14+Ind_IS!E14+Toc_IS!E13+HoldCo_IS!E10 | F12: =Cloud_IS!F14+Ind_IS!F14+Toc_IS!F13+HoldCo_IS!F10 | G12: =Cloud_IS!G14+Ind_IS!G14+Toc_IS!G13+HoldCo_IS!G10
A13: 管理费用 | C13: =Cloud_IS!C15+Ind_IS!C15+Toc_IS!C14+HoldCo_IS!C11 | D13: =Cloud_IS!D15+Ind_IS!D15+Toc_IS!D14+HoldCo_IS!D11 | E13: =Cloud_IS!E15+Ind_IS!E15+Toc_IS!E14+HoldCo_IS!E11 | F13: =Cloud_IS!F15+Ind_IS!F15+Toc_IS!F14+HoldCo_IS!F11 | G13: =Cloud_IS!G15+Ind_IS!G15+Toc_IS!G14+HoldCo_IS!G11
A14: 合并 EBIT | C14: =Consol_IS!C10-Consol_IS!C11-Consol_IS!C12-Consol_IS!C13 | D14: =Consol_IS!D10-Consol_IS!D11-Consol_IS!D12-Consol_IS!D13 | E14: =Consol_IS!E10-Consol_IS!E11-Consol_IS!E12-Consol_IS!E13 | F14: =Consol_IS!F10-Consol_IS!F11-Consol_IS!F12-Consol_IS!F13 | G14: =Consol_IS!G10-Consol_IS!G11-Consol_IS!G12-Consol_IS!G13
A15: 所得税（Σ） | C15: =Cloud_IS!C17+Ind_IS!C17+Toc_IS!C16+HoldCo_IS!C13 | D15: =Cloud_IS!D17+Ind_IS!D17+Toc_IS!D16+HoldCo_IS!D13 | E15: =Cloud_IS!E17+Ind_IS!E17+Toc_IS!E16+HoldCo_IS!E13 | F15: =Cloud_IS!F17+Ind_IS!F17+Toc_IS!F16+HoldCo_IS!F13 | G15: =Cloud_IS!G17+Ind_IS!G17+Toc_IS!G16+HoldCo_IS!G13
A16: 合并净利润 | C16: =Consol_IS!C14-Consol_IS!C15 | D16: =Consol_IS!D14-Consol_IS!D15 | E16: =Consol_IS!E14-Consol_IS!E15 | F16: =Consol_IS!F14-Consol_IS!F15 | G16: =Consol_IS!G14-Consol_IS!G15
A17: 少数股东损益（E3） | C17: =Eliminations!C22 | D17: =Eliminations!D22 | E17: =Eliminations!E22 | F17: =Eliminations!F22 | G17: =Eliminations!G22
A18: 归属于母公司净利润 | C18: =Consol_IS!C16-Consol_IS!C17 | D18: =Consol_IS!D16-Consol_IS!D17 | E18: =Consol_IS!E16-Consol_IS!E17 | F18: =Consol_IS!F16-Consol_IS!F17 | G18: =Consol_IS!G16-Consol_IS!G17

Sheet Consol_BS
A1: 智擎集团 · 合并资产负债表
A2: Σ四主体 − E0 − E2 + 少数股东权益 | 万元
A3: 科目（万元） | B3: 备注 | C3: 2023 | D3: 2024 | E3: 2025 | F3: 2026 | G3: 2027
A4: 货币资金 | C4: =HoldCo_BS!C18+Cloud_BS_CF!C15+Ind_BS_CF!C12+Toc_BS_CF!C12 | D4: =HoldCo_BS!D18+Cloud_BS_CF!D15+Ind_BS_CF!D12+Toc_BS_CF!D12 | E4: =HoldCo_BS!E18+Cloud_BS_CF!E15+Ind_BS_CF!E12+Toc_BS_CF!E12 | F4: =HoldCo_BS!F18+Cloud_BS_CF!F15+Ind_BS_CF!F12+Toc_BS_CF!F12 | G4: =HoldCo_BS!G18+Cloud_BS_CF!G15+Ind_BS_CF!G12+Toc_BS_CF!G12
A5: 应收账款 | C5: =HoldCo_BS!C4+Cloud_BS_CF!C5+Ind_BS_CF!C5+Toc_BS_CF!C5 | D5: =HoldCo_BS!D4+Cloud_BS_CF!D5+Ind_BS_CF!D5+Toc_BS_CF!D5 | E5: =HoldCo_BS!E4+Cloud_BS_CF!E5+Ind_BS_CF!E5+Toc_BS_CF!E5 | F5: =HoldCo_BS!F4+Cloud_BS_CF!F5+Ind_BS_CF!F5+Toc_BS_CF!F5 | G5: =HoldCo_BS!G4+Cloud_BS_CF!G5+Ind_BS_CF!G5+Toc_BS_CF!G5
A6: 固定资产 · GPU 净值 | C6: =HoldCo_BS!C6+Cloud_BS_CF!C7 | D6: =HoldCo_BS!D6+Cloud_BS_CF!D7 | E6: =HoldCo_BS!E6+Cloud_BS_CF!E7 | F6: =HoldCo_BS!F6+Cloud_BS_CF!F7 | G6: =HoldCo_BS!G6+Cloud_BS_CF!G7
A7: 内部应收（抵消后 0） | C7: =HoldCo_BS!C5+Cloud_BS_CF!C6-Eliminations!C19 | D7: =HoldCo_BS!D5+Cloud_BS_CF!D6-Eliminations!D19 | E7: =HoldCo_BS!E5+Cloud_BS_CF!E6-Eliminations!E19 | F7: =HoldCo_BS!F5+Cloud_BS_CF!F6-Eliminations!F19 | G7: =HoldCo_BS!G5+Cloud_BS_CF!G6-Eliminations!G19
A8: 长期股权投资（抵消后 0） | C8: =HoldCo_BS!C7-Eliminations!C7-Eliminations!C10-Eliminations!C13 | D8: =HoldCo_BS!D7-Eliminations!D7-Eliminations!D10-Eliminations!D13 | E8: =HoldCo_BS!E7-Eliminations!E7-Eliminations!E10-Eliminations!E13 | F8: =HoldCo_BS!F7-Eliminations!F7-Eliminations!F10-Eliminations!F13 | G8: =HoldCo_BS!G7-Eliminations!G7-Eliminations!G10-Eliminations!G13
A9: 资产总计 | C9: =Consol_BS!C4+Consol_BS!C5+Consol_BS!C6 | D9: =Consol_BS!D4+Consol_BS!D5+Consol_BS!D6 | E9: =Consol_BS!E4+Consol_BS!E5+Consol_BS!E6 | F9: =Consol_BS!F4+Consol_BS!F5+Consol_BS!F6 | G9: =Consol_BS!G4+Consol_BS!G5+Consol_BS!G6
A11: 应付账款 | C11: =HoldCo_BS!C10+Cloud_BS_CF!C9+Ind_BS_CF!C7+Toc_BS_CF!C7 | D11: =HoldCo_BS!D10+Cloud_BS_CF!D9+Ind_BS_CF!D7+Toc_BS_CF!D7 | E11: =HoldCo_BS!E10+Cloud_BS_CF!E9+Ind_BS_CF!E7+Toc_BS_CF!E7 | F11: =HoldCo_BS!F10+Cloud_BS_CF!F9+Ind_BS_CF!F7+Toc_BS_CF!F7 | G11: =HoldCo_BS!G10+Cloud_BS_CF!G9+Ind_BS_CF!G7+Toc_BS_CF!G7
A12: 递延收益 | C12: =HoldCo_BS!C12+Cloud_BS_CF!C11+Ind_BS_CF!C8+Toc_BS_CF!C8 | D12: =HoldCo_BS!D12+Cloud_BS_CF!D11+Ind_BS_CF!D8+Toc_BS_CF!D8 | E12: =HoldCo_BS!E12+Cloud_BS_CF!E11+Ind_BS_CF!E8+Toc_BS_CF!E8 | F12: =HoldCo_BS!F12+Cloud_BS_CF!F11+Ind_BS_CF!F8+Toc_BS_CF!F8 | G12: =HoldCo_BS!G12+Cloud_BS_CF!G11+Ind_BS_CF!G8+Toc_BS_CF!G8
A13: 内部应付（抵消后=在途差额） | B13: 按双边孰低抵消，剩余挂 other_pay | C13: =HoldCo_BS!C11+Cloud_BS_CF!C10+Ind_BS_CF!C6+Toc_BS_CF!C6-Eliminations!C19 | D13: =HoldCo_BS!D11+Cloud_BS_CF!D10+Ind_BS_CF!D6+Toc_BS_CF!D6-Eliminations!D19 | E13: =HoldCo_BS!E11+Cloud_BS_CF!E10+Ind_BS_CF!E6+Toc_BS_CF!E6-Eliminations!E19 | F13: =HoldCo_BS!F11+Cloud_BS_CF!F10+Ind_BS_CF!F6+Toc_BS_CF!F6-Eliminations!F19 | G13: =HoldCo_BS!G11+Cloud_BS_CF!G10+Ind_BS_CF!G6+Toc_BS_CF!G6-Eliminations!G19
A14: 其他应付款 · 内部在途 | C14: =Eliminations!C20 | D14: =Eliminations!D20 | E14: =Eliminations!E20 | F14: =Eliminations!F20 | G14: =Eliminations!G20
A15: 负债合计 | C15: =Consol_BS!C11+Consol_BS!C12+Consol_BS!C14 | D15: =Consol_BS!D11+Consol_BS!D12+Consol_BS!D14 | E15: =Consol_BS!E11+Consol_BS!E12+Consol_BS!E14 | F15: =Consol_BS!F11+Consol_BS!F12+Consol_BS!F14 | G15: =Consol_BS!G11+Consol_BS!G12+Consol_BS!G14
A16: 实收资本（研究院口径） | B16: 子公司全抵 | C16: =HoldCo_BS!C14 | D16: =HoldCo_BS!D14 | E16: =HoldCo_BS!E14 | F16: =HoldCo_BS!F14 | G16: =HoldCo_BS!G14
A17: 合并调整 · 资本公积（E0 差额） | C17: =Eliminations!C14 | D17: =Eliminations!D14 | E17: =Eliminations!E14 | F17: =Eliminations!F14 | G17: =Eliminations!G14
A18: 未分配利润（研究院口径） | C18: =HoldCo_BS!C15 | D18: =HoldCo_BS!D15 | E18: =HoldCo_BS!E15 | F18: =HoldCo_BS!F15 | G18: =HoldCo_BS!G15
A19: 少数股东权益（E3） | C19: =Eliminations!C23 | D19: =Eliminations!D23 | E19: =Eliminations!E23 | F19: =Eliminations!F23 | G19: =Eliminations!G23
A20: 合并所有者权益合计 | C20: =Consol_BS!C16+Consol_BS!C17+Consol_BS!C18+Consol_BS!C19 | D20: =Consol_BS!D16+Consol_BS!D17+Consol_BS!D18+Consol_BS!D19 | E20: =Consol_BS!E16+Consol_BS!E17+Consol_BS!E18+Consol_BS!E19 | F20: =Consol_BS!F16+Consol_BS!F17+Consol_BS!F18+Consol_BS!F19 | G20: =Consol_BS!G16+Consol_BS!G17+Consol_BS!G18+Consol_BS!G19
A21: 负债+权益合计 | C21: =Consol_BS!C15+Consol_BS!C20 | D21: =Consol_BS!D15+Consol_BS!D20 | E21: =Consol_BS!E15+Consol_BS!E20 | F21: =Consol_BS!F15+Consol_BS!F20 | G21: =Consol_BS!G15+Consol_BS!G20
A22: ★ 合并 BS 平衡差（应全 0）
A23: 资产 − 负债 − 权益 | C23: =Consol_BS!C9-Consol_BS!C21 | D23: =Consol_BS!D9-Consol_BS!D21 | E23: =Consol_BS!E9-Consol_BS!E21 | F23: =Consol_BS!F9-Consol_BS!F21 | G23: =Consol_BS!G9-Consol_BS!G21

Sheet Consol_CF
A1: 智擎集团 · 合并现金流量表（间接法）
A2: 合并 NI+D&A+ΔWC；内部结算不出合并范围自动消失 | 万元
A3: 科目（万元） | B3: 备注 | C3: 2023 | D3: 2024 | E3: 2025 | F3: 2026 | G3: 2027
A4: 合并净利润 | C4: =Consol_IS!C16 | D4: =Consol_IS!D16 | E4: =Consol_IS!E16 | F4: =Consol_IS!F16 | G4: =Consol_IS!G16
A5: 加：折旧（训练+推理） | C5: =Capex_Dep!C22+Capex_Dep!C24 | D5: =Capex_Dep!D22+Capex_Dep!D24 | E5: =Capex_Dep!E22+Capex_Dep!E24 | F5: =Capex_Dep!F22+Capex_Dep!F24 | G5: =Capex_Dep!G22+Capex_Dep!G24
A6: 减：应收增加 | C6: =-(Consol_BS!C5-(0)) | D6: =-(Consol_BS!D5-(Consol_BS!C5)) | E6: =-(Consol_BS!E5-(Consol_BS!D5)) | F6: =-(Consol_BS!F5-(Consol_BS!E5)) | G6: =-(Consol_BS!G5-(Consol_BS!F5))
A7: 加：递延增加 | C7: =Consol_BS!C12-(0) | D7: =Consol_BS!D12-(Consol_BS!C12) | E7: =Consol_BS!E12-(Consol_BS!D12) | F7: =Consol_BS!F12-(Consol_BS!E12) | G7: =Consol_BS!G12-(Consol_BS!F12)
A8: 加：应付增加 | C8: =Consol_BS!C11-(0) | D8: =Consol_BS!D11-(Consol_BS!C11) | E8: =Consol_BS!E11-(Consol_BS!D11) | F8: =Consol_BS!F11-(Consol_BS!E11) | G8: =Consol_BS!G11-(Consol_BS!F11)
A9: 加：在途挂账变动 | B9: 非现金 | C9: =Consol_BS!C14-(0) | D9: =Consol_BS!D14-(Consol_BS!C14) | E9: =Consol_BS!E14-(Consol_BS!D14) | F9: =Consol_BS!F14-(Consol_BS!E14) | G9: =Consol_BS!G14-(Consol_BS!F14)
A10: 经营活动现金流 | C10: =Consol_CF!C4+Consol_CF!C5+Consol_CF!C6+Consol_CF!C7+Consol_CF!C8+Consol_CF!C9 | D10: =Consol_CF!D4+Consol_CF!D5+Consol_CF!D6+Consol_CF!D7+Consol_CF!D8+Consol_CF!D9 | E10: =Consol_CF!E4+Consol_CF!E5+Consol_CF!E6+Consol_CF!E7+Consol_CF!E8+Consol_CF!E9 | F10: =Consol_CF!F4+Consol_CF!F5+Consol_CF!F6+Consol_CF!F7+Consol_CF!F8+Consol_CF!F9 | G10: =Consol_CF!G4+Consol_CF!G5+Consol_CF!G6+Consol_CF!G7+Consol_CF!G8+Consol_CF!G9
A11: 投资活动现金流 | C11: =-Capex_Dep!C5-Capex_Dep!C6 | D11: =-Capex_Dep!D5-Capex_Dep!D6 | E11: =-Capex_Dep!E5-Capex_Dep!E6 | F11: =-Capex_Dep!F5-Capex_Dep!F6 | G11: =-Capex_Dep!G5-Capex_Dep!G6
A12: 筹资活动（研究院注资+互联战投） | B12: 子公司注资=内部划转，抵消 | C12: =Assumptions!C56+Assumptions!C59*0.2 | D12: =Assumptions!D56+Assumptions!D59*0.2 | E12: =Assumptions!E56+Assumptions!E59*0.2 | F12: =Assumptions!F56+Assumptions!F59*0.2 | G12: =Assumptions!G56+Assumptions!G59*0.2
A13: 现金净变动 | C13: =Consol_CF!C10+Consol_CF!C11+Consol_CF!C12 | D13: =Consol_CF!D10+Consol_CF!D11+Consol_CF!D12 | E13: =Consol_CF!E10+Consol_CF!E11+Consol_CF!E12 | F13: =Consol_CF!F10+Consol_CF!F11+Consol_CF!F12 | G13: =Consol_CF!G10+Consol_CF!G11+Consol_CF!G12
A14: 期末现金（CF 推导） | C14: =68000.00000100001+Consol_CF!C13 | D14: =C14+Consol_CF!D13 | E14: =D14+Consol_CF!E13 | F14: =E14+Consol_CF!F13 | G14: =F14+Consol_CF!G13
A15: 期末现金（Σ单体 BS） | C15: =HoldCo_BS!C18+Cloud_BS_CF!C15+Ind_BS_CF!C12+Toc_BS_CF!C12 | D15: =HoldCo_BS!D18+Cloud_BS_CF!D15+Ind_BS_CF!D12+Toc_BS_CF!D12 | E15: =HoldCo_BS!E18+Cloud_BS_CF!E15+Ind_BS_CF!E12+Toc_BS_CF!E12 | F15: =HoldCo_BS!F18+Cloud_BS_CF!F15+Ind_BS_CF!F12+Toc_BS_CF!F12 | G15: =HoldCo_BS!G18+Cloud_BS_CF!G15+Ind_BS_CF!G12+Toc_BS_CF!G12
A16: ★ 合并 CF=BS 差异（应全 0）
A17: CF推导 − Σ单体现金 | C17: =Consol_CF!C14-Consol_CF!C15 | D17: =Consol_CF!D14-Consol_CF!D15 | E17: =Consol_CF!E14-Consol_CF!E15 | F17: =Consol_CF!F14-Consol_CF!F15 | G17: =Consol_CF!G14-Consol_CF!G15

Sheet FactTable
A1: FactTable · 规范化长表（数据层）
A2: Dashboard 取数源：主体 × 业务线 × 地区 × 年份 × 科目 | 引擎影子值直写（黑字）| 万元
A3: 主体 | B3: 业务线 | C3: 地区 | D3: 年份 | E3: 科目 | F3: 金额
A4: 合并 | B4: MaaS API | C4: 华东 | D4: 2023 | E4: 收入 | F4: 2107.875
A5: 智擎云 | B5: MaaS API | C5: 华东 | D5: 2023 | E5: 收入 | F5: 2107.875
A6: 合并 | B6: MaaS API | C6: 华北 | D6: 2023 | E6: 收入 | F6: 1806.75
A7: 智擎云 | B7: MaaS API | C7: 华北 | D7: 2023 | E7: 收入 | F7: 1806.75
A8: 合并 | B8: MaaS API | C8: 华南 | D8: 2023 | E8: 收入 | F8: 1204.5
A9: 智擎云 | B9: MaaS API | C9: 华南 | D9: 2023 | E9: 收入 | F9: 1204.5
A10: 合并 | B10: MaaS API | C10: 海外 | D10: 2023 | E10: 收入 | F10: 903.375
A11: 智擎云 | B11: MaaS API | C11: 海外 | D11: 2023 | E11: 收入 | F11: 903.375
A12: 合并 | B12: 私有化部署 | C12: 华东 | D12: 2023 | E12: 收入 | F12: 2800
A13: 智擎行业 | B13: 私有化部署 | C13: 华东 | D13: 2023 | E13: 收入 | F13: 2800
A14: 合并 | B14: 私有化部署 | C14: 华北 | D14: 2023 | E14: 收入 | F14: 2400
A15: 智擎行业 | B15: 私有化部署 | C15: 华北 | D15: 2023 | E15: 收入 | F15: 2400
... A523: 合并 | B523: 集团 | C523: 集团 | D523: 2027 | E523: EBITDA | F523: 36200.7

Sheet Dashboard
A1: 集团驾驶舱 Dashboard · 四维联动 | B1: 主体 × 业务线 × 地区 × 期间 下拉联动，SUMIFS 反查 FactTable | 万元
A2: 主体 | B2: * | C2: 业务线 | D2: * | E2: 地区 | F2: * | G2: 期间 | H2: * | I2: “*”=全部
A3: 取数条件（自动生成） | B3: =IF($B$2="*","<>合并",$B$2) | G3: 期间条件 | H3: =IF($H$2="*",">0",$H$2) | I3: 全部主体→<>合并；全部期间→>0
A5: ── 维度联动 · 损益视图（当期合计 · 万元）──
A6: 科目 | B6: 口径 | C6: 金额
A7: 营业收入（对外 · 分业务线/地区） | B7: 主体=全部→Σ四家单体对外收入=合并收入 | C7: =SUMIFS(FactTable!$F:$F,FactTable!$A:$A,$B$3,FactTable!$B:$B,$D$2,FactTable!$C:$C,$F$2,FactTable!$D:$D,$H$3,FactTable!$E:$E,"收入")
A8: 营业成本（分业务线） | B8: 对外成本直加 | C8: =SUMIFS(FactTable!$F:$F,FactTable!$A:$A,$B$3,FactTable!$B:$B,$D$2,FactTable!$C:$C,$F$2,FactTable!$D:$D,$H$3,FactTable!$E:$E,"成本")
A9: 毛利润（维度口径） | B9: 收入−成本 | C9: =C7-C8
A10: 研发费用 | B10: 无业务线/地区拆分 | C10: =SUMIFS(FactTable!$F:$F,FactTable!$A:$A,$B$3,FactTable!$B:$B,$D$2,FactTable!$C:$C,$F$2,FactTable!$D:$D,$H$3,FactTable!$E:$E,"研发费用")
A11: 销售费用 | B11: 无业务线/地区拆分 | C11: =SUMIFS(FactTable!$F:$F,FactTable!$A:$A,$B$3,FactTable!$B:$B,$D$2,FactTable!$C:$C,$F$2,FactTable!$D:$D,$H$3,FactTable!$E:$E,"销售费用")
A12: 管理费用 | B12: 无业务线/地区拆分 | C12: =SUMIFS(FactTable!$F:$F,FactTable!$A:$A,$B$3,FactTable!$B:$B,$D$2,FactTable!$C:$C,$F$2,FactTable!$D:$D,$H$3,FactTable!$E:$E,"管理费用")
A13: EBIT（维度口径） | B13: 毛利−三费 | C13: =C9-C10-C11-C12
A14: 净利润（全量科目） | B14: 只随主体/期间联动；主体=全部→Σ单体=合并 | C14: =SUMIFS(FactTable!$F:$F,FactTable!$A:$A,$B$3,FactTable!$B:$B,$D$2,FactTable!$C:$C,$F$2,FactTable!$D:$D,$H$3,FactTable!$E:$E,"净利润")
A15: EBITDA（全量科目） | B15: 只随主体/期间联动 | C15: =SUMIFS(FactTable!$F:$F,FactTable!$A:$A,$B$3,FactTable!$B:$B,$D$2,FactTable!$C:$C,$F$2,FactTable!$D:$D,$H$3,FactTable!$E:$E,"EBITDA")
A17: ── 比率 ──
A18: 毛利率（维度口径） | C18: =IF(C7=0,0,C9/C7)
A19: 净利率 | C19: =IF(C7=0,0,C14/C7)
A20: EBITDA 率 | C20: =IF(C7=0,0,C15/C7)
A22: 维度适用性说明：BS/CF 科目（净利润/EBITDA/现金/固定资产）无业务线/地区属性，本 Dashboard 只做 IS 维度联动，全量科目仅随主体×期间联动；维度口径为对外收入/成本直加，与合并抵消口径的差异 = 云 T3 内部毛利（0.45×T3，见 Eliminations/IC_Recon）。
A24: ── ★ 反查断言 · FactTable ↔ Consol_IS（不受下拉影响）──
A25: 科目（万元） | C25: 2023 | D25: 2024 | E25: 2025 | F25: 2026 | G25: 2027
A26: 反查 · SUMIFS 全量收入（主体=合并，业务线/地区=*，期间=各年） | B26: 合并粒度行按业务线×地区重建 | C26: =SUMIFS(FactTable!$F:$F,FactTable!$A:$A,"合并",FactTable!$B:$B,"*",FactTable!$C:$C,"*",FactTable!$D:$D,2023,FactTable!$E:$E,"收入") | D26: =SUMIFS(FactTable!$F:$F,FactTable!$A:$A,"合并",FactTable!$B:$B,"*",FactTable!$C:$C,"*",FactTable!$D:$D,2024,FactTable!$E:$E,"收入") | E26: =SUMIFS(FactTable!$F:$F,FactTable!$A:$A,"合并",FactTable!$B:$B,"*",FactTable!$C:$C,"*",FactTable!$D:$D,2025,FactTable!$E:$E,"收入") | F26: =SUMIFS(FactTable!$F:$F,FactTable!$A:$A,"合并",FactTable!$B:$B,"*",FactTable!$C:$C,"*",FactTable!$D:$D,2026,FactTable!$E:$E,"收入") | G26: =SUMIFS(FactTable!$F:$F,FactTable!$A:$A,"合并",FactTable!$B:$B,"*",FactTable!$C:$C,"*",FactTable!$D:$D,2027,FactTable!$E:$E,"收入")
A27: ★ 反查差异 vs Consol_IS!rev（应全 0） | C27: =Dashboard!C26-Consol_IS!C6 | D27: =Dashboard!D26-Consol_IS!D6 | E27: =Dashboard!E26-Consol_IS!E6 | F27: =Dashboard!F26-Consol_IS!F6 | G27: =Dashboard!G26-Consol_IS!G6
A29: ── 5 年趋势 · 合并口径（固定，不受下拉影响）──
A30: 科目（万元） | C30: 2023 | D30: 2024 | E30: 2025 | F30: 2026 | G30: 2027
A31: 合并营业收入 | C31: =Consol_IS!C6 | D31: =Consol_IS!D6 | E31: =Consol_IS!E6 | F31: =Consol_IS!F6 | G31: =Consol_IS!G6
A32: 合并毛利润 | C32: =Consol_IS!C10 | D32: =Consol_IS!D10 | E32: =Consol_IS!E10 | F32: =Consol_IS!F10 | G32: =Consol_IS!G10
A33: 合并净利润 | C33: =Consol_IS!C16 | D33: =Consol_IS!D16 | E33: =Consol_IS!E16 | F33: =Consol_IS!F16 | G33: =Consol_IS!G16
A34: 期末现金 | C34: =Consol_BS!C4 | D34: =Consol_BS!D4 | E34: =Consol_BS!E4 | F34: =Consol_BS!F4 | G34: =Consol_BS!G4

Sheet UE
A1: 单位经济模型 Unit Economics
A2: 上：智擎云 MaaS（token / 客户双视角）· 下：智擎互联 C 端单用户 | 单位见各行标签
A3: 科目（单位见行标签） | B3: 备注 | C3: 2023 | D3: 2024 | E3: 2025 | F3: 2026 | G3: 2027
A4: ── 一、智擎云 MaaS · 单 token 视角（每列=年份）──
A5: 收入单价（元/M tokens） | B5: Assumptions 混合计价 | C5: =Assumptions!C12 | D5: =Assumptions!D12 | E5: =Assumptions!E12 | F5: =Assumptions!F12 | G5: =Assumptions!G12
A6: 推理单位成本（元/M tokens） | B6: 自持+外租算力 | C6: =Assumptions!C13 | D6: =Assumptions!D13 | E6: =Assumptions!E13 | F6: =Assumptions!F13 | G6: =Assumptions!G13
A7: 单 token 毛利（元/M tokens） | B7: 价−成本 | C7: =UE!C5-UE!C6 | D7: =UE!D5-UE!D6 | E7: =UE!E5-UE!E6 | F7: =UE!F5-UE!F6 | G7: =UE!G5-UE!G6
A8: 单 token 毛利率 | B8: 毛利/单价 | C8: =UE!C7/UE!C5 | D8: =UE!D7/UE!D5 | E8: =UE!E7/UE!E5 | F8: =UE!F7/UE!F5 | G8: =UE!G7/UE!G5
A9: ── 剪刀差：成本降幅 vs 价格降幅（累计 vs 2023A）──
A10: 价格累计降幅 | C10: =(UE!C5-UE!C5)/UE!C5 | D10: =(UE!C5-UE!D5)/UE!C5 | E10: =(UE!C5-UE!E5)/UE!C5 | F10: =(UE!C5-UE!F5)/UE!C5 | G10: =(UE!C5-UE!G5)/UE!C5
A11: 单位成本累计降幅 | B11: 成本降得比价格快 | C11: =(UE!C6-UE!C6)/UE!C6 | D11: =(UE!C6-UE!D6)/UE!C6 | E11: =(UE!C6-UE!E6)/UE!C6 | F11: =(UE!C6-UE!F6)/UE!C6 | G11: =(UE!C6-UE!G6)/UE!C6
A12: 剪刀差 = 成本降幅 − 价格降幅 | B12: >0 → 毛利率逐年扩张 | C12: =UE!C11-UE!C10 | D12: =UE!D11-UE!D10 | E12: =UE!E11-UE!E10 | F12: =UE!F11-UE!F10 | G12: =UE!G11-UE!G10
A14: ── 二、智擎云 MaaS · 单客户视角 ──
A15: 付费客户数（家） | C15: =Assumptions!C18 | D15: =Assumptions!D18 | E15: =Assumptions!E18 | F15: =Assumptions!F18 | G15: =Assumptions!G18
A16: ARR / 客户（万元/家） | B16: 对外收入÷客户数 | C16: =Cloud_IS!C4/Assumptions!C18 | D16: =Cloud_IS!D4/Assumptions!D18 | E16: =Cloud_IS!E4/Assumptions!E18 | F16: =Cloud_IS!F4/Assumptions!F18 | G16: =Cloud_IS!G4/Assumptions!G18
A17: 毛利 / 客户（万元/家） | B17: 毛利÷客户数 | C17: =Cloud_IS!C12/Assumptions!C18 | D17: =Cloud_IS!D12/Assumptions!D18 | E17: =Cloud_IS!E12/Assumptions!E18 | F17: =Cloud_IS!F12/Assumptions!F18 | G17: =Cloud_IS!G12/Assumptions!G18
A18: 月流失率 churn（常量） | B18: 1.2%/月 | C18: =Assumptions!C19 | D18: =Assumptions!D19 | E18: =Assumptions!E19 | F18: =Assumptions!F19 | G18: =Assumptions!G19
A19: 平均生命周期（月）= 1/churn | C19: =1/UE!C18 | D19: =1/UE!D18 | E19: =1/UE!E18 | F19: =1/UE!F18 | G19: =1/UE!G18
A20: LTV（万元/客户）= 月毛利 × 生命周期 | B20: 月毛利=毛利/客户/12 | C20: =UE!C17/12*UE!C19 | D20: =UE!D17/12*UE!D19 | E20: =UE!E17/12*UE!E19 | F20: =UE!F17/12*UE!F19 | G20: =UE!G17/12*UE!G19
A21: CAC 获客成本（万元/客户，输入） | B21: 蓝字输入·本表假设 | C21: 3 | D21: 3.5 | E21: 4 | F21: 4.5 | G21: 5
A22: LTV / CAC（倍） | B22: >3x 为健康 | C22: =UE!C20/UE!C21 | D22: =UE!D20/UE!D21 | E22: =UE!E20/UE!E21 | F22: =UE!F20/UE!F21 | G22: =UE!G20/UE!G21
A23: CAC 回收期（月）= CAC / 月毛利 | C23: =UE!C21/(UE!C17/12) | D23: =UE!D21/(UE!D17/12) | E23: =UE!E21/(UE!E17/12) | F23: =UE!F21/(UE!F17/12) | G23: =UE!G21/(UE!G17/12)
A25: ── 三、智擎互联 · C 端单用户 ──
A26: ARPU（元/人/月） | B26: 收入(万)÷MAU(万人)÷12 | C26: =Toc_IS!C6/Assumptions!C31/12 | D26: =Toc_IS!D6/Assumptions!D31/12 | E26: =Toc_IS!E6/Assumptions!E31/12 | F26: =Toc_IS!F6/Assumptions!F31/12 | G26: =Toc_IS!G6/Assumptions!G31/12
A27: 推理+带宽成本（元/人/月） | B27: 含付云 T3 | C27: =Toc_IS!C7/Assumptions!C31/12 | D27: =Toc_IS!D7/Assumptions!D31/12 | E27: =Toc_IS!E7/Assumptions!E31/12 | F27: =Toc_IS!F7/Assumptions!F31/12 | G27: =Toc_IS!G7/Assumptions!G31/12
A28: 单用户月毛利（元/人/月） | B28: ARPU−单位成本 | C28: =UE!C26-UE!C27 | D28: =UE!D26-UE!D27 | E28: =UE!E26-UE!E27 | F28: =UE!F26-UE!F27 | G28: =UE!G26-UE!G27
A29: 获客 CAC（元/新增用户） | C29: =Assumptions!C36 | D29: =Assumptions!D36 | E29: =Assumptions!E36 | F29: =Assumptions!F36 | G29: =Assumptions!G36
A30: 回本周期（月）= CAC / 月毛利 | C30: =UE!C29/UE!C28 | D30: =UE!D29/UE!D28 | E30: =UE!E29/UE!E28 | F30: =UE!F29/UE!F28 | G30: =UE!G29/UE!G28
A31: 订阅收入占比 | C31: =Toc_IS!C4/Toc_IS!C6 | D31: =Toc_IS!D4/Toc_IS!D6 | E31: =Toc_IS!E4/Toc_IS!E6 | F31: =Toc_IS!F4/Toc_IS!F6 | G31: =Toc_IS!G4/Toc_IS!G6
A32: 广告收入占比 | C32: =Toc_IS!C5/Toc_IS!C6 | D32: =Toc_IS!D5/Toc_IS!D6 | E32: =Toc_IS!E5/Toc_IS!E6 | F32: =Toc_IS!F5/Toc_IS!F6 | G32: =Toc_IS!G5/Toc_IS!G6

Sheet ProjectEval
A1: 私有化项目评估 · ProjectEval
A2: 智擎行业 · 3 候选项目：现金流 → NPV@WACC / IRR → P1 敏感性 → 决策 | 蓝字=输入 | 万元
A3: 科目（万元） | B3: 备注 | C3: Y0 | D3: Y1 | E3: Y2 | F3: Y3 | G3: Y4 | H3: Y5
A4: ── 一、项目输入（蓝字=可调，改动联动现金流 / 指标 / 敏感性）──
A5: P1 · 华北某银行 · 风控大模型
A6: 合同额 | B6: 私有化一次性合同 | C6: 1800
A7: 交付年数（年） | B7: 交付期收入按年数均摊 | C7: 2
A8: 交付成本比例（按年，占合同额） | B8: C列=Y1、D列=Y2（P1 两年交付） | C8: 0.55 | D8: 0.25
A9: 运维收入（万/年，交付完成后） | C9: 180
A10: 运维成本率 | C10: 0.4
A11: P2 · 华东某车企 · 智能座舱
A12: 合同额 | B12: 私有化一次性合同 | C12: 1200
A13: 交付年数（年） | B13: 交付期收入按年数均摊 | C13: 1
A14: 交付成本比例（按年，占合同额） | B14: C列=Y1、D列=Y2（P1 两年交付） | C14: 0.65
A15: 运维收入（万/年，交付完成后） | C15: 120
A16: 运维成本率 | C16: 0.35
A17: P3 · 华南某政务 · 热线助手
A18: 合同额 | B18: 私有化一次性合同 | C18: 900
A19: 交付年数（年） | B19: 交付期收入按年数均摊 | C19: 1
A20: 交付成本比例（按年，占合同额） | B20: C列=Y1、D列=Y2（P1 两年交付） | C20: 0.6
A21: 运维收入（万/年，交付完成后） | C21: 150
A22: 运维成本率 | C22: 0.3
A24: ── 二、净现金流（Y0 恒 0；交付期收入=合同额/交付年数、成本=合同额×当年成本比例；交付完成后净额=运维收入×(1−成本率)）──
A25: P1 收入（交付+运维） | B25: 交付期=合同额/交付年数 | C25: 0 | D25: =$C$6/$C$7 | E25: =$C$6/$C$7 | F25: =$C$9 | G25: =$C$9 | H25: =$C$9
A26: P1 成本（交付+运维） | B26: 交付期=合同额×当年成本比例 | C26: 0 | D26: =$C$6*$C$8 | E26: =$C$6*$D$8 | F26: =$C$9*$C$10 | G26: =$C$9*$C$10 | H26: =$C$9*$C$10
A27: P1 净现金流 | B27: 收入−成本 | C27: 0 | D27: =D25-D26 | E27: =E25-E26 | F27: =F25-F26 | G27: =G25-G26 | H27: =H25-H26
A28: P2 收入（交付+运维） | B28: 交付期=合同额/交付年数 | C28: 0 | D28: =$C$12/$C$13 | E28: =$C$15 | F28: =$C$15 | G28: =$C$15 | H28: =$C$15
A29: P2 成本（交付+运维） | B29: 交付期=合同额×当年成本比例 | C29: 0 | D29: =$C$12*$C$14 | E29: =$C$15*$C$16 | F29: =$C$15*$C$16 | G29: =$C$15*$C$16 | H29: =$C$15*$C$16
A30: P2 净现金流 | B30: 收入−成本 | C30: 0 | D30: =D28-D29 | E30: =E28-E29 | F30: =F28-F29 | G30: =G28-G29 | H30: =H28-H29
A31: P3 收入（交付+运维） | B31: 交付期=合同额/交付年数 | C31: 0 | D31: =$C$18/$C$19 | E31: =$C$21 | F31: =$C$21 | G31: =$C$21 | H31: =$C$21
A32: P3 成本（交付+运维） | B32: 交付期=合同额×当年成本比例 | C32: 0 | D32: =$C$18*$C$20 | E32: =$C$21*$C$22 | F32: =$C$21*$C$22 | G32: =$C$21*$C$22 | H32: =$C$21*$C$22
A33: P3 净现金流 | B33: 收入−成本 | C33: 0 | D33: =D31-D32 | E33: =E31-E32 | F33: =F31-F32 | G33: =G31-G32 | H33: =H31-H32
A35: ── 三、指标：NPV@WACC 与 IRR（折现率引用 Assumptions!WACC；NPV 折 Y1-5，IRR 用 Y0-5）──
A36: 项目 | B36: 备注 | C36: NPV@WACC（万） | D36: IRR
A37: P1 华北某银行 · 风控大模型 | B37: 2 年交付 + 运维 | C37: =NPV(Assumptions!C9,D27:H27) | D37: =IFERROR(IRR(C27:H27),"—")
A38: P2 华东某车企 · 智能座舱 | B38: 1 年交付 + 运维 | C38: =NPV(Assumptions!C9,D30:H30) | D38: =IFERROR(IRR(C30:H30),"—")
A39: P3 华南某政务 · 热线助手 | B39: 1 年交付 + 运维 | C39: =NPV(Assumptions!C9,D33:H33) | D39: =IFERROR(IRR(C33:H33),"—")
A41: ── 四、敏感性：P1 NPV（万）＝合同额档位（行）× 交付成本比例档位（列），16 格独立公式重算 ──
A42: 合同额＼交付成本率 | B42: 收入=合同额×行档；成本=合同额×成本比例×列档；运维不变；按 P1 两年交付结构 | C42: 0.8 | D42: 0.9 | E42: 1.1 | F42: 1.2
A43: 0.8 | C43: =NPV(Assumptions!C9,$C$6*$A43/$C$7-$C$6*$C$8*C$42,$C$6*$A43/$C$7-$C$6*$D$8*C$42,$C$9*(1-$C$10),$C$9*(1-$C$10),$C$9*(1-$C$10)) | D43: =NPV(Assumptions!C9,$C$6*$A43/$C$7-$C$6*$C$8*D$42,$C$6*$A43/$C$7-$C$6*$D$8*D$42,$C$9*(1-$C$10),$C$9*(1-$C$10),$C$9*(1-$C$10)) | E43: =NPV(Assumptions!C9,$C$6*$A43/$C$7-$C$6*$C$8*E$42,$C$6*$A43/$C$7-$C$6*$D$8*E$42,$C$9*(1-$C$10),$C$9*(1-$C$10),$C$9*(1-$C$10)) | F43: =NPV(Assumptions!C9,$C$6*$A43/$C$7-$C$6*$C$8*F$42,$C$6*$A43/$C$7-$C$6*$D$8*F$42,$C$9*(1-$C$10),$C$9*(1-$C$10),$C$9*(1-$C$10))
A44: 0.9 | C44: =NPV(Assumptions!C9,$C$6*$A44/$C$7-$C$6*$C$8*C$42,$C$6*$A44/$C$7-$C$6*$D$8*C$42,$C$9*(1-$C$10),$C$9*(1-$C$10),$C$9*(1-$C$10)) | D44: =NPV(Assumptions!C9,$C$6*$A44/$C$7-$C$6*$C$8*D$42,$C$6*$A44/$C$7-$C$6*$D$8*D$42,$C$9*(1-$C$10),$C$9*(1-$C$10),$C$9*(1-$C$10)) | E44: =NPV(Assumptions!C9,$C$6*$A44/$C$7-$C$6*$C$8*E$42,$C$6*$A44/$C$7-$C$6*$D$8*E$42,$C$9*(1-$C$10),$C$9*(1-$C$10),$C$9*(1-$C$10)) | F44: =NPV(Assumptions!C9,$C$6*$A44/$C$7-$C$6*$C$8*F$42,$C$6*$A44/$C$7-$C$6*$D$8*F$42,$C$9*(1-$C$10),$C$9*(1-$C$10),$C$9*(1-$C$10))
A45: 1.1 | C45: =NPV(Assumptions!C9,$C$6*$A45/$C$7-$C$6*$C$8*C$42,$C$6*$A45/$C$7-$C$6*$D$8*C$42,$C$9*(1-$C$10),$C$9*(1-$C$10),$C$9*(1-$C$10)) | D45: =NPV(Assumptions!C9,$C$6*$A45/$C$7-$C$6*$C$8*D$42,$C$6*$A45/$C$7-$C$6*$D$8*D$42,$C$9*(1-$C$10),$C$9*(1-$C$10),$C$9*(1-$C$10)) | E45: =NPV(Assumptions!C9,$C$6*$A45/$C$7-$C$6*$C$8*E$42,$C$6*$A45/$C$7-$C$6*$D$8*E$42,$C$9*(1-$C$10),$C$9*(1-$C$10),$C$9*(1-$C$10)) | F45: =NPV(Assumptions!C9,$C$6*$A45/$C$7-$C$6*$C$8*F$42,$C$6*$A45/$C$7-$C$6*$D$8*F$42,$C$9*(1-$C$10),$C$9*(1-$C$10),$C$9*(1-$C$10))
A46: 1.2 | C46: =NPV(Assumptions!C9,$C$6*$A46/$C$7-$C$6*$C$8*C$42,$C$6*$A46/$C$7-$C$6*$D$8*C$42,$C$9*(1-$C$10),$C$9*(1-$C$10),$C$9*(1-$C$10)) | D46: =NPV(Assumptions!C9,$C$6*$A46/$C$7-$C$6*$C$8*D$42,$C$6*$A46/$C$7-$C$6*$D$8*D$42,$C$9*(1-$C$10),$C$9*(1-$C$10),$C$9*(1-$C$10)) | E46: =NPV(Assumptions!C9,$C$6*$A46/$C$7-$C$6*$C$8*E$42,$C$6*$A46/$C$7-$C$6*$D$8*E$42,$C$9*(1-$C$10),$C$9*(1-$C$10),$C$9*(1-$C$10)) | F46: =NPV(Assumptions!C9,$C$6*$A46/$C$7-$C$6*$C$8*F$42,$C$6*$A46/$C$7-$C$6*$D$8*F$42,$C$9*(1-$C$10),$C$9*(1-$C$10),$C$9*(1-$C$10))
A48: ── 五、决策结论 ──
A49: NPV 排名 | B49: WACC=10% 下 | C49: P3（630 万） ＞ P2（607 万） ＞ P1（512 万）
A50: IRR | B50: 排序以 NPV 为准 | C50: P1 ≈ 428%（首年仅 −90 万净流出，量级高且口径敏感）；P2/P3 全程净流入为正、IRR 无有限解（显示 —），首年即回收
A51: 敏感性（P1） | B51: 16 格公式重算 | C51: 双向 ±20% 压力下 NPV 区间 -55 ～ 1079 万；最差档（合同额×0.8、成本×1.2）转负——该档位即签约防线，需压成本率或抬合同额
A52: 建议 | B52: 结论基于基准输入 | C52: 三项目 NPV 均为正，均可承接；资源受限时优先 P3、P2（交付快、首年回收、运维利润率 70%/65%）；P1 首年净现金流 −90 万，签约应争取预付款/里程碑与成本发生节奏对齐

Sheet Checks
A1: 勾稽自检面板 · 8 组断言
A2: 全部公式实时链接 | 任何一格改坏假设，红灯立刻亮 | 万元
A3: 科目（万元） | B3: 备注 | C3: 2023 | D3: 2024 | E3: 2025 | F3: 2026 | G3: 2027 | I3: 状态
A4: ── C1 各主体资产负债表平衡（资产−负债−权益）──
A5: 智擎研究院 | B5: 倒挤现金=结构性平衡 | C5: =HoldCo_BS!C21 | D5: =HoldCo_BS!D21 | E5: =HoldCo_BS!E21 | F5: =HoldCo_BS!F21 | G5: =HoldCo_BS!G21 | I5: =IF(AND(ABS(C5)<0.01,ABS(D5)<0.01,ABS(E5)<0.01,ABS(F5)<0.01,ABS(G5)<0.01),"✅ PASS","❌ FAIL")
A6: 智擎云 | C6: =Cloud_BS_CF!C12+Cloud_BS_CF!C13+Cloud_BS_CF!C14-Cloud_BS_CF!C8-Cloud_BS_CF!C15 | D6: =Cloud_BS_CF!D12+Cloud_BS_CF!D13+Cloud_BS_CF!D14-Cloud_BS_CF!D8-Cloud_BS_CF!D15 | E6: =Cloud_BS_CF!E12+Cloud_BS_CF!E13+Cloud_BS_CF!E14-Cloud_BS_CF!E8-Cloud_BS_CF!E15 | F6: =Cloud_BS_CF!F12+Cloud_BS_CF!F13+Cloud_BS_CF!F14-Cloud_BS_CF!F8-Cloud_BS_CF!F15 | G6: =Cloud_BS_CF!G12+Cloud_BS_CF!G13+Cloud_BS_CF!G14-Cloud_BS_CF!G8-Cloud_BS_CF!G15 | I6: =IF(AND(ABS(C6)<0.01,ABS(D6)<0.01,ABS(E6)<0.01,ABS(F6)<0.01,ABS(G6)<0.01),"✅ PASS","❌ FAIL")
A7: 智擎行业 | C7: =Ind_BS_CF!C9+Ind_BS_CF!C10+Ind_BS_CF!C11-Ind_BS_CF!C5-Ind_BS_CF!C12 | D7: =Ind_BS_CF!D9+Ind_BS_CF!D10+Ind_BS_CF!D11-Ind_BS_CF!D5-Ind_BS_CF!D12 | E7: =Ind_BS_CF!E9+Ind_BS_CF!E10+Ind_BS_CF!E11-Ind_BS_CF!E5-Ind_BS_CF!E12 | F7: =Ind_BS_CF!F9+Ind_BS_CF!F10+Ind_BS_CF!F11-Ind_BS_CF!F5-Ind_BS_CF!F12 | G7: =Ind_BS_CF!G9+Ind_BS_CF!G10+Ind_BS_CF!G11-Ind_BS_CF!G5-Ind_BS_CF!G12 | I7: =IF(AND(ABS(C7)<0.01,ABS(D7)<0.01,ABS(E7)<0.01,ABS(F7)<0.01,ABS(G7)<0.01),"✅ PASS","❌ FAIL")
A8: 智擎互联 | C8: =Toc_BS_CF!C9+Toc_BS_CF!C10+Toc_BS_CF!C11-Toc_BS_CF!C5-Toc_BS_CF!C12 | D8: =Toc_BS_CF!D9+Toc_BS_CF!D10+Toc_BS_CF!D11-Toc_BS_CF!D5-Toc_BS_CF!D12 | E8: =Toc_BS_CF!E9+Toc_BS_CF!E10+Toc_BS_CF!E11-Toc_BS_CF!E5-Toc_BS_CF!E12 | F8: =Toc_BS_CF!F9+Toc_BS_CF!F10+Toc_BS_CF!F11-Toc_BS_CF!F5-Toc_BS_CF!F12 | G8: =Toc_BS_CF!G9+Toc_BS_CF!G10+Toc_BS_CF!G11-Toc_BS_CF!G5-Toc_BS_CF!G12 | I8: =IF(AND(ABS(C8)<0.01,ABS(D8)<0.01,ABS(E8)<0.01,ABS(F8)<0.01,ABS(G8)<0.01),"✅ PASS","❌ FAIL")
A9: ── C2 现金流量表 = 资产负债表现金（间接法交叉验证）──
A10: 智擎研究院 | C10: =HoldCo_CF!C19 | D10: =HoldCo_CF!D19 | E10: =HoldCo_CF!E19 | F10: =HoldCo_CF!F19 | G10: =HoldCo_CF!G19 | I10: =IF(AND(ABS(C10)<0.01,ABS(D10)<0.01,ABS(E10)<0.01,ABS(F10)<0.01,ABS(G10)<0.01),"✅ PASS","❌ FAIL")
A11: 智擎云 | C11: =Cloud_BS_CF!C29 | D11: =Cloud_BS_CF!D29 | E11: =Cloud_BS_CF!E29 | F11: =Cloud_BS_CF!F29 | G11: =Cloud_BS_CF!G29 | I11: =IF(AND(ABS(C11)<0.01,ABS(D11)<0.01,ABS(E11)<0.01,ABS(F11)<0.01,ABS(G11)<0.01),"✅ PASS","❌ FAIL")
A12: 智擎行业 | C12: =Ind_BS_CF!C24 | D12: =Ind_BS_CF!D24 | E12: =Ind_BS_CF!E24 | F12: =Ind_BS_CF!F24 | G12: =Ind_BS_CF!G24 | I12: =IF(AND(ABS(C12)<0.01,ABS(D12)<0.01,ABS(E12)<0.01,ABS(F12)<0.01,ABS(G12)<0.01),"✅ PASS","❌ FAIL")
A13: 智擎互联 | C13: =Toc_BS_CF!C24 | D13: =Toc_BS_CF!D24 | E13: =Toc_BS_CF!E24 | F13: =Toc_BS_CF!F24 | G13: =Toc_BS_CF!G24 | I13: =IF(AND(ABS(C13)<0.01,ABS(D13)<0.01,ABS(E13)<0.01,ABS(F13)<0.01,ABS(G13)<0.01),"✅ PASS","❌ FAIL")
A14: 合并集团 | C14: =Consol_CF!C17 | D14: =Consol_CF!D17 | E14: =Consol_CF!E17 | F14: =Consol_CF!F17 | G14: =Consol_CF!G17 | I14: =IF(AND(ABS(C14)<0.01,ABS(D14)<0.01,ABS(E14)<0.01,ABS(F14)<0.01,ABS(G14)<0.01),"✅ PASS","❌ FAIL")
A15: ── C3 合并资产负债表平衡 ──
A16: 合并资产 − 负债 − 权益 | C16: =Consol_BS!C23 | D16: =Consol_BS!D23 | E16: =Consol_BS!E23 | F16: =Consol_BS!F23 | G16: =Consol_BS!G23 | I16: =IF(AND(ABS(C16)<0.01,ABS(D16)<0.01,ABS(E16)<0.01,ABS(F16)<0.01,ABS(G16)<0.01),"✅ PASS","❌ FAIL")
A17: ── C4 合并 vs Σ单体 交叉验证（合并−Σ应=0）──
A18: 货币资金 | C18: =Consol_BS!C4-(HoldCo_BS!C18+Cloud_BS_CF!C15+Ind_BS_CF!C12+Toc_BS_CF!C12) | D18: =Consol_BS!D4-(HoldCo_BS!D18+Cloud_BS_CF!D15+Ind_BS_CF!D12+Toc_BS_CF!D12) | E18: =Consol_BS!E4-(HoldCo_BS!E18+Cloud_BS_CF!E15+Ind_BS_CF!E12+Toc_BS_CF!E12) | F18: =Consol_BS!F4-(HoldCo_BS!F18+Cloud_BS_CF!F15+Ind_BS_CF!F12+Toc_BS_CF!F12) | G18: =Consol_BS!G4-(HoldCo_BS!G18+Cloud_BS_CF!G15+Ind_BS_CF!G12+Toc_BS_CF!G12) | I18: =IF(AND(ABS(C18)<0.01,ABS(D18)<0.01,ABS(E18)<0.01,ABS(F18)<0.01,ABS(G18)<0.01),"✅ PASS","❌ FAIL")
A19: 应收账款 | C19: =Consol_BS!C5-(HoldCo_BS!C4+Cloud_BS_CF!C5+Ind_BS_CF!C5+Toc_BS_CF!C5) | D19: =Consol_BS!D5-(HoldCo_BS!D4+Cloud_BS_CF!D5+Ind_BS_CF!D5+Toc_BS_CF!D5) | E19: =Consol_BS!E5-(HoldCo_BS!E4+Cloud_BS_CF!E5+Ind_BS_CF!E5+Toc_BS_CF!E5) | F19: =Consol_BS!F5-(HoldCo_BS!F4+Cloud_BS_CF!F5+Ind_BS_CF!F5+Toc_BS_CF!F5) | G19: =Consol_BS!G5-(HoldCo_BS!G4+Cloud_BS_CF!G5+Ind_BS_CF!G5+Toc_BS_CF!G5) | I19: =IF(AND(ABS(C19)<0.01,ABS(D19)<0.01,ABS(E19)<0.01,ABS(F19)<0.01,ABS(G19)<0.01),"✅ PASS","❌ FAIL")
A20: 净利润 | C20: =Consol_IS!C16-(HoldCo_IS!C14+Cloud_IS!C18+Ind_IS!C18+Toc_IS!C17) | D20: =Consol_IS!D16-(HoldCo_IS!D14+Cloud_IS!D18+Ind_IS!D18+Toc_IS!D17) | E20: =Consol_IS!E16-(HoldCo_IS!E14+Cloud_IS!E18+Ind_IS!E18+Toc_IS!E17) | F20: =Consol_IS!F16-(HoldCo_IS!F14+Cloud_IS!F18+Ind_IS!F18+Toc_IS!F17) | G20: =Consol_IS!G16-(HoldCo_IS!G14+Cloud_IS!G18+Ind_IS!G18+Toc_IS!G17) | I20: =IF(AND(ABS(C20)<0.01,ABS(D20)<0.01,ABS(E20)<0.01,ABS(F20)<0.01,ABS(G20)<0.01),"✅ PASS","❌ FAIL")
A21: ── C5 关联方对账（调节后全 0）──
A22: 研究院 ↔ 智擎云 | C22: =IC_Recon!C7 | D22: =IC_Recon!D7 | E22: =IC_Recon!E7 | F22: =IC_Recon!F7 | G22: =IC_Recon!G7 | I22: =IF(AND(ABS(C22)<0.01,ABS(D22)<0.01,ABS(E22)<0.01,ABS(F22)<0.01,ABS(G22)<0.01),"✅ PASS","❌ FAIL")
A23: 研究院 ↔ 智擎行业 | C23: =IC_Recon!C11 | D23: =IC_Recon!D11 | E23: =IC_Recon!E11 | F23: =IC_Recon!F11 | G23: =IC_Recon!G11 | I23: =IF(AND(ABS(C23)<0.01,ABS(D23)<0.01,ABS(E23)<0.01,ABS(F23)<0.01,ABS(G23)<0.01),"✅ PASS","❌ FAIL")
A24: 研究院 ↔ 智擎互联 | C24: =IC_Recon!C15 | D24: =IC_Recon!D15 | E24: =IC_Recon!E15 | F24: =IC_Recon!F15 | G24: =IC_Recon!G15 | I24: =IF(AND(ABS(C24)<0.01,ABS(D24)<0.01,ABS(E24)<0.01,ABS(F24)<0.01,ABS(G24)<0.01),"✅ PASS","❌ FAIL")
A25: 智擎云 ↔ 智擎互联（在途调节后） | B25: 调节前差异 220 → 调节归零 | C25: =IC_Recon!C23 | D25: =IC_Recon!D23 | E25: =IC_Recon!E23 | F25: =IC_Recon!F23 | G25: =IC_Recon!G23 | I25: =IF(AND(ABS(C25)<0.01,ABS(D25)<0.01,ABS(E25)<0.01,ABS(F25)<0.01,ABS(G25)<0.01),"✅ PASS","❌ FAIL")
A26: ── C7 利润滚动：RE[t] − RE[t−1] = 当年 NI ──
A27: 智擎研究院 | C27: =HoldCo_BS!C15--15000-HoldCo_IS!C14 | D27: =HoldCo_BS!D15-HoldCo_BS!C15-HoldCo_IS!D14 | E27: =HoldCo_BS!E15-HoldCo_BS!D15-HoldCo_IS!E14 | F27: =HoldCo_BS!F15-HoldCo_BS!E15-HoldCo_IS!F14 | G27: =HoldCo_BS!G15-HoldCo_BS!F15-HoldCo_IS!G14 | I27: =IF(AND(ABS(C27)<0.01,ABS(D27)<0.01,ABS(E27)<0.01,ABS(F27)<0.01,ABS(G27)<0.01),"✅ PASS","❌ FAIL")
A28: 智擎云 | C28: =Cloud_BS_CF!C14--8000-Cloud_IS!C18 | D28: =Cloud_BS_CF!D14-Cloud_BS_CF!C14-Cloud_IS!D18 | E28: =Cloud_BS_CF!E14-Cloud_BS_CF!D14-Cloud_IS!E18 | F28: =Cloud_BS_CF!F14-Cloud_BS_CF!E14-Cloud_IS!F18 | G28: =Cloud_BS_CF!G14-Cloud_BS_CF!F14-Cloud_IS!G18 | I28: =IF(AND(ABS(C28)<0.01,ABS(D28)<0.01,ABS(E28)<0.01,ABS(F28)<0.01,ABS(G28)<0.01),"✅ PASS","❌ FAIL")
A29: 智擎行业 | C29: =Ind_BS_CF!C11--4000-Ind_IS!C18 | D29: =Ind_BS_CF!D11-Ind_BS_CF!C11-Ind_IS!D18 | E29: =Ind_BS_CF!E11-Ind_BS_CF!D11-Ind_IS!E18 | F29: =Ind_BS_CF!F11-Ind_BS_CF!E11-Ind_IS!F18 | G29: =Ind_BS_CF!G11-Ind_BS_CF!F11-Ind_IS!G18 | I29: =IF(AND(ABS(C29)<0.01,ABS(D29)<0.01,ABS(E29)<0.01,ABS(F29)<0.01,ABS(G29)<0.01),"✅ PASS","❌ FAIL")
A30: 智擎互联 | C30: =Toc_BS_CF!C11--3000-Toc_IS!C17 | D30: =Toc_BS_CF!D11-Toc_BS_CF!C11-Toc_IS!D17 | E30: =Toc_BS_CF!E11-Toc_BS_CF!D11-Toc_IS!E17 | F30: =Toc_BS_CF!F11-Toc_BS_CF!E11-Toc_IS!F17 | G30: =Toc_BS_CF!G11-Toc_BS_CF!F11-Toc_IS!G17 | I30: =IF(AND(ABS(C30)<0.01,ABS(D30)<0.01,ABS(E30)<0.01,ABS(F30)<0.01,ABS(G30)<0.01),"✅ PASS","❌ FAIL")
A31: ── C8 归母净利润 + 少数股东损益 = 合并净利润 ──
A32: 归属拆分核对 | C32: =Consol_IS!C18+Consol_IS!C17-Consol_IS!C16 | D32: =Consol_IS!D18+Consol_IS!D17-Consol_IS!D16 | E32: =Consol_IS!E18+Consol_IS!E17-Consol_IS!E16 | F32: =Consol_IS!F18+Consol_IS!F17-Consol_IS!F16 | G32: =Consol_IS!G18+Consol_IS!G17-Consol_IS!G16 | I32: =IF(AND(ABS(C32)<0.01,ABS(D32)<0.01,ABS(E32)<0.01,ABS(F32)<0.01,ABS(G32)<0.01),"✅ PASS","❌ FAIL")
A34: 总检灯 | C34: =IF(COUNTIF(I4:I32,"✅ PASS")=22,"🟢 全部通过 — 模型勾稽完整","🔴 存在断言失败，检查上行")
